Workbook

Sheet Cover
B3: IB PORTFOLIO · PROJECT 07 OF 20
B4: Cognizant Technology Solutions
B5: Leveraged Buyout — Debt Schedule and Returns
B6: Jainam Mehta · US$ millions unless stated · as of FY2025 10-K · market data 12 Sep 2026
B9: What this is | C9: A hypothetical take-private of Cognizant Technology Solutions by a financial sponsor, built on the FY2025 10-K and 12 September 2026 market data. Cognizant is used because Projects 3 and 4 already cover IT-services trading multiples and precedent M&A, so the sponsor's view of value can be set beside both.
B11: How it is built | C11: • Sources and uses from an offer premium, with debt sized as a multiple of EBITDA across a term loan and senior notes, and the sponsor equity falling out as the balancing figure.
C12: • A five-year debt schedule with mandatory amortisation and a full cash sweep, interest charged on opening balances so the model never needs iterative calculation switched on.
C13: • Returns by money multiple and IRR, a value-creation bridge splitting the return between debt paydown, EBITDA growth and multiple change, and two live sensitivity grids.
C14: • A solve for the maximum price a sponsor could pay and still clear a 20% return — the LBO floor that belongs on Project 5's football field.
B16: Contents | C16: Summary — the transaction, the return and the maximum price
C17: Sources & Uses — offer, debt quantum, fees and the equity cheque
C18: Model — operating forecast and free cash flow
C19: Debt Schedule — tranches, amortisation, sweep, interest and credit statistics
C20: Returns — exit, MOIC, IRR, value bridge and the hurdle-clearing price
C21: Sensitivity — IRR across premium, exit multiple and leverage
C22: Inputs — standalone financials, deal terms, debt pricing and the operating case
C23: Checks — sixteen tests; must read MODEL OK
B25: Key outputs (live) | C25: Offer price per share (US$) | E25: ='Sources & Uses'!$C$5 -> 81.3605
C26: Entry EV / EBITDA | E26: ='Sources & Uses'!$C$8 -> 9.5806503
C27: Sponsor equity cheque (US$m) | E27: ='Sources & Uses'!$C$24 -> 18924.903
C28: Money multiple | E28: =Returns!$C$12 -> 2.0017797
C29: Internal rate of return | E29: =Returns!$C$13 -> 0.14890271
C30: Maximum price at a 20% return (US$) | E30: =Returns!$C$25 -> 73.777755
B32: Colour code | C32: Blue = hard-coded input
C33: Black = formula
C34: Green = link to another sheet
C35: Accent fill = scenario selector / key levers
B37: Sources | C37: Cognizant Technology Solutions FY2025 Form 10-K (year to 31 December 2025), via the Yahoo Finance fundamentals series for CTSH.
C38: Share price and 52-week range: NASDAQ close, 12 September 2026.
C39: SOFR and US Treasury yields, 12 September 2026.
C40: Debt pricing, fee levels and the operating case are stated assumptions on the Inputs sheet, not quotations from lenders.
C41: The transaction is hypothetical. Nothing here suggests Cognizant is or has been in a sale process.
B43: Prepared by | C43: Jainam Mehta · github.com/jainammehta1215/ib-portfolio

Sheet Inputs
B1: Cognizant Technology Solutions — Leveraged Buyout — Debt Schedule and Returns | F1: IB PORTFOLIO
B2: Standalone financials, deal terms, debt structure and operating case
B4: COGNIZANT — FY2025A (US$m)
B5: Revenue | C5: 21108
B6: EBITDA | C6: 4066
B7: EBIT | C7: 3327
B8: Depreciation and amortisation | C8: 550
B9: Capital expenditure | C9: 288
B10: Total debt | C10: 1152
B11: Cash and equivalents | C11: 1901
B12: Shares outstanding (m) | C12: 488
B13: Share price (US$, 12 Sep 2026) | C13: 62.585
B14: Market capitalisation | C14: =Inputs!$C$13*Inputs!$C$12 -> 30541.48
B15: Net debt / (net cash) | C15: =Inputs!$C$10-Inputs!$C$11 -> -749
B16: Enterprise value, unaffected | C16: =Inputs!$C$14+Inputs!$C$15 -> 29792.48
B17: EV / EBITDA, unaffected | C17: =Inputs!$C$16/Inputs!$C$6 -> 7.3272209 | F17: The sector de-rated through 2026; this is the entry point that makes a take-private arithmetically possible at all
B19: TRANSACTION
B20: Offer premium to unaffected price | C20: 0.3 | F20: Typical control premium for a US public take-private
B21: Minimum cash left in the business | C21: 500
B22: Financing fees as % of debt raised | C22: 0.02 | F22: Underwriting and arrangement; capitalised and amortised over the term
B23: Advisory and other fees as % of transaction value | C23: 0.01 | F23: Sell-side and buy-side advisory, legal, accounting
B24: Cash tax rate | C24: 0.25 | F24: US federal plus state, blended. FY2025 reported rate was distorted by one-off items
B26: DEBT STRUCTURE
B27: Term Loan B (x EBITDA) | C27: 3
B28: Senior notes (x EBITDA) | C28: 2.25
B29: SOFR | C29: 0.0395 | F29: Three-month rate, 12 Sep 2026
B30: Term Loan B spread over SOFR | C30: 0.035
B31: Senior notes coupon (fixed) | C31: 0.085
B32: Term Loan B mandatory amortisation (% of original, per year) | C32: 0.01
B33: Cash sweep — % of free cash flow applied to debt | C33: 1 | F33: 100% sweep on the term loan until it is repaid. Notes are bullet and cannot be swept
B34: Financing fee amortisation period (years) | C34: 7
B36: OPERATING CASE
B37: Increase in working capital as % of incremental revenue | C37: 0.12
B38: Capital expenditure as % of revenue | C38: 0.014 | F38: FY2025 actual: 1.4%. Asset-light
B39: Depreciation and amortisation as % of revenue | C39: 0.026
B40: Exit EV / EBITDA multiple | C40: 9 | F40: Below the entry multiple on purpose. Assuming multiple expansion is how an LBO model is made to lie
B41: Sponsor target internal rate of return | C41: 0.2 | F41: The return the deal has to clear to be worth doing
B43: Revenue growth and EBITDA margin by year are set on the Model sheet, where they can be read against the historical figures. Everything else lives here.

Sheet Sources & Uses
B1: Cognizant Technology Solutions — Leveraged Buyout — Debt Schedule and Returns | F1: IB PORTFOLIO
B2: What the transaction costs and where the money comes from
B4: OFFER
B5: Offer price per share (US$) | C5: =Inputs!$C$13*(1+Inputs!$C$20) -> 81.3605
B6: Equity purchase price | C6: ='Sources & Uses'!$C$5*Inputs!$C$12 -> 39703.924
B7: Transaction enterprise value | C7: ='Sources & Uses'!$C$6+Inputs!$C$10-Inputs!$C$11 -> 38954.924
B8: Entry EV / EBITDA | C8: ='Sources & Uses'!$C$7/Inputs!$C$6 -> 9.5806503 | F8: The single most important number in the model: it sets the price and, with the exit multiple, most of the return
B10: USES
B11: Purchase of equity | C11: ='Sources & Uses'!$C$6 -> 39703.924
B12: Refinance existing debt | C12: =Inputs!$C$10 -> 1152
B13: memo: Term Loan B raised | C13: =Inputs!$C$6*Inputs!$C$27 -> 12198
B14: memo: Senior notes raised | C14: =Inputs!$C$6*Inputs!$C$28 -> 9148.5
B15: memo: Total debt raised | C15: ='Sources & Uses'!$C$13+'Sources & Uses'!$C$14 -> 21346.5
B16: Financing fees | C16: ='Sources & Uses'!$C$15*Inputs!$C$22 -> 426.93
B17: Advisory and other fees | C17: ='Sources & Uses'!$C$7*Inputs!$C$23 -> 389.54924
B18: Total uses | C18: ='Sources & Uses'!$C$11+'Sources & Uses'!$C$12+'Sources & Uses'!$C$16+'Sources & Uses'!$C$17 -> 41672.403
B20: SOURCES
B21: Term Loan B | C21: ='Sources & Uses'!$C$13 -> 12198
B22: Senior notes | C22: ='Sources & Uses'!$C$14 -> 9148.5
B23: Cash from the balance sheet | C23: =MAX(0,Inputs!$C$11-Inputs!$C$21) -> 1401 | F23: Excess cash above the minimum operating balance is used to fund the deal
B24: Sponsor equity | C24: ='Sources & Uses'!$C$18-'Sources & Uses'!$C$21-'Sources & Uses'!$C$22-'Sources & Uses'!$C$23 -> 18924.903 | F24: The cheque the fund writes, and the denominator of every return in this model
B25: Total sources | C25: ='Sources & Uses'!$C$21+'Sources & Uses'!$C$22+'Sources & Uses'!$C$23+'Sources & Uses'!$C$24 -> 41672.403
B27: Opening total leverage (x EBITDA) | C27: ='Sources & Uses'!$C$15/Inputs!$C$6 -> 5.25
B28: Sponsor equity as % of total capitalisation | C28: ='Sources & Uses'!$C$24/'Sources & Uses'!$C$18 -> 0.45413515
B29: An equity cheque of this size would in practice be a consortium of several funds rather than one. That does not change the arithmetic — it changes who writes it — so the model treats the sponsor as a single investor.

Sheet Model
B1: Cognizant Technology Solutions — Leveraged Buyout — Debt Schedule and Returns | I1: IB PORTFOLIO
B2: Operating forecast and free cash flow before debt repayment · US$ millions
B4: OPERATING FORECAST
C5: FY2025A | D5: FY2026E | E5: FY2027E | F5: FY2028E | G5: FY2029E | H5: FY2030E
B6: Revenue | C6: =Inputs!$C$5 -> 21108 | D6: =C6*(1+D7) -> 21741.24 | E6: =D6*(1+E7) -> 22502.183 | F6: =E6*(1+F7) -> 23402.271 | G6: =F6*(1+G7) -> 24338.362 | H6: =G6*(1+H7) -> 25311.896
B7: Growth | D7: 0.03 | E7: 0.035 | F7: 0.04 | G7: 0.04 | H7: 0.04
B8: EBITDA margin | C8: =Inputs!$C$6/Inputs!$C$5 -> 0.19262839 | D8: 0.196 | E8: 0.2 | F8: 0.204 | G8: 0.207 | H8: 0.21
B9: EBITDA | C9: =Inputs!$C$6 -> 4066 | D9: =D6*D8 -> 4261.283 | E9: =E6*E8 -> 4500.4367 | F9: =F6*F8 -> 4774.0632 | G9: =G6*G8 -> 5038.0408 | H9: =H6*H8 -> 5315.4982
B10: Depreciation and amortisation | C10: =Inputs!$C$8 -> 550 | D10: =D6*Inputs!$C$39 -> 565.27224 | E10: =E6*Inputs!$C$39 -> 585.05677 | F10: =F6*Inputs!$C$39 -> 608.45904 | G10: =G6*Inputs!$C$39 -> 632.7974 | H10: =H6*Inputs!$C$39 -> 658.1093
B11: Capital expenditure | C11: =Inputs!$C$9 -> 288 | D11: =D6*Inputs!$C$38 -> 304.37736 | E11: =E6*Inputs!$C$38 -> 315.03057 | F11: =F6*Inputs!$C$38 -> 327.63179 | G11: =G6*Inputs!$C$38 -> 340.73706 | H11: =H6*Inputs!$C$38 -> 354.36654
B12: Increase in working capital | D12: =(D6-C6)*Inputs!$C$37 -> 75.9888 | E12: =(E6-D6)*Inputs!$C$37 -> 91.313208 | F12: =(F6-E6)*Inputs!$C$37 -> 108.01048 | G12: =(G6-F6)*Inputs!$C$37 -> 112.3309 | H12: =(H6-G6)*Inputs!$C$37 -> 116.82414
B14: FREE CASH FLOW BEFORE DEBT SERVICE
B15: EBITDA | D15: =D9 -> 4261.283 | E15: =E9 -> 4500.4367 | F15: =F9 -> 4774.0632 | G15: =G9 -> 5038.0408 | H15: =H9 -> 5315.4982
B16: Less: capital expenditure | D16: =-D11 -> -304.37736 | E16: =-E11 -> -315.03057 | F16: =-F11 -> -327.63179 | G16: =-G11 -> -340.73706 | H16: =-H11 -> -354.36654
B17: Less: increase in working capital | D17: =-D12 -> -75.9888 | E17: =-E12 -> -91.313208 | F17: =-F12 -> -108.01048 | G17: =-G12 -> -112.3309 | H17: =-H12 -> -116.82414
B18: Interest and cash tax are charged on the Debt Schedule, where the opening balance for each year is known. Free cash flow after debt service flows back here only as the sweep amount.

Sheet Debt Schedule
B1: Cognizant Technology Solutions — Leveraged Buyout — Debt Schedule and Returns | I1: IB PORTFOLIO
B2: Interest charged on opening balances · cash sweep applied to the term loan
B4: INTEREST AND CASH TAX
C5: At close | D5: FY2026E | E5: FY2027E | F5: FY2028E | G5: FY2029E | H5: FY2030E
B6: Term Loan B — opening balance | C6: ='Sources & Uses'!$C$13 -> 12198 | D6: =C9 -> 12198 | E6: =D9 -> 10490.618 | F6: =E9 -> 8529.5032 | G6: =F9 -> 6277.0387 | H6: =G9 -> 3712.0755
B7: Mandatory amortisation | D7: =-MIN(D6,'Sources & Uses'!$C$13*Inputs!$C$32) -> -121.98 | E7: =-MIN(E6,'Sources & Uses'!$C$13*Inputs!$C$32) -> -121.98 | F7: =-MIN(F6,'Sources & Uses'!$C$13*Inputs!$C$32) -> -121.98 | G7: =-MIN(G6,'Sources & Uses'!$C$13*Inputs!$C$32) -> -121.98 | H7: =-MIN(H6,'Sources & Uses'!$C$13*Inputs!$C$32) -> -121.98
B8: Cash sweep | D8: =-MIN(MAX(0,D29)*Inputs!$C$33,D6+D7) -> -1585.4016 | E8: =-MIN(MAX(0,E29)*Inputs!$C$33,E6+E7) -> -1839.1352 | F8: =-MIN(MAX(0,F29)*Inputs!$C$33,F6+F7) -> -2130.4845 | G8: =-MIN(MAX(0,G29)*Inputs!$C$33,G6+G7) -> -2442.9831 | H8: =-MIN(MAX(0,H29)*Inputs!$C$33,H6+H7) -> -2782.5987
B9: Term Loan B — closing balance | C9: ='Sources & Uses'!$C$13 -> 12198 | D9: =D6+D7+D8 -> 10490.618 | E9: =E6+E7+E8 -> 8529.5032 | F9: =F6+F7+F8 -> 6277.0387 | G9: =G6+G7+G8 -> 3712.0755 | H9: =H6+H7+H8 -> 807.49687
B11: Senior notes — balance (bullet) | C11: ='Sources & Uses'!$C$14 -> 9148.5 | D11: ='Sources & Uses'!$C$14 -> 9148.5 | E11: ='Sources & Uses'!$C$14 -> 9148.5 | F11: ='Sources & Uses'!$C$14 -> 9148.5 | G11: ='Sources & Uses'!$C$14 -> 9148.5 | H11: ='Sources & Uses'!$C$14 -> 9148.5
B12: Total debt | C12: =C9+C11 -> 21346.5 | D12: =D9+D11 -> 19639.118 | E12: =E9+E11 -> 17678.003 | F12: =F9+F11 -> 15425.539 | G12: =G9+G11 -> 12860.576 | H12: =H9+H11 -> 9955.9969
B14: Interest — Term Loan B | D14: =D6*(Inputs!$C$29+Inputs!$C$30) -> 908.751 | E14: =E6*(Inputs!$C$29+Inputs!$C$30) -> 781.55107 | F14: =F6*(Inputs!$C$29+Inputs!$C$30) -> 635.44799 | G14: =G6*(Inputs!$C$29+Inputs!$C$30) -> 467.63938 | H14: =H6*(Inputs!$C$29+Inputs!$C$30) -> 276.54963
B15: Interest — senior notes | D15: ='Sources & Uses'!$C$14*Inputs!$C$31 -> 777.6225 | E15: ='Sources & Uses'!$C$14*Inputs!$C$31 -> 777.6225 | F15: ='Sources & Uses'!$C$14*Inputs!$C$31 -> 777.6225 | G15: ='Sources & Uses'!$C$14*Inputs!$C$31 -> 777.6225 | H15: ='Sources & Uses'!$C$14*Inputs!$C$31 -> 777.6225
B16: Financing fee amortisation | D16: ='Sources & Uses'!$C$16/Inputs!$C$34 -> 60.99 | E16: ='Sources & Uses'!$C$16/Inputs!$C$34 -> 60.99 | F16: ='Sources & Uses'!$C$16/Inputs!$C$34 -> 60.99 | G16: ='Sources & Uses'!$C$16/Inputs!$C$34 -> 60.99 | H16: ='Sources & Uses'!$C$16/Inputs!$C$34 -> 60.99
B17: Total interest and fee amortisation | D17: =SUM(D14:D16) -> 1747.3635 | E17: =SUM(E14:E16) -> 1620.1636 | F17: =SUM(F14:F16) -> 1474.0605 | G17: =SUM(G14:G16) -> 1306.2519 | H17: =SUM(H14:H16) -> 1115.1621
B19: Profit before tax | D19: =Model!D9-Model!D10-D17 -> 1948.6473 | E19: =Model!E9-Model!E10-E17 -> 2295.2163 | F19: =Model!F9-Model!F10-F17 -> 2691.5437 | G19: =Model!G9-Model!G10-G17 -> 3098.9916 | H19: =Model!H9-Model!H10-H17 -> 3542.2267
B20: Cash tax | D20: =-MAX(0,D19)*Inputs!$C$24 -> -487.16183 | E20: =-MAX(0,E19)*Inputs!$C$24 -> -573.80408 | F20: =-MAX(0,F19)*Inputs!$C$24 -> -672.88593 | G20: =-MAX(0,G19)*Inputs!$C$24 -> -774.74789 | H20: =-MAX(0,H19)*Inputs!$C$24 -> -885.55669
B22: CASH AVAILABLE FOR DEBT REPAYMENT
B23: EBITDA | D23: =Model!D9 -> 4261.283 | E23: =Model!E9 -> 4500.4367 | F23: =Model!F9 -> 4774.0632 | G23: =Model!G9 -> 5038.0408 | H23: =Model!H9 -> 5315.4982
B24: Less: capital expenditure | D24: =-Model!D11 -> -304.37736 | E24: =-Model!E11 -> -315.03057 | F24: =-Model!F11 -> -327.63179 | G24: =-Model!G11 -> -340.73706 | H24: =-Model!H11 -> -354.36654
B25: Less: increase in working capital | D25: =-Model!D12 -> -75.9888 | E25: =-Model!E12 -> -91.313208 | F25: =-Model!F12 -> -108.01048 | G25: =-Model!G12 -> -112.3309 | H25: =-Model!H12 -> -116.82414
B26: Less: cash interest | D26: =-(D14+D15) -> -1686.3735 | E26: =-(E14+E15) -> -1559.1736 | F26: =-(F14+F15) -> -1413.0705 | G26: =-(G14+G15) -> -1245.2619 | H26: =-(H14+H15) -> -1054.1721
B27: Less: cash tax | D27: =D20 -> -487.16183 | E27: =E20 -> -573.80408 | F27: =F20 -> -672.88593 | G27: =G20 -> -774.74789 | H27: =H20 -> -885.55669
B28: Less: mandatory amortisation | D28: =D7 -> -121.98 | E28: =E7 -> -121.98 | F28: =F7 -> -121.98 | G28: =G7 -> -121.98 | H28: =H7 -> -121.98
B29: Cash available for the sweep | D29: =SUM(D23:D28) -> 1585.4016 | E29: =SUM(E23:E28) -> 1839.1352 | F29: =SUM(F23:F28) -> 2130.4845 | G29: =SUM(G23:G28) -> 2442.9831 | H29: =SUM(H23:H28) -> 2782.5987
B31: CREDIT STATISTICS
B32: Total debt / EBITDA | C32: =C12/Inputs!$C$6 -> 5.25 | D32: =D12/Model!D9 -> 4.6087336 | E32: =E12/Model!E9 -> 3.928064 | F32: =F12/Model!F9 -> 3.2311132 | G32: =G12/Model!G9 -> 2.5526938 | H32: =H12/Model!H9 -> 1.8730129
B33: EBITDA / cash interest | D33: =Model!D9/(D14+D15) -> 2.5268916 | E33: =Model!E9/(E14+E15) -> 2.8864244 | F33: =Model!F9/(F14+F15) -> 3.3785032 | G33: =Model!G9/(G14+G15) -> 4.0457681 | H33: =Model!H9/(H14+H15) -> 5.0423437
B35: Leverage of over five times EBITDA at close, against interest cover of roughly two and a half times, is an aggressive but financeable structure for a business with Cognizant's cash conversion. The covenant question a lender would ask is what happens to cover if revenue falls rather than grows; the sensitivity grids answer it.

Sheet Returns
B1: Cognizant Technology Solutions — Leveraged Buyout — Debt Schedule and Returns | F1: IB PORTFOLIO
B2: Exit, money multiple, internal rate of return and the price that clears the hurdle
B4: EXIT AT THE END OF YEAR 5
B5: Exit-year EBITDA | C5: =Model!H9 -> 5315.4982
B6: Exit EV / EBITDA | C6: =Inputs!$C$40 -> 9
B7: Exit enterprise value | C7: =Returns!$C$5*Returns!$C$6 -> 47839.483
B8: Less: net debt at exit | C8: =-'Debt Schedule'!H12 -> -9955.9969
B9: Exit equity value | C9: =Returns!$C$7+Returns!$C$8 -> 37883.487
B11: Sponsor equity invested at close | C11: ='Sources & Uses'!$C$24 -> 18924.903
B12: Money multiple (MOIC) | C12: =Returns!$C$9/Returns!$C$11 -> 2.0017797
B13: Internal rate of return | C13: =Returns!$C$12^(1/5)-1 -> 0.14890271 | F13: A single entry and a single exit, so the IRR is the fifth root of the money multiple. No interim dividends are assumed
B14: Versus the 20% hurdle (percentage points) | C14: =(Returns!$C$13-Inputs!$C$41)*100 -> -5.1097287
B16: VALUE CREATION BRIDGE
B17: Debt repaid over the hold | C17: ='Debt Schedule'!C12-'Debt Schedule'!H12 -> 11390.503
B18: EBITDA growth, valued at the exit multiple | C18: =(Returns!$C$5-Inputs!$C$6)*Returns!$C$6 -> 11245.483
B19: Multiple change, valued on entry EBITDA | C19: =(Returns!$C$6-'Sources & Uses'!$C$8)*Inputs!$C$6 -> -2360.924 | F19: Negative here because the exit multiple is set below entry on purpose
B20: Total value created | C20: =Returns!$C$9-Returns!$C$11 -> 18958.583
B22: THE PRICE A SPONSOR COULD ACTUALLY PAY
B23: Sponsor equity consistent with a 20% return | C23: =Returns!$C$9/(1+Inputs!$C$41)^5 -> 15224.524
B24: Implied maximum equity purchase price | C24: =Returns!$C$23+'Sources & Uses'!$C$21+'Sources & Uses'!$C$22+'Sources & Uses'!$C$23-Inputs!$C$10-'Sources & Uses'!$C$16-'Sources & Uses'!$C$17 -> 36003.544
B25: Implied maximum offer price per share (US$) | C25: =Returns!$C$24/Inputs!$C$12 -> 73.777755 | F25: The LBO floor for Project 5's football field: what a financial buyer could pay and still clear its hurdle
B26: Implied maximum premium to the unaffected price | C26: =Returns!$C$25/Inputs!$C$13-1 -> 0.17884085
B27: Advisory fees move slightly with the transaction value, so the maximum price is very marginally circular. The effect is under a dollar a share and the fees are held at the base case rather than switching on iterative calculation, which would make the workbook fragile on another machine.

Sheet Sensitivity
B1: Cognizant Technology Solutions — Leveraged Buyout — Debt Schedule and Returns | H1: IB PORTFOLIO
B2: Internal rate of return · every cell rebuilds the equity cheque and the exit from scratch
B4: IRR — OFFER PREMIUM versus EXIT MULTIPLE
B5: Exit EV/EBITDA \ Offer premium | C5: 0.1 | D5: 0.2 | E5: 0.3 | F5: 0.4 | G5: 0.5
B6: 8 | C6: =((Model!H9*$B6-('Debt Schedule'!H12+(Inputs!$C$6*(Inputs!$C$27+Inputs!$C$28))-'Sources & Uses'!$C$15))/(((Inputs!$C$13*(1+C$5)*Inputs!$C$12)+Inputs!$C$10+(Inputs!$C$6*(Inputs!$C$27+Inputs!$C$28))*Inputs!$C$22+((Inputs!$C$13*(1+C$5)*Inputs!$C$12)+Inputs!$C$10-Inputs!$C$11)*Inputs!$C$23)-(Inputs!$C$6*(Inputs!$C$27+Inputs!$C$28))-'Sources & Uses'!$C$23))^(1/5)-1 -> 0.20619778 | D6: =((Model!H9*$B6-('Debt Schedule'!H12+(Inputs!$C$6*(Inputs!$C$27+Inputs!$C$28))-'Sources & Uses'!$C$15))/(((Inputs!$C$13*(1+D$5)*Inputs!$C$12)+Inputs!$C$10+(Inputs!$C$6*(Inputs!$C$27+Inputs!$C$28))*Inputs!$C$22+((Inputs!$C$13*(1+D$5)*Inputs!$C$12)+Inputs!$C$10-Inputs!$C$11)*Inputs!$C$23)-(Inputs!$C$6*(Inputs!$C$27+Inputs!$C$28))-'Sources & Uses'!$C$23))^(1/5)-1 -> 0.15506382 | E6: =((Model!H9*$B6-('Debt Schedule'!H12+(Inputs!$C$6*(Inputs!$C$27+Inputs!$C$28))-'Sources & Uses'!$C$15))/(((Inputs!$C$13*(1+E$5)*Inputs!$C$12)+Inputs!$C$10+(Inputs!$C$6*(Inputs!$C$27+Inputs!$C$28))*Inputs!$C$22+((Inputs!$C$13*(1+E$5)*Inputs!$C$12)+Inputs!$C$10-Inputs!$C$11)*Inputs!$C$23)-(Inputs!$C$6*(Inputs!$C$27+Inputs!$C$28))-'Sources & Uses'!$C$23))^(1/5)-1 -> 0.11468319 | F6: =((Model!H9*$B6-('Debt Schedule'!H12+(Inputs!$C$6*(Inputs!$C$27+Inputs!$C$28))-'Sources & Uses'!$C$15))/(((Inputs!$C$13*(1+F$5)*Inputs!$C$12)+Inputs!$C$10+(Inputs!$C$6*(Inputs!$C$27+Inputs!$C$28))*Inputs!$C$22+((Inputs!$C$13*(1+F$5)*Inputs!$C$12)+Inputs!$C$10-Inputs!$C$11)*Inputs!$C$23)-(Inputs!$C$6*(Inputs!$C$27+Inputs!$C$28))-'Sources & Uses'!$C$23))^(1/5)-1 -> 0.081523065 | G6: =((Model!H9*$B6-('Debt Schedule'!H12+(Inputs!$C$6*(Inputs!$C$27+Inputs!$C$28))-'Sources & Uses'!$C$15))/(((Inputs!$C$13*(1+G$5)*Inputs!$C$12)+Inputs!$C$10+(Inputs!$C$6*(Inputs!$C$27+Inputs!$C$28))*Inputs!$C$22+((Inputs!$C$13*(1+G$5)*Inputs!$C$12)+Inputs!$C$10-Inputs!$C$11)*Inputs!$C$23)-(Inputs!$C$6*(Inputs!$C$27+Inputs!$C$28))-'Sources & Uses'!$C$23))^(1/5)-1 -> 0.053521084
B7: 8.5 | C7: =((Model!H9*$B7-('Debt Schedule'!H12+(Inputs!$C$6*(Inputs!$C$27+Inputs!$C$28))-'Sources & Uses'!$C$15))/(((Inputs!$C$13*(1+C$5)*Inputs!$C$12)+Inputs!$C$10+(Inputs!$C$6*(Inputs!$C$27+Inputs!$C$28))*Inputs!$C$22+((Inputs!$C$13*(1+C$5)*Inputs!$C$12)+Inputs!$C$10-Inputs!$C$11)*Inputs!$C$23)-(Inputs!$C$6*(Inputs!$C$27+Inputs!$C$28))-'Sources & Uses'!$C$23))^(1/5)-1 -> 0.22527157 | D7: =((Model!H9*$B7-('Debt Schedule'!H12+(Inputs!$C$6*(Inputs!$C$27+Inputs!$C$28))-'Sources & Uses'!$C$15))/(((Inputs!$C$13*(1+D$5)*Inputs!$C$12)+Inputs!$C$10+(Inputs!$C$6*(Inputs!$C$27+Inputs!$C$28))*Inputs!$C$22+((Inputs!$C$13*(1+D$5)*Inputs!$C$12)+Inputs!$C$10-Inputs!$C$11)*Inputs!$C$23)-(Inputs!$C$6*(Inputs!$C$27+Inputs!$C$28))-'Sources & Uses'!$C$23))^(1/5)-1 -> 0.17332902 | E7: =((Model!H9*$B7-('Debt Schedule'!H12+(Inputs!$C$6*(Inputs!$C$27+Inputs!$C$28))-'Sources & Uses'!$C$15))/(((Inputs!$C$13*(1+E$5)*Inputs!$C$12)+Inputs!$C$10+(Inputs!$C$6*(Inputs!$C$27+Inputs!$C$28))*Inputs!$C$22+((Inputs!$C$13*(1+E$5)*Inputs!$C$12)+Inputs!$C$10-Inputs!$C$11)*Inputs!$C$23)-(Inputs!$C$6*(Inputs!$C$27+Inputs!$C$28))-'Sources & Uses'!$C$23))^(1/5)-1 -> 0.13230985 | F7: =((Model!H9*$B7-('Debt Schedule'!H12+(Inputs!$C$6*(Inputs!$C$27+Inputs!$C$28))-'Sources & Uses'!$C$15))/(((Inputs!$C$13*(1+F$5)*Inputs!$C$12)+Inputs!$C$10+(Inputs!$C$6*(Inputs!$C$27+Inputs!$C$28))*Inputs!$C$22+((Inputs!$C$13*(1+F$5)*Inputs!$C$12)+Inputs!$C$10-Inputs!$C$11)*Inputs!$C$23)-(Inputs!$C$6*(Inputs!$C$27+Inputs!$C$28))-'Sources & Uses'!$C$23))^(1/5)-1 -> 0.098625355 | G7: =((Model!H9*$B7-('Debt Schedule'!H12+(Inputs!$C$6*(Inputs!$C$27+Inputs!$C$28))-'Sources & Uses'!$C$15))/(((Inputs!$C$13*(1+G$5)*Inputs!$C$12)+Inputs!$C$10+(Inputs!$C$6*(Inputs!$C$27+Inputs!$C$28))*Inputs!$C$22+((Inputs!$C$13*(1+G$5)*Inputs!$C$12)+Inputs!$C$10-Inputs!$C$11)*Inputs!$C$23)-(Inputs!$C$6*(Inputs!$C$27+Inputs!$C$28))-'Sources & Uses'!$C$23))^(1/5)-1 -> 0.070180574
B8: 9 | C8: =((Model!H9*$B8-('Debt Schedule'!H12+(Inputs!$C$6*(Inputs!$C$27+Inputs!$C$28))-'Sources & Uses'!$C$15))/(((Inputs!$C$13*(1+C$5)*Inputs!$C$12)+Inputs!$C$10+(Inputs!$C$6*(Inputs!$C$27+Inputs!$C$28))*Inputs!$C$22+((Inputs!$C$13*(1+C$5)*Inputs!$C$12)+Inputs!$C$10-Inputs!$C$11)*Inputs!$C$23)-(Inputs!$C$6*(Inputs!$C$27+Inputs!$C$28))-'Sources & Uses'!$C$23))^(1/5)-1 -> 0.24322669 | D8: =((Model!H9*$B8-('Debt Schedule'!H12+(Inputs!$C$6*(Inputs!$C$27+Inputs!$C$28))-'Sources & Uses'!$C$15))/(((Inputs!$C$13*(1+D$5)*Inputs!$C$12)+Inputs!$C$10+(Inputs!$C$6*(Inputs!$C$27+Inputs!$C$28))*Inputs!$C$22+((Inputs!$C$13*(1+D$5)*Inputs!$C$12)+Inputs!$C$10-Inputs!$C$11)*Inputs!$C$23)-(Inputs!$C$6*(Inputs!$C$27+Inputs!$C$28))-'Sources & Uses'!$C$23))^(1/5)-1 -> 0.19052297 | E8: =((Model!H9*$B8-('Debt Schedule'!H12+(Inputs!$C$6*(Inputs!$C$27+Inputs!$C$28))-'Sources & Uses'!$C$15))/(((Inputs!$C$13*(1+E$5)*Inputs!$C$12)+Inputs!$C$10+(Inputs!$C$6*(Inputs!$C$27+Inputs!$C$28))*Inputs!$C$22+((Inputs!$C$13*(1+E$5)*Inputs!$C$12)+Inputs!$C$10-Inputs!$C$11)*Inputs!$C$23)-(Inputs!$C$6*(Inputs!$C$27+Inputs!$C$28))-'Sources & Uses'!$C$23))^(1/5)-1 -> 0.14890271 | F8: =((Model!H9*$B8-('Debt Schedule'!H12+(Inputs!$C$6*(Inputs!$C$27+Inputs!$C$28))-'Sources & Uses'!$C$15))/(((Inputs!$C$13*(1+F$5)*Inputs!$C$12)+Inputs!$C$10+(Inputs!$C$6*(Inputs!$C$27+Inputs!$C$28))*Inputs!$C$22+((Inputs!$C$13*(1+F$5)*Inputs!$C$12)+Inputs!$C$10-Inputs!$C$11)*Inputs!$C$23)-(Inputs!$C$6*(Inputs!$C$27+Inputs!$C$28))-'Sources & Uses'!$C$23))^(1/5)-1 -> 0.11472461 | G8: =((Model!H9*$B8-('Debt Schedule'!H12+(Inputs!$C$6*(Inputs!$C$27+Inputs!$C$28))-'Sources & Uses'!$C$15))/(((Inputs!$C$13*(1+G$5)*Inputs!$C$12)+Inputs!$C$10+(Inputs!$C$6*(Inputs!$C$27+Inputs!$C$28))*Inputs!$C$22+((Inputs!$C$13*(1+G$5)*Inputs!$C$12)+Inputs!$C$10-Inputs!$C$11)*Inputs!$C$23)-(Inputs!$C$6*(Inputs!$C$27+Inputs!$C$28))-'Sources & Uses'!$C$23))^(1/5)-1 -> 0.085862995
B9: 9.5 | C9: =((Model!H9*$B9-('Debt Schedule'!H12+(Inputs!$C$6*(Inputs!$C$27+Inputs!$C$28))-'Sources & Uses'!$C$15))/(((Inputs!$C$13*(1+C$5)*Inputs!$C$12)+Inputs!$C$10+(Inputs!$C$6*(Inputs!$C$27+Inputs!$C$28))*Inputs!$C$22+((Inputs!$C$13*(1+C$5)*Inputs!$C$12)+Inputs!$C$10-Inputs!$C$11)*Inputs!$C$23)-(Inputs!$C$6*(Inputs!$C$27+Inputs!$C$28))-'Sources & Uses'!$C$23))^(1/5)-1 -> 0.26020075 | D9: =((Model!H9*$B9-('Debt Schedule'!H12+(Inputs!$C$6*(Inputs!$C$27+Inputs!$C$28))-'Sources & Uses'!$C$15))/(((Inputs!$C$13*(1+D$5)*Inputs!$C$12)+Inputs!$C$10+(Inputs!$C$6*(Inputs!$C$27+Inputs!$C$28))*Inputs!$C$22+((Inputs!$C$13*(1+D$5)*Inputs!$C$12)+Inputs!$C$10-Inputs!$C$11)*Inputs!$C$23)-(Inputs!$C$6*(Inputs!$C$27+Inputs!$C$28))-'Sources & Uses'!$C$23))^(1/5)-1 -> 0.20677746 | E9: =((Model!H9*$B9-('Debt Schedule'!H12+(Inputs!$C$6*(Inputs!$C$27+Inputs!$C$28))-'Sources & Uses'!$C$15))/(((Inputs!$C$13*(1+E$5)*Inputs!$C$12)+Inputs!$C$10+(Inputs!$C$6*(Inputs!$C$27+Inputs!$C$28))*Inputs!$C$22+((Inputs!$C$13*(1+E$5)*Inputs!$C$12)+Inputs!$C$10-Inputs!$C$11)*Inputs!$C$23)-(Inputs!$C$6*(Inputs!$C$27+Inputs!$C$28))-'Sources & Uses'!$C$23))^(1/5)-1 -> 0.16458894 | F9: =((Model!H9*$B9-('Debt Schedule'!H12+(Inputs!$C$6*(Inputs!$C$27+Inputs!$C$28))-'Sources & Uses'!$C$15))/(((Inputs!$C$13*(1+F$5)*Inputs!$C$12)+Inputs!$C$10+(Inputs!$C$6*(Inputs!$C$27+Inputs!$C$28))*Inputs!$C$22+((Inputs!$C$13*(1+F$5)*Inputs!$C$12)+Inputs!$C$10-Inputs!$C$11)*Inputs!$C$23)-(Inputs!$C$6*(Inputs!$C$27+Inputs!$C$28))-'Sources & Uses'!$C$23))^(1/5)-1 -> 0.12994419 | G9: =((Model!H9*$B9-('Debt Schedule'!H12+(Inputs!$C$6*(Inputs!$C$27+Inputs!$C$28))-'Sources & Uses'!$C$15))/(((Inputs!$C$13*(1+G$5)*Inputs!$C$12)+Inputs!$C$10+(Inputs!$C$6*(Inputs!$C$27+Inputs!$C$28))*Inputs!$C$22+((Inputs!$C$13*(1+G$5)*Inputs!$C$12)+Inputs!$C$10-Inputs!$C$11)*Inputs!$C$23)-(Inputs!$C$6*(Inputs!$C$27+Inputs!$C$28))-'Sources & Uses'!$C$23))^(1/5)-1 -> 0.10068853
B10: 10 | C10: =((Model!H9*$B10-('Debt Schedule'!H12+(Inputs!$C$6*(Inputs!$C$27+Inputs!$C$28))-'Sources & Uses'!$C$15))/(((Inputs!$C$13*(1+C$5)*Inputs!$C$12)+Inputs!$C$10+(Inputs!$C$6*(Inputs!$C$27+Inputs!$C$28))*Inputs!$C$22+((Inputs!$C$13*(1+C$5)*Inputs!$C$12)+Inputs!$C$10-Inputs!$C$11)*Inputs!$C$23)-(Inputs!$C$6*(Inputs!$C$27+Inputs!$C$28))-'Sources & Uses'!$C$23))^(1/5)-1 -> 0.27630669 | D10: =((Model!H9*$B10-('Debt Schedule'!H12+(Inputs!$C$6*(Inputs!$C$27+Inputs!$C$28))-'Sources & Uses'!$C$15))/(((Inputs!$C$13*(1+D$5)*Inputs!$C$12)+Inputs!$C$10+(Inputs!$C$6*(Inputs!$C$27+Inputs!$C$28))*Inputs!$C$22+((Inputs!$C$13*(1+D$5)*Inputs!$C$12)+Inputs!$C$10-Inputs!$C$11)*Inputs!$C$23)-(Inputs!$C$6*(Inputs!$C$27+Inputs!$C$28))-'Sources & Uses'!$C$23))^(1/5)-1 -> 0.22220062 | E10: =((Model!H9*$B10-('Debt Schedule'!H12+(Inputs!$C$6*(Inputs!$C$27+Inputs!$C$28))-'Sources & Uses'!$C$15))/(((Inputs!$C$13*(1+E$5)*Inputs!$C$12)+Inputs!$C$10+(Inputs!$C$6*(Inputs!$C$27+Inputs!$C$28))*Inputs!$C$22+((Inputs!$C$13*(1+E$5)*Inputs!$C$12)+Inputs!$C$10-Inputs!$C$11)*Inputs!$C$23)-(Inputs!$C$6*(Inputs!$C$27+Inputs!$C$28))-'Sources & Uses'!$C$23))^(1/5)-1 -> 0.17947292 | F10: =((Model!H9*$B10-('Debt Schedule'!H12+(Inputs!$C$6*(Inputs!$C$27+Inputs!$C$28))-'Sources & Uses'!$C$15))/(((Inputs!$C$13*(1+F$5)*Inputs!$C$12)+Inputs!$C$10+(Inputs!$C$6*(Inputs!$C$27+Inputs!$C$28))*Inputs!$C$22+((Inputs!$C$13*(1+F$5)*Inputs!$C$12)+Inputs!$C$10-Inputs!$C$11)*Inputs!$C$23)-(Inputs!$C$6*(Inputs!$C$27+Inputs!$C$28))-'Sources & Uses'!$C$23))^(1/5)-1 -> 0.1443854 | G10: =((Model!H9*$B10-('Debt Schedule'!H12+(Inputs!$C$6*(Inputs!$C$27+Inputs!$C$28))-'Sources & Uses'!$C$15))/(((Inputs!$C$13*(1+G$5)*Inputs!$C$12)+Inputs!$C$10+(Inputs!$C$6*(Inputs!$C$27+Inputs!$C$28))*Inputs!$C$22+((Inputs!$C$13*(1+G$5)*Inputs!$C$12)+Inputs!$C$10-Inputs!$C$11)*Inputs!$C$23)-(Inputs!$C$6*(Inputs!$C$27+Inputs!$C$28))-'Sources & Uses'!$C$23))^(1/5)-1 -> 0.11475583
B12: IRR — OPENING LEVERAGE versus EXIT MULTIPLE (at the 30% base-case premium)
B13: Exit EV/EBITDA \ Total leverage | C13: 4.25 | D13: 4.75 | E13: 5.25 | F13: 5.75 | G13: 6.25
B14: 8 | C14: =((Model!H9*$B14-('Debt Schedule'!H12+(Inputs!$C$6*C$13)-'Sources & Uses'!$C$15))/(((Inputs!$C$13*(1+Inputs!$C$20)*Inputs!$C$12)+Inputs!$C$10+(Inputs!$C$6*C$13)*Inputs!$C$22+((Inputs!$C$13*(1+Inputs!$C$20)*Inputs!$C$12)+Inputs!$C$10-Inputs!$C$11)*Inputs!$C$23)-(Inputs!$C$6*C$13)-'Sources & Uses'!$C$23))^(1/5)-1 -> 0.098432573 | D14: =((Model!H9*$B14-('Debt Schedule'!H12+(Inputs!$C$6*D$13)-'Sources & Uses'!$C$15))/(((Inputs!$C$13*(1+Inputs!$C$20)*Inputs!$C$12)+Inputs!$C$10+(Inputs!$C$6*D$13)*Inputs!$C$22+((Inputs!$C$13*(1+Inputs!$C$20)*Inputs!$C$12)+Inputs!$C$10-Inputs!$C$11)*Inputs!$C$23)-(Inputs!$C$6*D$13)-'Sources & Uses'!$C$23))^(1/5)-1 -> 0.10590243 | E14: =((Model!H9*$B14-('Debt Schedule'!H12+(Inputs!$C$6*E$13)-'Sources & Uses'!$C$15))/(((Inputs!$C$13*(1+Inputs!$C$20)*Inputs!$C$12)+Inputs!$C$10+(Inputs!$C$6*E$13)*Inputs!$C$22+((Inputs!$C$13*(1+Inputs!$C$20)*Inputs!$C$12)+Inputs!$C$10-Inputs!$C$11)*Inputs!$C$23)-(Inputs!$C$6*E$13)-'Sources & Uses'!$C$23))^(1/5)-1 -> 0.11468319 | F14: =((Model!H9*$B14-('Debt Schedule'!H12+(Inputs!$C$6*F$13)-'Sources & Uses'!$C$15))/(((Inputs!$C$13*(1+Inputs!$C$20)*Inputs!$C$12)+Inputs!$C$10+(Inputs!$C$6*F$13)*Inputs!$C$22+((Inputs!$C$13*(1+Inputs!$C$20)*Inputs!$C$12)+Inputs!$C$10-Inputs!$C$11)*Inputs!$C$23)-(Inputs!$C$6*F$13)-'Sources & Uses'!$C$23))^(1/5)-1 -> 0.12516188 | G14: =((Model!H9*$B14-('Debt Schedule'!H12+(Inputs!$C$6*G$13)-'Sources & Uses'!$C$15))/(((Inputs!$C$13*(1+Inputs!$C$20)*Inputs!$C$12)+Inputs!$C$10+(Inputs!$C$6*G$13)*Inputs!$C$22+((Inputs!$C$13*(1+Inputs!$C$20)*Inputs!$C$12)+Inputs!$C$10-Inputs!$C$11)*Inputs!$C$23)-(Inputs!$C$6*G$13)-'Sources & Uses'!$C$23))^(1/5)-1 -> 0.13789873
B15: 8.5 | C15: =((Model!H9*$B15-('Debt Schedule'!H12+(Inputs!$C$6*C$13)-'Sources & Uses'!$C$15))/(((Inputs!$C$13*(1+Inputs!$C$20)*Inputs!$C$12)+Inputs!$C$10+(Inputs!$C$6*C$13)*Inputs!$C$22+((Inputs!$C$13*(1+Inputs!$C$20)*Inputs!$C$12)+Inputs!$C$10-Inputs!$C$11)*Inputs!$C$23)-(Inputs!$C$6*C$13)-'Sources & Uses'!$C$23))^(1/5)-1 -> 0.1139272 | D15: =((Model!H9*$B15-('Debt Schedule'!H12+(Inputs!$C$6*D$13)-'Sources & Uses'!$C$15))/(((Inputs!$C$13*(1+Inputs!$C$20)*Inputs!$C$12)+Inputs!$C$10+(Inputs!$C$6*D$13)*Inputs!$C$22+((Inputs!$C$13*(1+Inputs!$C$20)*Inputs!$C$12)+Inputs!$C$10-Inputs!$C$11)*Inputs!$C$23)-(Inputs!$C$6*D$13)-'Sources & Uses'!$C$23))^(1/5)-1 -> 0.12239245 | E15: =((Model!H9*$B15-('Debt Schedule'!H12+(Inputs!$C$6*E$13)-'Sources & Uses'!$C$15))/(((Inputs!$C$13*(1+Inputs!$C$20)*Inputs!$C$12)+Inputs!$C$10+(Inputs!$C$6*E$13)*Inputs!$C$22+((Inputs!$C$13*(1+Inputs!$C$20)*Inputs!$C$12)+Inputs!$C$10-Inputs!$C$11)*Inputs!$C$23)-(Inputs!$C$6*E$13)-'Sources & Uses'!$C$23))^(1/5)-1 -> 0.13230985 | F15: =((Model!H9*$B15-('Debt Schedule'!H12+(Inputs!$C$6*F$13)-'Sources & Uses'!$C$15))/(((Inputs!$C$13*(1+Inputs!$C$20)*Inputs!$C$12)+Inputs!$C$10+(Inputs!$C$6*F$13)*Inputs!$C$22+((Inputs!$C$13*(1+Inputs!$C$20)*Inputs!$C$12)+Inputs!$C$10-Inputs!$C$11)*Inputs!$C$23)-(Inputs!$C$6*F$13)-'Sources & Uses'!$C$23))^(1/5)-1 -> 0.14410023 | G15: =((Model!H9*$B15-('Debt Schedule'!H12+(Inputs!$C$6*G$13)-'Sources & Uses'!$C$15))/(((Inputs!$C$13*(1+Inputs!$C$20)*Inputs!$C$12)+Inputs!$C$10+(Inputs!$C$6*G$13)*Inputs!$C$22+((Inputs!$C$13*(1+Inputs!$C$20)*Inputs!$C$12)+Inputs!$C$10-Inputs!$C$11)*Inputs!$C$23)-(Inputs!$C$6*G$13)-'Sources & Uses'!$C$23))^(1/5)-1 -> 0.15837011
B16: 9 | C16: =((Model!H9*$B16-('Debt Schedule'!H12+(Inputs!$C$6*C$13)-'Sources & Uses'!$C$15))/(((Inputs!$C$13*(1+Inputs!$C$20)*Inputs!$C$12)+Inputs!$C$10+(Inputs!$C$6*C$13)*Inputs!$C$22+((Inputs!$C$13*(1+Inputs!$C$20)*Inputs!$C$12)+Inputs!$C$10-Inputs!$C$11)*Inputs!$C$23)-(Inputs!$C$6*C$13)-'Sources & Uses'!$C$23))^(1/5)-1 -> 0.1286048 | D16: =((Model!H9*$B16-('Debt Schedule'!H12+(Inputs!$C$6*D$13)-'Sources & Uses'!$C$15))/(((Inputs!$C$13*(1+Inputs!$C$20)*Inputs!$C$12)+Inputs!$C$10+(Inputs!$C$6*D$13)*Inputs!$C$22+((Inputs!$C$13*(1+Inputs!$C$20)*Inputs!$C$12)+Inputs!$C$10-Inputs!$C$11)*Inputs!$C$23)-(Inputs!$C$6*D$13)-'Sources & Uses'!$C$23))^(1/5)-1 -> 0.13796675 | E16: =((Model!H9*$B16-('Debt Schedule'!H12+(Inputs!$C$6*E$13)-'Sources & Uses'!$C$15))/(((Inputs!$C$13*(1+Inputs!$C$20)*Inputs!$C$12)+Inputs!$C$10+(Inputs!$C$6*E$13)*Inputs!$C$22+((Inputs!$C$13*(1+Inputs!$C$20)*Inputs!$C$12)+Inputs!$C$10-Inputs!$C$11)*Inputs!$C$23)-(Inputs!$C$6*E$13)-'Sources & Uses'!$C$23))^(1/5)-1 -> 0.14890271 | F16: =((Model!H9*$B16-('Debt Schedule'!H12+(Inputs!$C$6*F$13)-'Sources & Uses'!$C$15))/(((Inputs!$C$13*(1+Inputs!$C$20)*Inputs!$C$12)+Inputs!$C$10+(Inputs!$C$6*F$13)*Inputs!$C$22+((Inputs!$C$13*(1+Inputs!$C$20)*Inputs!$C$12)+Inputs!$C$10-Inputs!$C$11)*Inputs!$C$23)-(Inputs!$C$6*F$13)-'Sources & Uses'!$C$23))^(1/5)-1 -> 0.16186179 | G16: =((Model!H9*$B16-('Debt Schedule'!H12+(Inputs!$C$6*G$13)-'Sources & Uses'!$C$15))/(((Inputs!$C$13*(1+Inputs!$C$20)*Inputs!$C$12)+Inputs!$C$10+(Inputs!$C$6*G$13)*Inputs!$C$22+((Inputs!$C$13*(1+Inputs!$C$20)*Inputs!$C$12)+Inputs!$C$10-Inputs!$C$11)*Inputs!$C$23)-(Inputs!$C$6*G$13)-'Sources & Uses'!$C$23))^(1/5)-1 -> 0.17748897
B17: 9.5 | C17: =((Model!H9*$B17-('Debt Schedule'!H12+(Inputs!$C$6*C$13)-'Sources & Uses'!$C$15))/(((Inputs!$C$13*(1+Inputs!$C$20)*Inputs!$C$12)+Inputs!$C$10+(Inputs!$C$6*C$13)*Inputs!$C$22+((Inputs!$C$13*(1+Inputs!$C$20)*Inputs!$C$12)+Inputs!$C$10-Inputs!$C$11)*Inputs!$C$23)-(Inputs!$C$6*C$13)-'Sources & Uses'!$C$23))^(1/5)-1 -> 0.14255634 | D17: =((Model!H9*$B17-('Debt Schedule'!H12+(Inputs!$C$6*D$13)-'Sources & Uses'!$C$15))/(((Inputs!$C$13*(1+Inputs!$C$20)*Inputs!$C$12)+Inputs!$C$10+(Inputs!$C$6*D$13)*Inputs!$C$22+((Inputs!$C$13*(1+Inputs!$C$20)*Inputs!$C$12)+Inputs!$C$10-Inputs!$C$11)*Inputs!$C$23)-(Inputs!$C$6*D$13)-'Sources & Uses'!$C$23))^(1/5)-1 -> 0.15273235 | E17: =((Model!H9*$B17-('Debt Schedule'!H12+(Inputs!$C$6*E$13)-'Sources & Uses'!$C$15))/(((Inputs!$C$13*(1+Inputs!$C$20)*Inputs!$C$12)+Inputs!$C$10+(Inputs!$C$6*E$13)*Inputs!$C$22+((Inputs!$C$13*(1+Inputs!$C$20)*Inputs!$C$12)+Inputs!$C$10-Inputs!$C$11)*Inputs!$C$23)-(Inputs!$C$6*E$13)-'Sources & Uses'!$C$23))^(1/5)-1 -> 0.16458894 | F17: =((Model!H9*$B17-('Debt Schedule'!H12+(Inputs!$C$6*F$13)-'Sources & Uses'!$C$15))/(((Inputs!$C$13*(1+Inputs!$C$20)*Inputs!$C$12)+Inputs!$C$10+(Inputs!$C$6*F$13)*Inputs!$C$22+((Inputs!$C$13*(1+Inputs!$C$20)*Inputs!$C$12)+Inputs!$C$10-Inputs!$C$11)*Inputs!$C$23)-(Inputs!$C$6*F$13)-'Sources & Uses'!$C$23))^(1/5)-1 -> 0.17859931 | G17: =((Model!H9*$B17-('Debt Schedule'!H12+(Inputs!$C$6*G$13)-'Sources & Uses'!$C$15))/(((Inputs!$C$13*(1+Inputs!$C$20)*Inputs!$C$12)+Inputs!$C$10+(Inputs!$C$6*G$13)*Inputs!$C$22+((Inputs!$C$13*(1+Inputs!$C$20)*Inputs!$C$12)+Inputs!$C$10-Inputs!$C$11)*Inputs!$C$23)-(Inputs!$C$6*G$13)-'Sources & Uses'!$C$23))^(1/5)-1 -> 0.19544116
B18: 10 | C18: =((Model!H9*$B18-('Debt Schedule'!H12+(Inputs!$C$6*C$13)-'Sources & Uses'!$C$15))/(((Inputs!$C$13*(1+Inputs!$C$20)*Inputs!$C$12)+Inputs!$C$10+(Inputs!$C$6*C$13)*Inputs!$C$22+((Inputs!$C$13*(1+Inputs!$C$20)*Inputs!$C$12)+Inputs!$C$10-Inputs!$C$11)*Inputs!$C$23)-(Inputs!$C$6*C$13)-'Sources & Uses'!$C$23))^(1/5)-1 -> 0.15585796 | D18: =((Model!H9*$B18-('Debt Schedule'!H12+(Inputs!$C$6*D$13)-'Sources & Uses'!$C$15))/(((Inputs!$C$13*(1+Inputs!$C$20)*Inputs!$C$12)+Inputs!$C$10+(Inputs!$C$6*D$13)*Inputs!$C$22+((Inputs!$C$13*(1+Inputs!$C$20)*Inputs!$C$12)+Inputs!$C$10-Inputs!$C$11)*Inputs!$C$23)-(Inputs!$C$6*D$13)-'Sources & Uses'!$C$23))^(1/5)-1 -> 0.16677802 | E18: =((Model!H9*$B18-('Debt Schedule'!H12+(Inputs!$C$6*E$13)-'Sources & Uses'!$C$15))/(((Inputs!$C$13*(1+Inputs!$C$20)*Inputs!$C$12)+Inputs!$C$10+(Inputs!$C$6*E$13)*Inputs!$C$22+((Inputs!$C$13*(1+Inputs!$C$20)*Inputs!$C$12)+Inputs!$C$10-Inputs!$C$11)*Inputs!$C$23)-(Inputs!$C$6*E$13)-'Sources & Uses'!$C$23))^(1/5)-1 -> 0.17947292 | F18: =((Model!H9*$B18-('Debt Schedule'!H12+(Inputs!$C$6*F$13)-'Sources & Uses'!$C$15))/(((Inputs!$C$13*(1+Inputs!$C$20)*Inputs!$C$12)+Inputs!$C$10+(Inputs!$C$6*F$13)*Inputs!$C$22+((Inputs!$C$13*(1+Inputs!$C$20)*Inputs!$C$12)+Inputs!$C$10-Inputs!$C$11)*Inputs!$C$23)-(Inputs!$C$6*F$13)-'Sources & Uses'!$C$23))^(1/5)-1 -> 0.19443676 | G18: =((Model!H9*$B18-('Debt Schedule'!H12+(Inputs!$C$6*G$13)-'Sources & Uses'!$C$15))/(((Inputs!$C$13*(1+Inputs!$C$20)*Inputs!$C$12)+Inputs!$C$10+(Inputs!$C$6*G$13)*Inputs!$C$22+((Inputs!$C$13*(1+Inputs!$C$20)*Inputs!$C$12)+Inputs!$C$10-Inputs!$C$11)*Inputs!$C$23)-(Inputs!$C$6*G$13)-'Sources & Uses'!$C$23))^(1/5)-1 -> 0.21237557
B20: The leverage grid holds the debt paydown path at the base case and flexes only the opening quantum, so it slightly flatters high-leverage cases (more debt would mean more interest and less sweep). It is shown to illustrate the direction and size of the effect, not to price a financing.

Sheet Summary
B1: Cognizant Technology Solutions — Leveraged Buyout — Debt Schedule and Returns | F1: IB PORTFOLIO
B2: The transaction on one page
B4: THE TRANSACTION
B5: Offer price per share (US$) | C5: ='Sources & Uses'!$C$5 -> 81.3605
B6: Premium to unaffected price | C6: =Inputs!$C$20 -> 0.3
B7: Transaction enterprise value | C7: ='Sources & Uses'!$C$7 -> 38954.924
B8: Entry EV / EBITDA | C8: ='Sources & Uses'!$C$8 -> 9.5806503
B9: Opening leverage (x EBITDA) | C9: ='Sources & Uses'!$C$27 -> 5.25
B10: Sponsor equity cheque | C10: ='Sources & Uses'!$C$24 -> 18924.903
B12: THE RETURN
B13: Exit EV / EBITDA assumed | C13: =Inputs!$C$40 -> 9
B14: Money multiple | C14: =Returns!$C$12 -> 2.0017797
B15: Internal rate of return | C15: =Returns!$C$13 -> 0.14890271
B16: Versus the 20% hurdle (pp) | C16: =Returns!$C$14 -> -5.1097287
B18: THE USEFUL OUTPUT
B19: Maximum offer price at a 20% return (US$) | C19: =Returns!$C$25 -> 73.777755
B20: Maximum premium to the unaffected price | C20: =Returns!$C$26 -> 0.17884085
B21: Unaffected share price (US$) | C21: =Inputs!$C$13 -> 62.585
B23: \u2022 Cognizant is buyable precisely because the sector de-rated: at roughly seven times EBITDA unaffected, a financial buyer can lever it. At twenty times, as the sector traded in 2021, no sponsor could.
B24: \u2022 The return is driven by debt paydown and margin expansion, not by multiple expansion — the exit multiple is set below entry on purpose. Any LBO whose return depends on selling at a higher multiple than it bought is an assumption dressed as an analysis.
B25: \u2022 The most useful number here is not the IRR at a 30% premium. It is the maximum price a sponsor could pay and still clear 20%, because that is the floor under the share price in any sale process, and it is the ninth bar on Project 5's football field.
B26: \u2022 The equity cheque is large enough that this would be a consortium deal. The arithmetic is unchanged; the practicality is not.

Sheet Checks
B1: Cognizant Technology Solutions — Leveraged Buyout — Debt Schedule and Returns | E1: IB PORTFOLIO
B2: Every check must read TRUE
B4: INTEGRITY CHECKS
B5: Sources equal uses | C5: =ABS('Sources & Uses'!$C$25-'Sources & Uses'!$C$18)<0.01 -> TRUE
B6: Sponsor equity is positive | C6: ='Sources & Uses'!$C$24>0 -> TRUE
B7: Opening leverage equals the sum of the tranches | C7: =ABS('Sources & Uses'!$C$27-(Inputs!$C$27+Inputs!$C$28))<0.001 -> TRUE
B8: Term loan balance never goes negative | C8: =MIN('Debt Schedule'!D9:H9)>=-0.01 -> TRUE
B9: Term loan closing balance ties to opening less repayments | C9: =ABS('Debt Schedule'!H9-('Debt Schedule'!H6+'Debt Schedule'!H7+'Debt Schedule'!H8))<0.01 -> TRUE
B10: Debt falls over the hold | C10: ='Debt Schedule'!H12<'Debt Schedule'!C12 -> TRUE
B11: Cash available for the sweep is positive in every year | C11: =MIN('Debt Schedule'!D29:H29)>0 -> TRUE
B12: Interest cover stays above 1.5x in every year | C12: =MIN('Debt Schedule'!D33:H33)>1.5 -> TRUE
B13: Leverage falls every year | C13: =AND('Debt Schedule'!H32<'Debt Schedule'!D32) -> TRUE
B14: Exit equity ties to exit enterprise value less net debt | C14: =ABS(Returns!$C$9-(Returns!$C$7+Returns!$C$8))<0.01 -> TRUE
B15: Money multiple and IRR are consistent | C15: =ABS((1+Returns!$C$13)^5-Returns!$C$12)<0.0001 -> TRUE
B16: Exit multiple is not above the entry multiple | C16: =Inputs!$C$40<='Sources & Uses'!$C$8 -> TRUE
B17: The maximum price is below the assumed offer price when the deal misses the hurdle | C17: =IF(Returns!$C$13<Inputs!$C$41,Returns!$C$25<'Sources & Uses'!$C$5,TRUE()) -> TRUE
B18: Base-case sensitivity cell reconciles to the Returns sheet | C18: =ABS(Sensitivity!E8-Returns!$C$13)<0.002 -> TRUE
B19: Entry EV/EBITDA is above the unaffected multiple | C19: ='Sources & Uses'!$C$8>Inputs!$C$17 -> TRUE
B20: Standalone figures tie to the reported FY2025 accounts | C20: =AND(ABS(Inputs!$C$6-4066)<1,ABS(Inputs!$C$5-21108)<1,ABS(Inputs!$C$12-488)<1) -> TRUE
B22: MODEL STATUS | C22: =IF(COUNTIF(C5:C20,FALSE())=0,"MODEL OK","CHECK FAILED") -> MODEL OK
B24: The check that the exit multiple is not above the entry multiple is a discipline check, not an arithmetic one. It fails the model if someone later raises the exit assumption to make the return work, which is the single most common way an LBO model is quietly bent.
