Workbook

Sheet Cover
B3: IB PORTFOLIO · PROJECT 14 OF 20
B4: Dabur India
B5: Quality of Earnings and Working-Capital Peg
B6: NSE: DABUR · ₹ crore unless stated · as of FY2026 consolidated accounts (year to 31 March 2026)
B9: What this is | C9: A buy-side quality-of-earnings review of Dabur India on the FY2023–FY2026 consolidated accounts: a bridge from the headline EBITDA a seller quotes to the operating EBITDA a buyer should pay for, a cash-conversion and accruals test, a working-capital analysis in days, and a working-capital peg built four ways for a sale and purchase agreement.
B11: How it is built | C11: • Operating EBITDA rebuilt from revenue, cost of sales and operating expenses and tied to reported operating income; treasury income, other non-operating income and exceptionals bridged out of the headline.
C12: • Cash conversion measured with treasury income removed from both EBITDA and operating cash flow; accruals ratio and revenue-quality flags across four years.
C13: • Trade working capital defined as the SPA would (receivables, inventory, payables; cash-free, debt-free), with days and the cash conversion cycle.
C14: • A peg from four methods — four-year average, average days, two-year run-rate, seasonality-adjusted — with weights as inputs and the spread between methods shown as the negotiating range.
B16: Contents | C16: Summary — earnings, cash, working capital
C17: Statements — four years as reported, with operating EBITDA rebuilt and tied
C18: EBITDA Bridge — headline to adjusted, and what the gap is worth
C19: Cash Conversion — EBITDA to cash, accruals, revenue quality
C20: Working Capital — trade working capital, days, the SPA definition
C21: Peg — four methods, weights, the adjustment
C22: Checks — fourteen tests; must read MODEL OK
B24: Key outputs (live) | C24: Headline EBITDA FY2026 (₹ crore) | E24: ='EBITDA Bridge'!$F$6 -> 3014.8
C25: Adjusted operating EBITDA | E25: ='EBITDA Bridge'!$F$10 -> 2473.2
C26: Adjusted as % of headline | E26: ='EBITDA Bridge'!$F$12 -> 0.82035293
C27: Cash conversion | E27: ='Cash Conversion'!$F$9 -> 1.1513921
C28: Working-capital peg | E28: =Peg!$C$20 -> 365.57919
C29: Adjustment if closing were today | E29: =Peg!$C$22 -> -282.87919
B31: Colour code | C31: Blue = hard-coded input
C32: Black = formula
C33: Green = link to another sheet
C34: Accent fill = scenario selector / key levers
B36: Sources | C36: Dabur India Limited consolidated financial statements FY2023–FY2026 (years to 31 March) via Yahoo Finance for DABUR.NS; quarterly revenue for the seasonality ratio from the same source.
C37: Total assets for the accruals ratio are approximated; the ratio is directional. Transaction multiple and peg weights are stated inputs.
C38: The review is a portfolio exercise on public information. Dabur is not, to the author's knowledge, in any sale process.
B40: Prepared by | C40: Jainam Mehta · github.com/jainammehta1215/ib-portfolio

Sheet Statements
B1: Dabur India — Quality of Earnings and Working-Capital Peg | G1: DABUR INDIA
B2: Four years of consolidated figures as reported — the raw material
B4: INCOME STATEMENT
C5: FY2023A | D5: FY2024A | E5: FY2025A | F5: FY2026A
B6: Revenue from operations | C6: 11426.5 | D6: 12261.6 | E6: 12400 | F6: 13042
B7: Cost of goods sold | C7: -6316.1 | D7: -6496.4 | E7: -6583.5 | F7: -6880.6
B8: Gross profit | C8: =C6+C7 -> 5110.4 | D8: =D6+D7 -> 5765.2 | E8: =E6+E7 -> 5816.5 | F8: =F6+F7 -> 6161.4
B9: Gross margin | C9: =C8/C6 -> 0.44724106 | D9: =D8/D6 -> 0.47018334 | E9: =E8/E6 -> 0.46907258 | F9: =F8/F6 -> 0.47242754
B10: Operating expenses before depreciation | C10: =-(11426.5-6316.1-1868.5-311) -> -2930.9 | D10: =-(12261.6-6496.4-2018.8-399.2) -> -3347.2 | E10: =-(12400-6583.5-1883.9-445.6) -> -3487 | F10: =-(13042-6880.6-2004.3-468.9) -> -3688.2
B11: Operating EBITDA (revenue − COGS − opex) | C11: =C8+C10 -> 2179.5 | D11: =D8+D10 -> 2418 | E11: =E8+E10 -> 2329.5 | F11: =F8+F10 -> 2473.2
B12: Depreciation and amortisation | C12: -311 | D12: -399.2 | E12: -445.6 | F12: -468.9
B13: Operating income (EBIT from operations) | C13: =C11+C12 -> 1868.5 | D13: =D11+D12 -> 2018.8 | E13: =E11+E12 -> 1883.9 | F13: =F11+F12 -> 2004.3
B14: check: reported operating income | C14: 1868.5 | D14: 2018.8 | E14: 1883.9 | F14: 2004.3
B15: Interest and treasury income | C15: 361.1 | D15: 393.1 | E15: 408.2 | F15: 366.2
B16: Other income, incl. gains on investments (derived: PBT − operating income − interest income + finance costs − exceptionals) | C16: =2218.7-1868.5-361.1+69.1-15.6 -> 42.6 | D16: =2358.7-2018.8-393.1+110.2--16.8 -> 73.8 | E16: =2257.9-1883.9-408.2+146.9--3.8 -> 116.5 | F16: =2420.4-2004.3-366.2+125.5--20 -> 195.4 | G16: The public data feed does not carry this line separately; it is the balancing item to reported profit before tax and is treated as non-operating
B17: Exceptional items (− = charge) | C17: 15.6 | D17: -16.8 | E17: -3.8 | F17: -20
B18: Finance costs | C18: -69.1 | D18: -110.2 | E18: -146.9 | F18: -125.5
B19: Profit before tax | C19: =SUM(C13:C18)-C14 -> 2218.7 | D19: =SUM(D13:D18)-D14 -> 2358.7 | E19: =SUM(E13:E18)-E14 -> 2257.9 | F19: =SUM(F13:F18)-F14 -> 2420.4
B20: check: reported profit before tax | C20: 2218.7 | D20: 2358.7 | E20: 2257.9 | F20: 2420.4
B21: Tax | C21: -517.4 | D21: -547.4 | E21: -517.5 | F21: -551.7
B22: Profit after tax (reported) | C22: 1707.2 | D22: 1842.7 | E22: 1767.6 | F22: 1895
B23: Effective tax rate | C23: =-C21/C19 -> 0.23319962 | D23: =-D21/D19 -> 0.23207699 | E23: =-E21/E19 -> 0.22919527 | F23: =-F21/F19 -> 0.22793753
B24: memo: share-based payment expense (inside opex) | C24: 51.2 | D24: 50.4 | E24: 13.5 | F24: 28.6
B26: BALANCE SHEET (selected)
B27: Trade receivables | C27: 848.8 | D27: 898.7 | E27: 888.5 | F27: 715.4
B28: Inventories | C28: 2024.2 | D28: 1947 | E28: 2300.1 | F28: 2321.6
B29: Trade payables | C29: 2186.6 | D29: 2421.7 | E29: 2825.3 | F29: 2954.3
B30: Current provisions | C30: 214 | D30: 249.9 | E30: 260.5 | F30: 310.2
B31: Cash and current investments (treasury book) | C31: 1051.6 | D31: 2323.1 | E31: 2655.5 | F31: 5147.8
B32: Borrowings | C32: 1173.8 | D32: 1365.1 | E32: 950.1 | F32: 1287.3
B33: Shareholders' equity | C33: 8973.3 | D33: 9866.3 | E33: 10800.7 | F33: 11419.5
B34: Property, plant and equipment | C34: 2408.7 | D34: 2770 | E34: 2966.3 | F34: 2977.4
B35: Goodwill and intangibles | C35: 1298 | D35: 1231.8 | E35: 1148.9 | F35: 1056.5
B37: CASH FLOW (selected)
B38: Net cash from operating activities (after tax) | C38: 1488.4 | D38: 2013.5 | E38: 1986.8 | F38: 2578.6
B39: Capital expenditure | C39: -509.1 | D39: -563.9 | E39: -569.5 | F39: -420.1
B40: Free cash flow | C40: =C38+C39 -> 979.3 | D40: =D38+D39 -> 1449.6 | E40: =E38+E39 -> 1417.3 | F40: =F38+F39 -> 2158.5
B41: Dividends paid | C41: -921.3 | D41: -965.8 | E41: -974.8 | F41: -1419
B42: Yahoo Finance's headline 'EBITDA' for Dabur is EBIT plus depreciation, where EBIT is profit before tax plus finance costs — so it includes treasury income and exceptional items. That headline is what a seller quotes. Operating EBITDA above is rebuilt from revenue, cost of sales and operating expenses, and ties to reported operating income on the check row.

Sheet EBITDA Bridge
B1: Dabur India — Quality of Earnings and Working-Capital Peg | G1: DABUR INDIA
B2: From the headline the seller quotes to the EBITDA a buyer should pay for
B4: HEADLINE TO ADJUSTED EBITDA
C5: FY2023A | D5: FY2024A | E5: FY2025A | F5: FY2026A
B6: Headline EBITDA (PBT + finance costs + D&A) | C6: =Statements!$C$19-Statements!$C$18-Statements!$C$12 -> 2598.8 | D6: =Statements!$D$19-Statements!$D$18-Statements!$D$12 -> 2868.1 | E6: =Statements!$E$19-Statements!$E$18-Statements!$E$12 -> 2850.4 | F6: =Statements!$F$19-Statements!$F$18-Statements!$F$12 -> 3014.8
B7: Less: interest and treasury income | C7: =-Statements!$C$15 -> -361.1 | D7: =-Statements!$D$15 -> -393.1 | E7: =-Statements!$E$15 -> -408.2 | F7: =-Statements!$F$15 -> -366.2
B8: Less: other income incl. investment gains (derived) | C8: =-Statements!$C$16 -> -42.6 | D8: =-Statements!$D$16 -> -73.8 | E8: =-Statements!$E$16 -> -116.5 | F8: =-Statements!$F$16 -> -195.4
B9: Add back / (remove): exceptional items | C9: =-Statements!$C$17 -> -15.6 | D9: =-Statements!$D$17 -> 16.8 | E9: =-Statements!$E$17 -> 3.8 | F9: =-Statements!$F$17 -> 20
B10: Adjusted operating EBITDA | C10: =SUM(C6:C9) -> 2179.5 | D10: =SUM(D6:D9) -> 2418 | E10: =SUM(E6:E9) -> 2329.5 | F10: =SUM(F6:F9) -> 2473.2
B11: check: operating EBITDA from the Statements sheet, ex exceptionals | C11: =Statements!$C$11 -> 2179.5 | D11: =Statements!$D$11 -> 2418 | E11: =Statements!$E$11 -> 2329.5 | F11: =Statements!$F$11 -> 2473.2
B12: Adjusted as % of headline | C12: ='EBITDA Bridge'!$C$10/'EBITDA Bridge'!$C$6 -> 0.8386563 | D12: ='EBITDA Bridge'!$D$10/'EBITDA Bridge'!$D$6 -> 0.84306684 | E12: ='EBITDA Bridge'!$E$10/'EBITDA Bridge'!$E$6 -> 0.81725372 | F12: ='EBITDA Bridge'!$F$10/'EBITDA Bridge'!$F$6 -> 0.82035293
B13: Adjusted EBITDA margin | C13: ='EBITDA Bridge'!$C$10/Statements!$C$6 -> 0.19074082 | D13: ='EBITDA Bridge'!$D$10/Statements!$D$6 -> 0.19720102 | E13: ='EBITDA Bridge'!$E$10/Statements!$E$6 -> 0.1878629 | F13: ='EBITDA Bridge'!$F$10/Statements!$F$6 -> 0.18963349
B14: Headline EBITDA margin | C14: ='EBITDA Bridge'!$C$6/Statements!$C$6 -> 0.22743622 | D14: ='EBITDA Bridge'!$D$6/Statements!$D$6 -> 0.23390911 | E14: ='EBITDA Bridge'!$E$6/Statements!$E$6 -> 0.22987097 | F14: ='EBITDA Bridge'!$F$6/Statements!$F$6 -> 0.23116086
B16: ITEMS CONSIDERED AND LEFT IN
B17: Share-based payments as % of adjusted EBITDA (left in as a real cost) | C17: =Statements!$C$24/'EBITDA Bridge'!$C$10 -> 0.023491627 | D17: =Statements!$D$24/'EBITDA Bridge'!$D$10 -> 0.020843672 | E17: =Statements!$E$24/'EBITDA Bridge'!$E$10 -> 0.005795235 | F17: =Statements!$F$24/'EBITDA Bridge'!$F$10 -> 0.011563966
B18: Decline in intangibles (amortisation, inside D&A, below EBITDA) | D18: =Statements!$C$35-Statements!$D$35 -> 66.2 | E18: =Statements!$D$35-Statements!$E$35 -> 82.9 | F18: =Statements!$E$35-Statements!$F$35 -> 92.4
B20: WHAT THE DIFFERENCE IS WORTH
B21: Illustrative transaction multiple of EBITDA | C21: 20 | G21: Indian consumer staples change hands at high-teens to mid-twenties
B22: Headline less adjusted EBITDA, FY2026 | C22: ='EBITDA Bridge'!$F$6-'EBITDA Bridge'!$F$10 -> 541.6
B23: Value at the multiple — what a buyer would overpay on the headline | C23: ='EBITDA Bridge'!$C$22*'EBITDA Bridge'!$C$21 -> 10832
B24: Treasury book that generates the income (cash and current investments) | C24: =Statements!$F$31 -> 5147.8 | G24: The buyer gets this as cash at closing — once. Paying a multiple for its income as well is paying twice
B25: Overpayment as a multiple of the treasury book itself | C25: ='EBITDA Bridge'!$C$23/'EBITDA Bridge'!$C$24 -> 2.1041999
B26: Nearly a fifth of the headline EBITDA is treasury income on a cash pile of over ₹5,000 crore. In a transaction the cash transfers at face value, so a buyer who capitalises its income at 20x has paid for it twice. This is the single most common adjustment in an Indian consumer QoE and it is usually the largest.

Sheet Cash Conversion
B1: Dabur India — Quality of Earnings and Working-Capital Peg | G1: DABUR INDIA
B2: Does the adjusted EBITDA turn into cash?
B4: EBITDA TO CASH
C5: FY2023A | D5: FY2024A | E5: FY2025A | F5: FY2026A
B6: Adjusted operating EBITDA | C6: ='EBITDA Bridge'!$C$10 -> 2179.5 | D6: ='EBITDA Bridge'!$D$10 -> 2418 | E6: ='EBITDA Bridge'!$E$10 -> 2329.5 | F6: ='EBITDA Bridge'!$F$10 -> 2473.2
B7: Less: tax (charge used as proxy for cash tax) | C7: =Statements!$C$21 -> -517.4 | D7: =Statements!$D$21 -> -547.4 | E7: =Statements!$E$21 -> -517.5 | F7: =Statements!$F$21 -> -551.7
B8: Operating cash flow before interest received (reported OCF less treasury income) | C8: =Statements!$C$38-Statements!$C$15 -> 1127.3 | D8: =Statements!$D$38-Statements!$D$15 -> 1620.4 | E8: =Statements!$E$38-Statements!$E$15 -> 1578.6 | F8: =Statements!$F$38-Statements!$F$15 -> 2212.4 | G8: Reported OCF includes interest received on the treasury book; it is removed for the same reason as on the Bridge
B9: Cash conversion: OCF before interest / (adjusted EBITDA − tax) | C9: ='Cash Conversion'!$C$8/('Cash Conversion'!$C$6+'Cash Conversion'!$C$7) -> 0.67823837 | D9: ='Cash Conversion'!$D$8/('Cash Conversion'!$D$6+'Cash Conversion'!$D$7) -> 0.86624612 | E9: ='Cash Conversion'!$E$8/('Cash Conversion'!$E$6+'Cash Conversion'!$E$7) -> 0.87119205 | F9: ='Cash Conversion'!$F$8/('Cash Conversion'!$F$6+'Cash Conversion'!$F$7) -> 1.1513921
B10: for comparison: reported OCF / headline EBITDA | C10: =Statements!$C$38/'EBITDA Bridge'!$C$6 -> 0.57272587 | D10: =Statements!$D$38/'EBITDA Bridge'!$D$6 -> 0.7020327 | E10: =Statements!$E$38/'EBITDA Bridge'!$E$6 -> 0.69702498 | F10: =Statements!$F$38/'EBITDA Bridge'!$F$6 -> 0.85531379
B11: Capex / depreciation | C11: =-Statements!$C$39/-Statements!$C$12 -> 1.6369775 | D11: =-Statements!$D$39/-Statements!$D$12 -> 1.4125752 | E11: =-Statements!$E$39/-Statements!$E$12 -> 1.2780521 | F11: =-Statements!$F$39/-Statements!$F$12 -> 0.89592664
B12: Free cash flow / profit after tax | C12: =Statements!$C$40/Statements!$C$22 -> 0.57362933 | D12: =Statements!$D$40/Statements!$D$22 -> 0.78667173 | E12: =Statements!$E$40/Statements!$E$22 -> 0.80182168 | F12: =Statements!$F$40/Statements!$F$22 -> 1.1390501
B14: ACCRUALS
B15: Accruals ratio: (profit after tax − OCF) / average total assets | C15: =(Statements!$C$22-Statements!$C$38)/13800 -> 0.015855072 | D15: =(Statements!$D$22-Statements!$D$38)/14900 -> -0.011463087 | E15: =(Statements!$E$22-Statements!$E$38)/16100 -> -0.013614907 | F15: =(Statements!$F$22-Statements!$F$38)/18100 -> -0.037767956 | G15: Total assets are approximated (equity + debt + payables + provisions + other); negative is good, meaning cash exceeds profit
B16: Direction over four years | C16: =IF('Cash Conversion'!$F$15<'Cash Conversion'!$C$15,"Improving (cash gaining on profit)","Deteriorating") -> Improving (cash gaining on profit)
B18: REVENUE QUALITY
B19: Revenue growth | D19: =Statements!$D$6/Statements!$C$6-1 -> 0.073084497 | E19: =Statements!$E$6/Statements!$D$6-1 -> 0.011287271 | F19: =Statements!$F$6/Statements!$E$6-1 -> 0.051774194
B20: Receivables growth | D20: =Statements!$D$27/Statements!$C$27-1 -> 0.058788878 | E20: =Statements!$E$27/Statements!$D$27-1 -> -0.011349727 | F20: =Statements!$F$27/Statements!$E$27-1 -> -0.19482273
B21: Inventory growth | D21: =Statements!$D$28/Statements!$C$28-1 -> -0.038138524 | E21: =Statements!$E$28/Statements!$D$28-1 -> 0.18135593 | F21: =Statements!$F$28/Statements!$E$28-1 -> 0.0093474197
B22: Flag: receivables or inventory growing faster than revenue | D22: =IF(OR('Cash Conversion'!$D$20>'Cash Conversion'!$D$19+0.05,'Cash Conversion'!$D$21>'Cash Conversion'!$D$19+0.05),"Review","Clean") -> Clean | E22: =IF(OR('Cash Conversion'!$E$20>'Cash Conversion'!$E$19+0.05,'Cash Conversion'!$E$21>'Cash Conversion'!$E$19+0.05),"Review","Clean") -> Review | F22: =IF(OR('Cash Conversion'!$F$20>'Cash Conversion'!$F$19+0.05,'Cash Conversion'!$F$21>'Cash Conversion'!$F$19+0.05),"Review","Clean") -> Clean
B23: FY2025 inventory grew 18% on 1% revenue growth — the year of the distributor inventory correction that Dabur disclosed. FY2026 receivables then fell 19% on 5% growth as channel stock normalised. Both are consistent with the company's own account and neither is a revenue-recognition concern; a QoE would still ask for the channel-inventory data to confirm it.

Sheet Working Capital
B1: Dabur India — Quality of Earnings and Working-Capital Peg | G1: DABUR INDIA
B2: Days, trends and the definition the SPA will use
B4: TRADE WORKING CAPITAL
C5: FY2023A | D5: FY2024A | E5: FY2025A | F5: FY2026A
B6: Trade receivables | C6: =Statements!$C$27 -> 848.8 | D6: =Statements!$D$27 -> 898.7 | E6: =Statements!$E$27 -> 888.5 | F6: =Statements!$F$27 -> 715.4
B7: Inventories | C7: =Statements!$C$28 -> 2024.2 | D7: =Statements!$D$28 -> 1947 | E7: =Statements!$E$28 -> 2300.1 | F7: =Statements!$F$28 -> 2321.6
B8: Less: trade payables | C8: =-Statements!$C$29 -> -2186.6 | D8: =-Statements!$D$29 -> -2421.7 | E8: =-Statements!$E$29 -> -2825.3 | F8: =-Statements!$F$29 -> -2954.3
B9: Trade working capital | C9: =SUM(C6:C8) -> 686.4 | D9: =SUM(D6:D8) -> 424 | E9: =SUM(E6:E8) -> 363.3 | F9: =SUM(F6:F8) -> 82.7
B10: as % of revenue | C10: ='Working Capital'!$C$9/Statements!$C$6 -> 0.060070888 | D10: ='Working Capital'!$D$9/Statements!$D$6 -> 0.0345795 | E10: ='Working Capital'!$E$9/Statements!$E$6 -> 0.029298387 | F10: ='Working Capital'!$F$9/Statements!$F$6 -> 0.006341052
B12: DAYS
B13: Receivable days (on revenue) | C13: =Statements!$C$27/Statements!$C$6*365 -> 27.113464 | D13: =Statements!$D$27/Statements!$D$6*365 -> 26.752259 | E13: =Statements!$E$27/Statements!$E$6*365 -> 26.153427 | F13: =Statements!$F$27/Statements!$F$6*365 -> 20.021546
B14: Inventory days (on cost of goods sold) | C14: =Statements!$C$28/-Statements!$C$7*365 -> 116.97614 | D14: =Statements!$D$28/-Statements!$D$7*365 -> 109.39212 | E14: =Statements!$E$28/-Statements!$E$7*365 -> 127.5213 | F14: =Statements!$F$28/-Statements!$F$7*365 -> 123.15554
B15: Payable days (on cost of goods sold) | C15: =Statements!$C$29/-Statements!$C$7*365 -> 126.36105 | D15: =Statements!$D$29/-Statements!$D$7*365 -> 136.06313 | E15: =Statements!$E$29/-Statements!$E$7*365 -> 156.63925 | F15: =Statements!$F$29/-Statements!$F$7*365 -> 156.71882
B16: Cash conversion cycle (days) | C16: ='Working Capital'!$C$13+'Working Capital'!$C$14-'Working Capital'!$C$15 -> 17.728559 | D16: ='Working Capital'!$D$13+'Working Capital'!$D$14-'Working Capital'!$D$15 -> 0.081256684 | E16: ='Working Capital'!$E$13+'Working Capital'!$E$14-'Working Capital'!$E$15 -> -2.964519 | F16: ='Working Capital'!$F$13+'Working Capital'!$F$14-'Working Capital'!$F$15 -> -13.541734
B18: DEFINITION FOR THE SALE AND PURCHASE AGREEMENT
B19: Included: trade receivables, inventories, trade payables. Excluded: cash and investments (cash-free / debt-free), borrowings, tax balances, provisions, capex creditors.
B20: Current provisions (excluded from the peg; treated as debt-like) | C20: =Statements!$C$30 -> 214 | D20: =Statements!$D$30 -> 249.9 | E20: =Statements!$E$30 -> 260.5 | F20: =Statements!$F$30 -> 310.2
B21: Payable days have stretched from 126 to 157 over four years while inventory days sat near 120. A buyer will ask whether the payables extension is structural (supplier financing, longer terms) or a closing-date effect that unwinds after completion. If it unwinds, the buyer funds roughly ₹500 crore of working capital in the first year. That question, not the peg arithmetic, is where the negotiation happens.

Sheet Peg
B1: Dabur India — Quality of Earnings and Working-Capital Peg | F1: DABUR INDIA
B2: A normal level of working capital, so the buyer pays for the business and not for the closing date
B4: METHOD 1 — AVERAGE OF THE FOUR YEAR-END BALANCES
B5: Average trade working capital, FY2023–FY2026 | C5: =AVERAGE('Working Capital'!$C$9,'Working Capital'!$D$9,'Working Capital'!$E$9,'Working Capital'!$F$9) -> 389.1
B6: METHOD 2 — AVERAGE DAYS APPLIED TO THE LATEST YEAR
B7: Average trade working capital as % of revenue, four years | C7: =AVERAGE('Working Capital'!$C$10,'Working Capital'!$D$10,'Working Capital'!$E$10,'Working Capital'!$F$10) -> 0.032572457
B8: Applied to FY2026 revenue | C8: =Peg!$C$7*Statements!$F$6 -> 424.80998
B9: METHOD 3 — LAST TWO YEARS ONLY (the post-correction run-rate)
B10: Average of FY2025 and FY2026 | C10: =AVERAGE('Working Capital'!$E$9,'Working Capital'!$F$9) -> 223
B11: METHOD 4 — SEASONALITY-ADJUSTED (stated)
B12: Ratio of average quarterly revenue to the March quarter | C12: =AVERAGE(2830.1,3404.6,3558.6,3038)/AVERAGE(2830.1,3038) -> 1.0933096 | F12: March is Dabur's seasonally softest quarter; a March year-end understates average working capital
B13: Method 1 scaled by the seasonality ratio | C13: =Peg!$C$5*Peg!$C$12 -> 425.40676
B15: THE PEG
B16: Weight on method 1 | C16: 0.25
B17: Weight on method 2 | C17: 0.25
B18: Weight on method 3 | C18: 0.25
B19: Weight on method 4 | C19: 0.25
B20: Proposed working-capital peg | C20: =Peg!$C$16*Peg!$C$5+Peg!$C$17*Peg!$C$8+Peg!$C$18*Peg!$C$10+Peg!$C$19*Peg!$C$13 -> 365.57919
B21: Trade working capital at the latest balance sheet (31 March 2026) | C21: ='Working Capital'!$F$9 -> 82.7
B22: Price adjustment if closing were today: closing less peg (− = buyer receives) | C22: =Peg!$C$21-Peg!$C$20 -> -282.87919
B23: per share (₹) | C23: =Peg!$C$22/177.7 -> -1.5918919
B24: as % of market capitalisation | C24: =Peg!$C$22/(387.45*177.7) -> -0.0041086382
B26: HOW SENSITIVE THE ADJUSTMENT IS TO THE METHOD
B27: Lowest of the four methods | C27: =MIN(Peg!$C$5,Peg!$C$8,Peg!$C$10,Peg!$C$13) -> 223
B28: Highest of the four methods | C28: =MAX(Peg!$C$5,Peg!$C$8,Peg!$C$10,Peg!$C$13) -> 425.40676
B29: Spread between them — the size of the argument | C29: =Peg!$C$28-Peg!$C$27 -> 202.40676
B30: The seller will argue for method 3 (the recent run-rate, lowest peg, smallest adjustment); the buyer for method 4 (seasonally adjusted, highest peg). The spread between them is the negotiating range. A real peg uses twelve to twenty-four monthly balance sheets from the data room; Indian filers publish only half-yearly, so this one uses year-ends and a stated seasonality ratio, and says so.

Sheet Summary
B1: Dabur India — Quality of Earnings and Working-Capital Peg | F1: DABUR INDIA
B2: The quality-of-earnings findings on one page
B4: EARNINGS
B5: Headline EBITDA, FY2026 (₹ crore) | C5: ='EBITDA Bridge'!$F$6 -> 3014.8
B6: Adjusted operating EBITDA, FY2026 | C6: ='EBITDA Bridge'!$F$10 -> 2473.2
B7: Adjusted as % of headline | C7: ='EBITDA Bridge'!$F$12 -> 0.82035293
B8: Adjusted EBITDA margin | C8: ='EBITDA Bridge'!$F$13 -> 0.18963349
B9: Value of the difference at 20x | C9: ='EBITDA Bridge'!$C$23 -> 10832
B11: CASH
B12: Cash conversion, FY2026 (before treasury income) | C12: ='Cash Conversion'!$F$9 -> 1.1513921
B13: Capex / depreciation, FY2026 | C13: ='Cash Conversion'!$F$11 -> 0.89592664
B14: Accruals ratio, FY2026 | C14: ='Cash Conversion'!$F$15 -> -0.037767956
B15: Accruals direction | C15: ='Cash Conversion'!$C$16 -> Improving (cash gaining on profit)
B17: WORKING CAPITAL
B18: Trade working capital at 31 March 2026 | C18: =Peg!$C$21 -> 82.7
B19: Proposed peg | C19: =Peg!$C$20 -> 365.57919
B20: Price adjustment if closing were today (− = buyer receives) | C20: =Peg!$C$22 -> -282.87919
B21: Spread between peg methods | C21: =Peg!$C$29 -> 202.40676
B22: Payable days: FY2023 → FY2026 | C22: =TEXT('Working Capital'!$C$15,"0")&" → "&TEXT('Working Capital'!$F$15,"0") -> 126 → 157
B24: • The headline EBITDA overstates operating earnings by close to a fifth, and almost all of it is interest on a ₹5,000-crore treasury book. The cash transfers at face value in any deal; a buyer who also capitalises its income at 20x has paid for the same asset twice. This is the finding a QoE exists to make.
B25: • Cash conversion is strong once the same treasury income is removed from both sides, capex runs close to depreciation, and accruals are negative and improving. The operating earnings are real.
B26: • Working capital is the negotiation. Payables have stretched by a month over four years, trade working capital has fallen to almost nothing, and a March year-end is seasonally soft. Whether the payables extension holds after completion is worth around ₹500 crore to whoever gets the answer right.
B27: • The peg spread between the seller's method and the buyer's is the size of the argument, and it is small relative to the equity value. The EBITDA adjustment is where the money is.

Sheet Checks
B1: Dabur India — Quality of Earnings and Working-Capital Peg | E1: DABUR INDIA
B2: Every check must read TRUE
B4: INTEGRITY CHECKS
B5: Rebuilt operating income ties to reported in every year | C5: =AND(ABS(Statements!$C$13-Statements!$C$14)<1,ABS(Statements!$D$13-Statements!$D$14)<1,ABS(Statements!$E$13-Statements!$E$14)<1,ABS(Statements!$F$13-Statements!$F$14)<1) -> TRUE
B6: Rebuilt profit before tax ties to reported in every year | C6: =AND(ABS(Statements!$C$19-Statements!$C$20)<1,ABS(Statements!$D$19-Statements!$D$20)<1,ABS(Statements!$E$19-Statements!$E$20)<1,ABS(Statements!$F$19-Statements!$F$20)<1) -> TRUE
B7: Derived other income is between 0% and 3% of revenue in every year (a plausibility bound on the plug) | C7: =AND(Statements!$C$16>=0,Statements!$C$16<0.03*Statements!$C$6,Statements!$D$16>=0,Statements!$D$16<0.03*Statements!$D$6,Statements!$E$16>=0,Statements!$E$16<0.03*Statements!$E$6,Statements!$F$16>=0,Statements!$F$16<0.03*Statements!$F$6) -> TRUE
B8: Adjusted EBITDA on the Bridge equals operating EBITDA on the Statements | C8: =AND(ABS('EBITDA Bridge'!$C$10-'EBITDA Bridge'!$C$11)<1,ABS('EBITDA Bridge'!$D$10-'EBITDA Bridge'!$D$11)<1,ABS('EBITDA Bridge'!$E$10-'EBITDA Bridge'!$E$11)<1,ABS('EBITDA Bridge'!$F$10-'EBITDA Bridge'!$F$11)<1) -> TRUE
B9: Adjusted EBITDA is below headline in every year | C9: =AND('EBITDA Bridge'!$C$10<'EBITDA Bridge'!$C$6,'EBITDA Bridge'!$D$10<'EBITDA Bridge'!$D$6,'EBITDA Bridge'!$E$10<'EBITDA Bridge'!$E$6,'EBITDA Bridge'!$F$10<'EBITDA Bridge'!$F$6) -> TRUE
B10: Effective tax rate is between 20% and 26% in every year | C10: =AND(Statements!$C$23>0.2,Statements!$C$23<0.26,Statements!$D$23>0.2,Statements!$D$23<0.26,Statements!$E$23>0.2,Statements!$E$23<0.26,Statements!$F$23>0.2,Statements!$F$23<0.26) -> TRUE
B11: Cash conversion before treasury income is between 60% and 130% in every year | C11: =AND('Cash Conversion'!$C$9>0.6,'Cash Conversion'!$C$9<1.3,'Cash Conversion'!$D$9>0.6,'Cash Conversion'!$D$9<1.3,'Cash Conversion'!$E$9>0.6,'Cash Conversion'!$E$9<1.3,'Cash Conversion'!$F$9>0.6,'Cash Conversion'!$F$9<1.3) -> TRUE
B12: Cash conversion cycle equals DSO + DIO − DPO | C12: =AND(ABS('Working Capital'!$C$16-('Working Capital'!$C$13+'Working Capital'!$C$14-'Working Capital'!$C$15))<0.01,ABS('Working Capital'!$D$16-('Working Capital'!$D$13+'Working Capital'!$D$14-'Working Capital'!$D$15))<0.01,ABS('Working Capital'!$E$16-('Working Capital'!$E$13+'Working Capital'!$E$14-'Working Capital'!$E$15))<0.01,ABS('Working Capital'!$F$16-('Working Capital'!$F$13+'Working Capital'!$F$14-'Working Capital'!$F$15))<0.01) -> TRUE
B13: Payable days have lengthened over the period | C13: ='Working Capital'!$F$15>'Working Capital'!$C$15 -> TRUE
B14: Peg weights sum to 100% | C14: =ABS(Peg!$C$16+Peg!$C$17+Peg!$C$18+Peg!$C$19-1)<0.0001 -> TRUE
B15: Peg lies between the lowest and highest method | C15: =AND(Peg!$C$20>=Peg!$C$27,Peg!$C$20<=Peg!$C$28) -> TRUE
B16: Price adjustment equals closing working capital less the peg | C16: =ABS(Peg!$C$22-(Peg!$C$21-Peg!$C$20))<0.01 -> TRUE
B17: Seasonality ratio is above 1 (March is a soft quarter) | C17: =Peg!$C$12>1 -> TRUE
B18: Treasury income is below 5% of the treasury book (a sanity check on the classification) | C18: =Statements!$F$15/Statements!$F$31<0.1 -> TRUE
B20: MODEL STATUS | C20: =IF(COUNTIF(C5:C18,FALSE())=0,"MODEL OK","CHECK FAILED") -> MODEL OK
B22: The first two checks matter most: the operating EBITDA used throughout is rebuilt from revenue and costs and must tie to the reported operating income and profit before tax. Everything after that inherits its credibility from them.
