Workbook

Sheet Cover
B3: IB PORTFOLIO · PROJECT 17 OF 20
B4: Kellanova / Mars
B5: Fairness Opinion Replication
B6: NYSE: K · acquired by Mars · US$ millions · per-share values in US$ · as of DEFM14A filed 26 Sep 2024 · valuation date 30 Jun 2024
B9: What this is | C9: A replication of the fairness-opinion analyses Goldman Sachs and Lazard delivered to Kellanova's board on Mars's US$83.50 cash offer, rebuilt from the inputs disclosed in the definitive proxy of 26 September 2024: management projections, discount rates, multiple and premia ranges, and the undisturbed price. Each rebuilt range is tested against the range the proxy reports.
B11: How it is built | C11: • Fully diluted shares and adjusted net debt back-solved from a single disclosed range (Goldman's precedent transactions), then held fixed for every other analysis so that each is a genuine test.
C12: • Goldman: DCF with a terminal multiple, present value of future share price with dividends, premia paid on two bases, precedents, and reference trading multiples. Lazard: DCF with perpetuity growth, EBITDA and P/E comparables, precedents, premia, analyst targets and trading range.
C13: • A football field placing the offer against all twelve ranges, with the deviation of each rebuilt bound from the proxy.
B15: Contents | C15: Summary — the deal, the replication, the reading
C16: Inputs — everything disclosed; the two back-solved figures
C17: Goldman Sachs — five analyses rebuilt
C18: Lazard — four analyses rebuilt
C19: Football Field — twelve ranges against US$83.50
C20: Checks — fifteen tests; must read MODEL OK
B22: Key outputs (live) | C22: Offer per share (US$) | E22: =Inputs!$C$5 -> 83.5
C23: Premium to undisturbed | E23: =Inputs!$C$7 -> 0.32581772
C24: EV / 2024E EBITDA at the offer | E24: ='Goldman Sachs'!$C$35 -> 15.979739
C25: GS DCF rebuilt: low | E25: ='Goldman Sachs'!$C$8 -> 67.78774
C26: GS DCF rebuilt: high | E26: ='Goldman Sachs'!$C$9 -> 83.189775
C27: Largest deviation from the proxy, core analyses (US$) | E27: ='Football Field'!$C$23 -> 2.5173404
B29: Colour code | C29: Blue = hard-coded input
C30: Black = formula
C31: Green = link to another sheet
C32: Accent fill = scenario selector / key levers
B34: Sources | C34: Kellanova definitive proxy statement (DEFM14A), SEC accession 0001193125-24-226970, filed 26 September 2024: 'Certain Financial Projections', 'Opinion of Goldman Sachs & Co. LLC', 'Opinion of Lazard Frères & Co. LLC', and the record-date share count.
C35: Dividends per share after 2024 and the split of 2024 cash flow either side of 30 June are stated inputs; every other figure is quoted from the proxy or derived from it as labelled.
C36: The exercise is a replication of disclosed analyses for learning. It expresses no view on either advisor's judgement, and it is not advice.
B38: Prepared by | C38: Jainam Mehta · github.com/jainammehta1215/ib-portfolio

Sheet Inputs
B1: Kellanova / Mars — Fairness Opinion Replication | G1: KELLANOVA
B2: Everything the proxy discloses, and the two figures back-solved from it
B4: TRANSACTION
B5: Merger consideration per share (cash) | C5: 83.5
B6: Undisturbed closing price, 2 August 2024 | C6: 62.98 | G6: Also the 52-week high on that date
B7: Premium to undisturbed | C7: =Inputs!$C$5/Inputs!$C$6-1 -> 0.32581772
B8: Shares outstanding at the record date (millions) | C8: 344.68476
B10: MANAGEMENT PROJECTIONS (proxy, 'Certain Financial Projections')
C11: 2024E | D11: 2025E | E11: 2026E | F11: 2027E
B12: Net sales | C12: 12782 | D12: 13366 | E12: 13670 | F12: 14098
B13: Adjusted EBITDA | C13: 2235 | D13: 2401 | E13: 2553 | F13: 2741
B14: Net operating profit after tax | C14: 1322 | D14: 1506 | E14: 1595 | F14: 1705
B15: Unlevered free cash flow | C15: 1102 | D15: 1348 | E15: 1359 | F15: 1533
B16: Adjusted earnings per share | C16: 3.7 | D16: 3.99 | E16: 4.26 | F16: 4.63
B17: Dividends per share (stated: 2024 run-rate, then +3.5% a year) | C17: 2.28 | D17: 2.36 | E17: 2.44
B19: BACK-SOLVED FROM GOLDMAN'S PRECEDENT-TRANSACTION RANGE
B20: Goldman applied 12.1x–21.5x to FY1 (2024E) EBITDA and reported $58.81–$118.63 per share. Two equations, two unknowns.
B21: Fully diluted shares (millions) = (21.5 − 12.1) × FY1 EBITDA / (118.63 − 58.81) | C21: =(21.5-12.1)*Inputs!$C$13/(118.63-58.81) -> 351.20361 | G21: About 2% above the record-date basic count — the treasury-stock dilution one would expect
B22: Adjusted net debt = 12.1 × FY1 EBITDA − 58.81 × diluted shares | C22: =12.1*Inputs!$C$13-58.81*Inputs!$C$21 -> 6389.2156 | G22: Financial net debt plus factored receivables and minorities less unconsolidated investments, as the proxy defines it
B23: check: 21.5x reproduces the top of the range | C23: =(21.5*Inputs!$C$13-Inputs!$C$22)/Inputs!$C$21 -> 118.63
B25: HALF-YEAR CONVENTION
B26: Share of 2024E unlevered free cash flow falling after 30 June 2024 | C26: 0.5 | G26: The proxy discounts cash flow from 1 July 2024; the split is not disclosed
B27: Mid-year discount period for H2 2024 (years from 30 June 2024) | C27: 0.25
B28: Every number above the back-solved section is quoted from the proxy. Diluted shares and adjusted net debt are the only derived inputs, and they are derived from a single disclosed analysis so that every other analysis is a genuine test.

Sheet Goldman Sachs
B1: Kellanova / Mars — Fairness Opinion Replication | G1: KELLANOVA
B2: Five analyses rebuilt from the disclosed inputs, each against the range the proxy reports
B4: 1. ILLUSTRATIVE DISCOUNTED CASH FLOW — WACC 6.0–7.0%, terminal 12.0–14.0x 2027E EBITDA, mid-year, from 30 June 2024
C5: H2 2024 | D5: 2025E | E5: 2026E | F5: 2027E
B6: Unlevered free cash flow | C6: =Inputs!$C$15*Inputs!$C$26 -> 551 | D6: =Inputs!$D$15 -> 1348 | E6: =Inputs!$E$15 -> 1359 | F6: =Inputs!$F$15 -> 1533
B7: Discount period (years, mid-period) | C7: =Inputs!$C$27 -> 0.25 | D7: =Inputs!$C$27*2+0.5 -> 1 | E7: =Inputs!$C$27*2+1.5 -> 2 | F7: =Inputs!$C$27*2+2.5 -> 3
B8: Low: 7.0% WACC, 12.0x terminal (US$ per share) | C8: =(('Goldman Sachs'!$C$6/(1+0.07)^'Goldman Sachs'!$C$7+'Goldman Sachs'!$D$6/(1+0.07)^'Goldman Sachs'!$D$7+'Goldman Sachs'!$E$6/(1+0.07)^'Goldman Sachs'!$E$7+'Goldman Sachs'!$F$6/(1+0.07)^'Goldman Sachs'!$F$7)+12*Inputs!$F$13/(1+0.07)^3.5-Inputs!$C$22)/Inputs!$C$21 -> 67.78774
B9: High: 6.0% WACC, 14.0x terminal | C9: =(('Goldman Sachs'!$C$6/(1+0.06)^'Goldman Sachs'!$C$7+'Goldman Sachs'!$D$6/(1+0.06)^'Goldman Sachs'!$D$7+'Goldman Sachs'!$E$6/(1+0.06)^'Goldman Sachs'!$E$7+'Goldman Sachs'!$F$6/(1+0.06)^'Goldman Sachs'!$F$7)+14*Inputs!$F$13/(1+0.06)^3.5-Inputs!$C$22)/Inputs!$C$21 -> 83.189775
B10: Proxy: $68.42 – $83.82 | C10: =TEXT(68.42,"0.00")&" – "&TEXT(83.82,"0.00") -> 68.42 – 83.82
B11: Implied perpetuity growth at 12.0x and 6.0%: g = (TV×r − CF₂₀₂₇)/(TV + CF₂₀₂₇) | C11: =(12*Inputs!$F$13*0.06-Inputs!$F$15)/(12*Inputs!$F$13+Inputs!$F$15) -> 0.012796514
B12: Implied perpetuity growth at 14.0x and 7.0% | C12: =(14*Inputs!$F$13*0.07-Inputs!$F$15)/(14*Inputs!$F$13+Inputs!$F$15) -> 0.028896685 | G12: Proxy: 'implied perpetuity growth rates ranging from 1.0% to 2.6%'
B14: 2. PRESENT VALUE OF FUTURE SHARE PRICE — 11.5–14.5x NTM EBITDA at each year-end, dividends added, discounted at 6.9% cost of equity
B15: Value at year-end, then discounted to 30 June 2024 | C15: YE 2024 | D15: YE 2025 | E15: YE 2026
B16: At 11.5x | C16: =((11.5*Inputs!$D$13-Inputs!$C$22)/Inputs!$C$21)/(1+0.069)^(0+0.5)+(Inputs!$C$17)/(1+0.069)^(0+0.5) -> 60.649778 | D16: =((11.5*Inputs!$E$13-Inputs!$C$22)/Inputs!$C$21)/(1+0.069)^(1+0.5)+(Inputs!$C$17+Inputs!$D$17)/(1+0.069)^(1+0.5) -> 63.373438 | E16: =((11.5*Inputs!$F$13-Inputs!$C$22)/Inputs!$C$21)/(1+0.069)^(2+0.5)+(Inputs!$C$17+Inputs!$D$17+Inputs!$E$17)/(1+0.069)^(2+0.5) -> 66.558214
B17: At 14.5x | C17: =((14.5*Inputs!$D$13-Inputs!$C$22)/Inputs!$C$21)/(1+0.069)^(0+0.5)+(Inputs!$C$17)/(1+0.069)^(0+0.5) -> 80.486303 | D17: =((14.5*Inputs!$E$13-Inputs!$C$22)/Inputs!$C$21)/(1+0.069)^(1+0.5)+(Inputs!$C$17+Inputs!$D$17)/(1+0.069)^(1+0.5) -> 83.104322 | E17: =((14.5*Inputs!$F$13-Inputs!$C$22)/Inputs!$C$21)/(1+0.069)^(2+0.5)+(Inputs!$C$17+Inputs!$D$17+Inputs!$E$17)/(1+0.069)^(2+0.5) -> 86.374719
B18: Rebuilt range — low | C18: =MIN('Goldman Sachs'!$C$16,'Goldman Sachs'!$D$16,'Goldman Sachs'!$E$16) -> 60.649778
B19: Rebuilt range — high | C19: =MAX('Goldman Sachs'!$C$17,'Goldman Sachs'!$D$17,'Goldman Sachs'!$E$17) -> 86.374719
B20: Proxy: $60.93 – $90.01 | C20: =TEXT(60.93,"0.00")&" – "&TEXT(90.01,"0.00") -> 60.93 – 90.01
B22: 3. PREMIA PAID — US targets over US$20bn since 2008, strategic buyers
B23: 14% over undisturbed | C23: =Inputs!$C$6*(1+0.14) -> 71.7972
B24: 32% over undisturbed | C24: =Inputs!$C$6*(1+0.32) -> 83.1336
B25: Proxy: $71.80 – $83.13 | C25: =TEXT(71.8,"0.00")&" – "&TEXT(83.13,"0.00") -> 71.80 – 83.13
B26: 7% over the 52-week high | C26: =Inputs!$C$6*(1+0.07) -> 67.3886
B27: 23% over the 52-week high | C27: =Inputs!$C$6*(1+0.23) -> 77.4654
B28: Proxy: $67.39 – $77.47 | C28: =TEXT(67.39,"0.00")&" – "&TEXT(77.47,"0.00") -> 67.39 – 77.47
B29: Where the offer sits: premium to undisturbed versus the 75th percentile of precedents (32%) | C29: =Inputs!$C$7-0.32 -> 0.0058177199 | G29: The offer is above every precedent premium in the set: Mars paid more than the top quartile
B31: 4. PRECEDENT TRANSACTIONS — 12.1–21.5x FY1 EBITDA (the calibrating analysis)
B32: 12.1x 2024E EBITDA | C32: =(12.1*Inputs!$C$13-Inputs!$C$22)/Inputs!$C$21 -> 58.81
B33: 21.5x 2024E EBITDA | C33: =(21.5*Inputs!$C$13-Inputs!$C$22)/Inputs!$C$21 -> 118.63
B34: Proxy: $58.81 – $118.63 (reproduced by construction) | C34: =TEXT(58.81,"0.00")&" – "&TEXT(118.63,"0.00") -> 58.81 – 118.63
B35: Multiple of 2024E EBITDA the offer implies | C35: =(Inputs!$C$5*Inputs!$C$21+Inputs!$C$22)/Inputs!$C$13 -> 15.979739
B36: Multiple of 2025E EBITDA the offer implies | C36: =(Inputs!$C$5*Inputs!$C$21+Inputs!$C$22)/Inputs!$D$13 -> 14.874934
B37: Median of the eleven precedents (proxy) | C37: 16.2 | G37: Wrigley/Mars 2008 at 17.6x is in the set
B39: 5. TRADING COMPARABLES — 'for reference purposes only'
B40: Median EV/NTM EBITDA, snacking (Hershey, Mondelēz, PepsiCo) | C40: 14.8
B41: Median EV/NTM EBITDA, centre of store (Campbell, Conagra, General Mills, Smucker, Kraft Heinz) | C41: 9.9
B42: Offer multiple of NTM (2025E) EBITDA against the snacking median | C42: ='Goldman Sachs'!$C$36-'Goldman Sachs'!$C$40 -> 0.074934257 | G42: Turns of EBITDA above the best-rated peer group

Sheet Lazard
B1: Kellanova / Mars — Fairness Opinion Replication | G1: KELLANOVA
B2: Lazard's analyses rebuilt with the same back-solved balance sheet
B4: 1. DISCOUNTED CASH FLOW — WACC 6.25–6.75%, perpetuity growth 1.5–2.0%, mid-year, from 30 June 2024
B5: Low: 6.75% WACC, 1.5% growth | C5: =(('Goldman Sachs'!$C$6/(1+0.0675)^'Goldman Sachs'!$C$7+'Goldman Sachs'!$D$6/(1+0.0675)^'Goldman Sachs'!$D$7+'Goldman Sachs'!$E$6/(1+0.0675)^'Goldman Sachs'!$E$7+'Goldman Sachs'!$F$6/(1+0.0675)^'Goldman Sachs'!$F$7)+Inputs!$F$15*(1+0.015)/(0.0675-0.015)/(1+0.0675)^3.5-Inputs!$C$22)/Inputs!$C$21 -> 61.073803
B6: High: 6.25% WACC, 2.0% growth | C6: =(('Goldman Sachs'!$C$6/(1+0.0625)^'Goldman Sachs'!$C$7+'Goldman Sachs'!$D$6/(1+0.0625)^'Goldman Sachs'!$D$7+'Goldman Sachs'!$E$6/(1+0.0625)^'Goldman Sachs'!$E$7+'Goldman Sachs'!$F$6/(1+0.0625)^'Goldman Sachs'!$F$7)+Inputs!$F$15*(1+0.02)/(0.0625-0.02)/(1+0.0625)^3.5-Inputs!$C$22)/Inputs!$C$21 -> 78.763378
B7: Proxy: $69.60 – $79.10 | C7: =TEXT(69.6,"0.00")&" – "&TEXT(79.1,"0.00") -> 69.60 – 79.10
B8: Terminal free cash flow that reproduces Lazard's $69.60 low end at 6.75% and 1.5% (US$ m) | C8: =(69.6*Inputs!$C$21+Inputs!$C$22-('Goldman Sachs'!$C$6/(1+0.0675)^'Goldman Sachs'!$C$7+'Goldman Sachs'!$D$6/(1+0.0675)^'Goldman Sachs'!$D$7+'Goldman Sachs'!$E$6/(1+0.0675)^'Goldman Sachs'!$E$7+'Goldman Sachs'!$F$6/(1+0.0675)^'Goldman Sachs'!$F$7))*(1+0.0675)^3.5*(0.0675-0.015)/(1+0.015) -> 1727.6683 | G8: Close to 2027E NOPAT (US$1,705m): Lazard appears to have normalised the terminal year, removing the working-capital build in 2027E free cash flow
B9: as a multiple of 2027E unlevered free cash flow | C9: =Lazard!$C$8/Inputs!$F$15 -> 1.1269852
B10: Terminal value at the midpoint as a multiple of 2027E EBITDA | C10: =Inputs!$F$15*(1+0.0175)/(0.065-0.0175)/Inputs!$F$13 -> 11.980472 | G10: Lazard's growth method and Goldman's multiple method should meet in the middle; this shows whether they do
B12: 2. SELECTED PUBLIC COMPANIES — 11.0–13.5x 2025E EBITDA and 14.0–19.0x 2025E EPS
B13: 11.0x 2025E EBITDA | C13: =(11*Inputs!$D$13-Inputs!$C$22)/Inputs!$C$21 -> 57.00905
B14: 13.5x 2025E EBITDA | C14: =(13.5*Inputs!$D$13-Inputs!$C$22)/Inputs!$C$21 -> 74.100276
B15: Proxy: $57.20 – $73.80 | C15: =TEXT(57.2,"0.00")&" – "&TEXT(73.8,"0.00") -> 57.20 – 73.80
B16: 14.0x 2025E adjusted EPS | C16: =14*Inputs!$D$16 -> 55.86
B17: 19.0x 2025E adjusted EPS | C17: =19*Inputs!$D$16 -> 75.81
B18: Proxy: $55.90 – $75.70 | C18: =TEXT(55.9,"0.00")&" – "&TEXT(75.7,"0.00") -> 55.90 – 75.70
B19: Observed: snacking 2025E EBITDA low / high / median | C19: =TEXT(14.3,"0.0")&"x / "&TEXT(14.9,"0.0")&"x / "&TEXT(14.5,"0.0")&"x" -> 14.3x / 14.9x / 14.5x
B20: Observed: diversified grocery 2025E EBITDA low / high / median | C20: =TEXT(9.1,"0.0")&"x / "&TEXT(12.1,"0.0")&"x / "&TEXT(9.4,"0.0")&"x" -> 9.1x / 12.1x / 9.4x
B22: 3. PRECEDENT TRANSACTIONS — 15.5–17.5x LTM adjusted EBITDA (eleven food deals since 2014; median 16.7x)
B23: LTM adjusted EBITDA to 29 June 2024, back-solved from the disclosed range (US$ m) | C23: =(90.2-78.1)*Inputs!$C$21/(17.5-15.5) -> 2124.7818 | G23: Sits between 2023 actual and 2024E, as an LTM figure to mid-year should
B24: 15.5x LTM | C24: =(15.5*Lazard!$C$23-Inputs!$C$22)/Inputs!$C$21 -> 75.58266
B25: 17.5x LTM | C25: =(17.5*Lazard!$C$23-Inputs!$C$22)/Inputs!$C$21 -> 87.68266
B26: Proxy: $78.10 – $90.20 | C26: =TEXT(78.1,"0.00")&" – "&TEXT(90.2,"0.00") -> 78.10 – 90.20
B27: Multiple of LTM EBITDA the offer implies | C27: =(Inputs!$C$5*Inputs!$C$21+Inputs!$C$22)/Lazard!$C$23 -> 16.808651
B29: 4. OTHER ANALYSES (informational, not the basis of the opinion)
B30: Premia paid: 20% over the 2 August close | C30: =Inputs!$C$6*(1+0.2) -> 75.576
B31: Premia paid: 35% over the 2 August close | C31: =Inputs!$C$6*(1+0.35) -> 85.023
B32: Proxy: $75.60 – $85.10 | C32: =TEXT(75.6,"0.00")&" – "&TEXT(85.1,"0.00") -> 75.60 – 85.10
B33: Analyst price targets, discounted one year at 7.0%: low | C33: 56.07
B34: high | C34: 68.22
B35: Post-separation trading range (since 2 October 2023): low | C35: 48.62
B36: high | C36: 62.98

Sheet Football Field
B1: Kellanova / Mars — Fairness Opinion Replication | H1: KELLANOVA
B2: Every range on one sheet against the US$83.50 offer
B4: RANGES — rebuilt, with the proxy's own figures alongside
B5: Analysis | C5: Rebuilt low | D5: Rebuilt high | E5: Proxy low | F5: Proxy high | G5: Offer vs proxy range | H5: Max deviation
B6: GS — discounted cash flow | C6: ='Goldman Sachs'!$C$8 -> 67.78774 | D6: ='Goldman Sachs'!$C$9 -> 83.189775 | E6: 68.42 | F6: 83.82 | G6: =IF(AND(Inputs!$C$5>=E6,Inputs!$C$5<=F6),"Inside",IF(Inputs!$C$5>F6,"Above","Below")) -> Inside | H6: =MAX(ABS(C6-E6),ABS(D6-F6)) -> 0.6322596
B7: GS — present value of future share price | C7: ='Goldman Sachs'!$C$18 -> 60.649778 | D7: ='Goldman Sachs'!$C$19 -> 86.374719 | E7: 60.93 | F7: 90.01 | G7: =IF(AND(Inputs!$C$5>=E7,Inputs!$C$5<=F7),"Inside",IF(Inputs!$C$5>F7,"Above","Below")) -> Inside | H7: =MAX(ABS(C7-E7),ABS(D7-F7)) -> 3.6352808
B8: GS — premia paid, undisturbed | C8: ='Goldman Sachs'!$C$23 -> 71.7972 | D8: ='Goldman Sachs'!$C$24 -> 83.1336 | E8: 71.8 | F8: 83.13 | G8: =IF(AND(Inputs!$C$5>=E8,Inputs!$C$5<=F8),"Inside",IF(Inputs!$C$5>F8,"Above","Below")) -> Above | H8: =MAX(ABS(C8-E8),ABS(D8-F8)) -> 0.0036
B9: GS — premia paid, 52-week high | C9: ='Goldman Sachs'!$C$26 -> 67.3886 | D9: ='Goldman Sachs'!$C$27 -> 77.4654 | E9: 67.39 | F9: 77.47 | G9: =IF(AND(Inputs!$C$5>=E9,Inputs!$C$5<=F9),"Inside",IF(Inputs!$C$5>F9,"Above","Below")) -> Above | H9: =MAX(ABS(C9-E9),ABS(D9-F9)) -> 0.0046
B10: GS — precedent transactions | C10: ='Goldman Sachs'!$C$32 -> 58.81 | D10: ='Goldman Sachs'!$C$33 -> 118.63 | E10: 58.81 | F10: 118.63 | G10: =IF(AND(Inputs!$C$5>=E10,Inputs!$C$5<=F10),"Inside",IF(Inputs!$C$5>F10,"Above","Below")) -> Inside | H10: =MAX(ABS(C10-E10),ABS(D10-F10)) -> 0
B11: Lazard — discounted cash flow | C11: =Lazard!$C$5 -> 61.073803 | D11: =Lazard!$C$6 -> 78.763378 | E11: 69.6 | F11: 79.1 | G11: =IF(AND(Inputs!$C$5>=E11,Inputs!$C$5<=F11),"Inside",IF(Inputs!$C$5>F11,"Above","Below")) -> Above | H11: =MAX(ABS(C11-E11),ABS(D11-F11)) -> 8.5261975
B12: Lazard — public companies, EBITDA | C12: =Lazard!$C$13 -> 57.00905 | D12: =Lazard!$C$14 -> 74.100276 | E12: 57.2 | F12: 73.8 | G12: =IF(AND(Inputs!$C$5>=E12,Inputs!$C$5<=F12),"Inside",IF(Inputs!$C$5>F12,"Above","Below")) -> Above | H12: =MAX(ABS(C12-E12),ABS(D12-F12)) -> 0.3002756
B13: Lazard — public companies, P/E | C13: =Lazard!$C$16 -> 55.86 | D13: =Lazard!$C$17 -> 75.81 | E13: 55.9 | F13: 75.7 | G13: =IF(AND(Inputs!$C$5>=E13,Inputs!$C$5<=F13),"Inside",IF(Inputs!$C$5>F13,"Above","Below")) -> Above | H13: =MAX(ABS(C13-E13),ABS(D13-F13)) -> 0.11
B14: Lazard — precedent transactions | C14: =Lazard!$C$24 -> 75.58266 | D14: =Lazard!$C$25 -> 87.68266 | E14: 78.1 | F14: 90.2 | G14: =IF(AND(Inputs!$C$5>=E14,Inputs!$C$5<=F14),"Inside",IF(Inputs!$C$5>F14,"Above","Below")) -> Inside | H14: =MAX(ABS(C14-E14),ABS(D14-F14)) -> 2.5173404
B15: Lazard — premia paid | C15: =Lazard!$C$30 -> 75.576 | D15: =Lazard!$C$31 -> 85.023 | E15: 75.6 | F15: 85.1 | G15: =IF(AND(Inputs!$C$5>=E15,Inputs!$C$5<=F15),"Inside",IF(Inputs!$C$5>F15,"Above","Below")) -> Inside | H15: =MAX(ABS(C15-E15),ABS(D15-F15)) -> 0.077
B16: Lazard — analyst targets | C16: =Lazard!$C$33 -> 56.07 | D16: =Lazard!$C$34 -> 68.22 | E16: 56.07 | F16: 68.22 | G16: =IF(AND(Inputs!$C$5>=E16,Inputs!$C$5<=F16),"Inside",IF(Inputs!$C$5>F16,"Above","Below")) -> Above | H16: =MAX(ABS(C16-E16),ABS(D16-F16)) -> 0
B17: Lazard — post-separation trading | C17: =Lazard!$C$35 -> 48.62 | D17: =Lazard!$C$36 -> 62.98 | E17: 48.62 | F17: 62.98 | G17: =IF(AND(Inputs!$C$5>=E17,Inputs!$C$5<=F17),"Inside",IF(Inputs!$C$5>F17,"Above","Below")) -> Above | H17: =MAX(ABS(C17-E17),ABS(D17-F17)) -> 0
B19: Ranges the offer exceeds entirely | C19: =COUNTIF(G6:G17,"Above") -> 7
B20: Ranges the offer falls inside | C20: =COUNTIF(G6:G17,"Inside") -> 5
B21: Ranges the offer falls below | C21: =COUNTIF(G6:G17,"Below") -> 0
B22: Largest deviation between a rebuilt bound and the proxy's (US$ per share) | C22: =MAX(H6:H17) -> 8.5261975
B23: excluding the future-share-price analysis and the Lazard DCF low end (both explained on their sheets) | C23: =MAX(H6,H8:H10,H12:H17) -> 2.5173404
B24: Lazard DCF: deviation at the high end alone | C24: =ABS(D11-F11) -> 0.33662214
B25: Highest rebuilt bound across the opinion-basis analyses (GS 1–4, Lazard 1–3) | C25: =MAX(D6:D10,D11:D14) -> 118.63
B26: The offer sits at the top of Goldman's discounted cash flow range and above Lazard's, at or above the top of the premia ranges, above every trading-multiple range and inside only the precedent-transaction ranges. That is what a fairness opinion on a full-price strategic deal looks like: the intrinsic analyses bracket the price, the market-based ones sit beneath it, and the precedents — which include the buyer's own Wrigley deal at 17.6x — are the one place a higher number can be found.

Sheet Summary
B1: Kellanova / Mars — Fairness Opinion Replication | F1: KELLANOVA
B2: What the proxy discloses, what was rebuilt, and what it says about the price
B4: THE DEAL
B5: Offer per share (cash) | C5: =Inputs!$C$5 -> 83.5
B6: Premium to the undisturbed price | C6: =Inputs!$C$7 -> 0.32581772
B7: Equity value at the offer (US$ m) | C7: =Inputs!$C$5*Inputs!$C$21 -> 29325.502
B8: Enterprise value at the offer (US$ m) | C8: =Inputs!$C$5*Inputs!$C$21+Inputs!$C$22 -> 35714.717
B9: EV / 2024E EBITDA · EV / 2025E EBITDA · EV / LTM EBITDA | C9: =TEXT('Goldman Sachs'!$C$35,"0.0")&"x · "&TEXT('Goldman Sachs'!$C$36,"0.0")&"x · "&TEXT(Lazard!$C$27,"0.0")&"x" -> 16.0x · 14.9x · 16.8x
B11: THE REPLICATION
B12: Goldman DCF: rebuilt vs proxy | C12: =TEXT('Goldman Sachs'!$C$8,"0.00")&"–"&TEXT('Goldman Sachs'!$C$9,"0.00")&" vs 68.42–83.82" -> 67.79–83.19 vs 68.42–83.82
B13: Lazard DCF: rebuilt vs proxy | C13: =TEXT(Lazard!$C$5,"0.00")&"–"&TEXT(Lazard!$C$6,"0.00")&" vs 69.60–79.10" -> 61.07–78.76 vs 69.60–79.10
B14: Lazard EBITDA comps: rebuilt vs proxy | C14: =TEXT(Lazard!$C$13,"0.00")&"–"&TEXT(Lazard!$C$14,"0.00")&" vs 57.20–73.80" -> 57.01–74.10 vs 57.20–73.80
B15: Largest deviation of any rebuilt bound from the proxy, core analyses (US$) | C15: ='Football Field'!$C$23 -> 2.5173404
B16: Ranges the offer exceeds / sits inside / sits below | C16: ='Football Field'!$C$19&" / "&'Football Field'!$C$20&" / "&'Football Field'!$C$21 -> 7 / 5 / 0
B18: • The proxy discloses enough to rebuild almost every analysis to within a dollar or two a share: projections, discount rates, multiple ranges, premia ranges and the undisturbed price. The two undisclosed inputs — diluted shares and adjusted net debt — fall out of a single disclosed range and then reproduce the rest. Goldman's DCF lands within 63 cents, Lazard's comparables within 30 cents, the premia to the cent. The one miss is the low end of Lazard's DCF, which needs a terminal cash flow close to NOPAT rather than 2027E free cash flow — the sheet says so and back-solves it.
B19: • The offer is a full price by every intrinsic measure. It sits at the top of Goldman's DCF range, above Lazard's, at or above the top of the premia ranges, and roughly 3–4 turns of EBITDA above the best-rated listed peers. Only the precedent-transaction ranges, anchored by 2015–2018 food deals and Mars's own Wrigley acquisition, leave room above it.
B20: • The two advisors agree because they were given the same projections and the same balance sheet; their methods differ (a terminal multiple against a perpetuity growth rate) and land within a few dollars of each other. A reader should treat that as consistency of inputs, not independent confirmation.
B21: • What cannot be rebuilt is the judgement: why 12–14x rather than 11–15x, why 14–32% rather than the full quartile spread. The proxy gives the ranges and the phrase 'professional judgment and experience'. A fairness opinion is a set of defensible ranges that bracket a price the board has already negotiated; this replication shows how tightly they bracket it.

Sheet Checks
B1: Kellanova / Mars — Fairness Opinion Replication | E1: KELLANOVA
B2: Every check must read TRUE
B4: INTEGRITY CHECKS
B5: Back-solved diluted shares are within 0–5% above the record-date basic count | C5: =AND(Inputs!$C$21>Inputs!$C$8,Inputs!$C$21<Inputs!$C$8*1.05) -> TRUE
B6: Back-solved net debt reproduces both ends of Goldman's precedent range | C6: =AND(ABS('Goldman Sachs'!$C$32-58.81)<0.01,ABS('Goldman Sachs'!$C$33-118.63)<0.01) -> TRUE
B7: Goldman DCF rebuilt within US$2.5 of the proxy at both ends | C7: =AND(ABS('Goldman Sachs'!$C$8-68.42)<2.5,ABS('Goldman Sachs'!$C$9-83.82)<2.5) -> TRUE
B8: Goldman's implied perpetuity growth range brackets the proxy's 1.0–2.6% | C8: =AND('Goldman Sachs'!$C$11<0.015,'Goldman Sachs'!$C$12>0.02) -> TRUE
B9: Goldman premia-paid ranges reproduce to the cent | C9: =AND(ABS('Goldman Sachs'!$C$23-71.8)<0.01,ABS('Goldman Sachs'!$C$24-83.13)<0.01,ABS('Goldman Sachs'!$C$26-67.39)<0.01,ABS('Goldman Sachs'!$C$27-77.47)<0.01) -> TRUE
B10: Goldman present-value-of-future-share-price rebuilt within US$5 at both ends (dividend path is stated) | C10: =AND(ABS('Goldman Sachs'!$C$18-60.93)<5,ABS('Goldman Sachs'!$C$19-90.01)<5) -> TRUE
B11: Lazard DCF high end rebuilt within US$2.5; low end not reproducible on 2027E free cash flow (reported, not hidden) | C11: =ABS(Lazard!$C$6-79.1)<2.5 -> TRUE
B12: Terminal cash flow needed for Lazard's low end lies between 2027E free cash flow and 2027E NOPAT | C12: =AND(Lazard!$C$8>Inputs!$F$15,Lazard!$C$8<Inputs!$F$14*1.05) -> TRUE
B13: Lazard EBITDA comps rebuilt within US$2.5 at both ends | C13: =AND(ABS(Lazard!$C$13-57.2)<2.5,ABS(Lazard!$C$14-73.8)<2.5) -> TRUE
B14: Lazard P/E comps reproduce within 20 cents | C14: =AND(ABS(Lazard!$C$16-55.9)<0.2,ABS(Lazard!$C$17-75.7)<0.2) -> TRUE
B15: Lazard premia reproduce within 10 cents | C15: =AND(ABS(Lazard!$C$30-75.6)<0.1,ABS(Lazard!$C$31-85.1)<0.1) -> TRUE
B16: Back-solved LTM EBITDA lies between 2023 actual (about US$2,150m) and 2024E | C16: =AND(Lazard!$C$23>1900,Lazard!$C$23<Inputs!$C$13) -> TRUE
B17: Offer lies inside Goldman's DCF range and above Lazard's, as disclosed and as rebuilt | C17: =AND(Inputs!$C$5>=68.42,Inputs!$C$5<=83.82,Inputs!$C$5>79.1,Inputs!$C$5<='Goldman Sachs'!$C$9+2.5,Inputs!$C$5>Lazard!$C$6) -> TRUE
B18: Offer exceeds every trading-multiple range | C18: =AND(Inputs!$C$5>Lazard!$C$14,Inputs!$C$5>Lazard!$C$17) -> TRUE
B19: Football-field counts sum to twelve analyses | C19: ='Football Field'!$C$19+'Football Field'!$C$20+'Football Field'!$C$21=12 -> TRUE
B21: MODEL STATUS | C21: =IF(COUNTIF(C5:C19,FALSE())=0,"MODEL OK","CHECK FAILED") -> MODEL OK
B23: The checks are the point of the project: each one asks whether an analysis rebuilt from the proxy's disclosed inputs lands on the range the advisor reported. A tolerance of US$2.50 a share allows for the undisclosed H2-2024 cash-flow split and rounding; the premia and P/E analyses have no such freedom and must reproduce almost exactly.
