Workbook

Sheet Cover
B3: IB PORTFOLIO · PROJECT 20 OF 20
B4: HDFC Bank / HDFC Ltd
B5: Capstone: Live-Deal Replication and Post-Mortem
B6: NSE: HDFCBANK · ₹ crore · per-share values in ₹ (pre-bonus basis) · as of announcement 4 Apr 2022 · outcome to 18 Sep 2026
B9: What this is | C9: India's largest corporate transaction — HDFC Ltd folded into HDFC Bank at 42 shares for 25, announced 4 April 2022 and effective 1 July 2023 — replicated at announcement with the merger toolkit from Project 6 and the bank-valuation frame from Project 11, then judged against three years of reported results and the share price relative to Nifty Bank.
B11: How it is built | C11: • Contribution analysis on profit, net worth, loans and market value, with HDFC Ltd's 21% stake in the bank cancelled; the implied ratio on each measure against the agreed 1.68x; premium, new shares, post-merger ownership.
C12: • Pro forma FY2022 EPS, book value and ROE, before and after the regulatory drag of CRR, SLR and priority-sector lending on a bond-funded mortgage book, net of the deposit-funding saving as it arrives.
C13: • Post-mortem: reported FY2023–FY2026 profit, net worth, EPS, book value and ROE against the announcement case; total shareholder return against Nifty Bank; the de-rating of price-to-book against the multiple today's ROE justifies.
B15: Contents | C15: Summary — at announcement; three years on
C16: Exchange Ratio — contribution analysis; the agreed ratio against the implied ones
C17: Accretion — pro forma EPS, book, ROE; value at announcement
C18: Regulatory Drag — CRR, SLR, priority sector, funding saving
C19: Post-Mortem — reported results; price against the index; the de-rating
C20: Inputs — terms, market data, FY2022 accounts, regulatory parameters
C21: Checks — fifteen tests; must read MODEL OK
B23: Key outputs (live) | C23: Exchange ratio | E23: =Inputs!$C$7 -> 1.68
C24: HDFC Ltd holders' ownership | E24: ='Exchange Ratio'!$C$20 -> 0.41012889
C25: EPS accretion after the drag | E25: =Accretion!$C$17 -> -0.093109344
C26: ROE: standalone → FY2026 reported | E26: =TEXT('Post-Mortem'!$C$11,"0.0%")&" → "&TEXT('Post-Mortem'!$F$11,"0.0%") -> 15.7% → 12.8%
C27: TSR since announcement vs Nifty Bank | E27: =TEXT('Post-Mortem'!$C$29,"0%")&" vs "&TEXT('Post-Mortem'!$C$30,"0%") -> 4% vs 51%
C28: P/B: 2022 → today | E28: =TEXT('Post-Mortem'!$C$33,"0.0")&"x → "&TEXT('Post-Mortem'!$C$32,"0.0")&"x" -> 3.5x → 2.1x
B30: Colour code | C30: Blue = hard-coded input
C31: Black = formula
C32: Green = link to another sheet
C33: Accent fill = scenario selector / key levers
B35: Sources | C35: Merger announcement and investor presentation of 4 April 2022; FY2022 standalone accounts of HDFC Bank and HDFC Ltd as reported; HDFC Bank reported results FY2023–FY2026 (FY2026 net worth derived as stated).
C36: NSE closing prices and Nifty Bank levels via public market data; HDFC Bank per-share figures restated to the pre-bonus basis after the August 2025 1:1 bonus.
C37: Regulatory parameters as in force in 2022; yield gaps, funding costs and the refinancing share are stated inputs. Nothing here is a recommendation.
B39: Prepared by | C39: Jainam Mehta · github.com/jainammehta1215/ib-portfolio

Sheet Inputs
B1: HDFC Bank / HDFC Ltd — Capstone: Live-Deal Replication and Post-Mortem | G1: HDFC BANK
B2: The two companies on the eve of the announcement, and the terms
B4: TERMS ANNOUNCED 4 APRIL 2022
B5: HDFC Bank shares issued | C5: 42
B6: for every HDFC Ltd shares | C6: 25
B7: Exchange ratio (HDFC Bank shares per HDFC Ltd share) | C7: =Inputs!$C$5/Inputs!$C$6 -> 1.68
B8: HDFC Ltd's shareholding in HDFC Bank, cancelled on merger | C8: 0.21
B9: Carrying value of that stake in HDFC Ltd's standalone books (₹ crore, stated) | C9: 14000 | G9: Held at cost since the 1990s; a small fraction of its ₹1.75 lakh crore market value
B10: HDFC Bank dividend per share for FY2022 (₹) | C10: 15.5
B11: Effective date | C11: 1 July 2023
B13: MARKET, CLOSE OF 1 APRIL 2022 (last day before the announcement)
C14: HDFC Bank | D14: HDFC Ltd
B15: Share price (₹) | C15: 1506.55 | D15: 2450.25
B16: Shares outstanding (crore) | C16: 554.55 | D16: 181.31
B17: Market capitalisation (₹ crore) | C17: =Inputs!$C$15*Inputs!$C$16 -> 835457.3 | D17: =Inputs!$D$15*Inputs!$D$16 -> 444254.83
B18: Share price at close on 4 April 2022 (announcement day) | C18: 1656.8 | D18: 2678.9 | G18: Both rose about 10% on the day; the market's first verdict was positive
B20: FY2022 FINANCIALS, STANDALONE, YEAR TO 31 MARCH 2022 (as reported)
B21: Net profit | C21: 36961 | D21: 13742
B22: Net worth | C22: 240093 | D22: 120187
B23: Advances / loan book | C23: 1368821 | D23: 568363
B24: Deposits | C24: 1559217 | D24: 160900
B25: Borrowings (HDFC Ltd: non-deposit funding) | C25: 184817 | D25: 462000
B26: Earnings per share (₹) | C26: =Inputs!$C$21/Inputs!$C$16 -> 66.650437 | D26: =Inputs!$D$21/Inputs!$D$16 -> 75.792841
B27: Book value per share (₹) | C27: =Inputs!$C$22/Inputs!$C$16 -> 432.95104 | D27: =Inputs!$D$22/Inputs!$D$16 -> 662.88125
B28: Return on closing equity | C28: =Inputs!$C$21/Inputs!$C$22 -> 0.15394451 | D28: =Inputs!$D$21/Inputs!$D$22 -> 0.11433849
B29: Price / book | C29: =Inputs!$C$15/Inputs!$C$27 -> 3.4797237 | D29: =Inputs!$D$15/Inputs!$D$27 -> 3.6963634
B30: Price / earnings | C30: =Inputs!$C$15/Inputs!$C$26 -> 22.603753 | D30: =Inputs!$D$15/Inputs!$D$26 -> 32.328251
B32: REGULATORY PARAMETERS (RBI, 2022)
B33: Cash reserve ratio | C33: 0.045
B34: Statutory liquidity ratio | C34: 0.18
B35: Priority-sector lending requirement (share of adjusted net bank credit) | C35: 0.4
B36: Mortgage lending yield forgone on cash reserves (stated) | C36: 0.07 | G36: CRR earns nothing
B37: Yield gap between mortgages and government securities held for SLR (stated) | C37: 0.02
B38: Share of HDFC Ltd's book not already qualifying as priority-sector (stated) | C38: 0.5 | G38: Affordable-housing loans under the RBI limits already qualify
B39: Cost of meeting the shortfall through priority-sector certificates and RIDF deposits (stated) | C39: 0.01
B40: Tax rate | C40: 0.25
B41: Years of RBI glide path granted for CRR/SLR/PSL on HDFC Ltd's book | C41: 3 | G41: RBI allowed a phased approach on part of the requirement; the model applies the full drag from year one for conservatism, then phases it in the Post-Mortem comparison

Sheet Exchange Ratio
B1: HDFC Bank / HDFC Ltd — Capstone: Live-Deal Replication and Post-Mortem | G1: HDFC BANK
B2: What each company brought, and the ratio each measure implies
B4: CONTRIBUTION ANALYSIS
C5: HDFC Bank | D5: HDFC Ltd | E5: HDFC Ltd share | F5: Implied ratio
B6: Net profit | C6: =Inputs!$C$21 -> 36961 | D6: =Inputs!$D$21 -> 13742 | E6: =(D6+Inputs!$C$8*C6)/(C6+D6) -> 0.42411317 | F6: =E6/(1-E6)*Inputs!$C$16*(1-Inputs!$C$8)/Inputs!$D$16 -> 1.7794699
B7: Net worth | C7: =Inputs!$C$22 -> 240093 | D7: =Inputs!$D$22 -> 120187 | E7: =(D7+Inputs!$C$8*C7)/(C7+D7) -> 0.47353872 | F7: =E7/(1-E7)*Inputs!$C$16*(1-Inputs!$C$8)/Inputs!$D$16 -> 2.1733772
B8: Loan book | C8: =Inputs!$C$23 -> 1368821 | D8: =Inputs!$D$23 -> 568363 | E8: =(D8+Inputs!$C$8*C8)/(C8+D8) -> 0.44178323 | F8: =E8/(1-E8)*Inputs!$C$16*(1-Inputs!$C$8)/Inputs!$D$16 -> 1.912284
B9: Market capitalisation (HDFC Ltd's already includes its bank stake) | C9: =Inputs!$C$17 -> 835457.3 | D9: =Inputs!$D$17 -> 444254.83 | E9: =D9/(C9*(1-Inputs!$C$8)+D9) -> 0.40230777 | F9: =E9/(1-E9)*Inputs!$C$16*(1-Inputs!$C$8)/Inputs!$D$16 -> 1.6263981
B10: The implied ratio asks: if HDFC Ltd shareholders should own the share of the combined bank that they contribute on each measure, how many HDFC Bank shares does each HDFC Ltd share deserve? Their contribution is looked through: HDFC Ltd's own figure plus 21% of the bank's, because that 21% was theirs before the deal. Market capitalisation already embeds the stake.
B12: THE AGREED RATIO AGAINST THE IMPLIED ONES
B13: Agreed ratio | C13: =Inputs!$C$7 -> 1.68
B14: Value of one HDFC Ltd share at the ratio (₹, on the 1 April HDFC Bank price) | C14: =Inputs!$C$7*Inputs!$C$15 -> 2531.004
B15: Premium to HDFC Ltd's 1 April close | C15: ='Exchange Ratio'!$C$14/Inputs!$D$15-1 -> 0.032957453 | G15: Presented as a merger of equals; the premium was small
B16: Premium on HDFC Ltd ex the value of its stake in the bank | C16: ='Exchange Ratio'!$C$14/(Inputs!$D$15-Inputs!$C$8*Inputs!$C$17/Inputs!$D$16)-1 -> 0.70714778 | G16: What the bank paid for the mortgage business itself, after netting off its own shares coming back
B17: New HDFC Bank shares issued (crore) | C17: =Inputs!$C$7*Inputs!$D$16 -> 304.6008
B18: HDFC Bank shares cancelled (HDFC Ltd's stake, crore) | C18: =Inputs!$C$8*Inputs!$C$16 -> 116.4555
B19: Post-merger shares outstanding (crore) | C19: =Inputs!$C$16-'Exchange Ratio'!$C$18+'Exchange Ratio'!$C$17 -> 742.6953
B20: HDFC Ltd shareholders' ownership of the combined bank | C20: ='Exchange Ratio'!$C$17/'Exchange Ratio'!$C$19 -> 0.41012889 | G20: Announced as 41%
B21: Ownership given versus net-profit contribution (percentage points) | C21: ='Exchange Ratio'!$C$20-'Exchange Ratio'!$E$6 -> -0.013984277
B22: Ownership given versus net-worth contribution | C22: ='Exchange Ratio'!$C$20-'Exchange Ratio'!$E$7 -> -0.063409829

Sheet Accretion
B1: HDFC Bank / HDFC Ltd — Capstone: Live-Deal Replication and Post-Mortem | F1: HDFC BANK
B2: Pro forma FY2022 as if merged: EPS, book value, return on equity
B4: PRO FORMA BEFORE REGULATORY COSTS
B5: Combined net profit (HDFC Ltd's dividend from the bank eliminated) | C5: =Inputs!$C$21+Inputs!$D$21-Inputs!$C$8*Inputs!$C$10*Inputs!$C$16 -> 48897.94 | F5: HDFC Ltd's income included the dividend on its bank stake; removed to avoid double counting
B6: Pro forma EPS (₹) | C6: =Accretion!$C$5/'Exchange Ratio'!$C$19 -> 65.838494
B7: EPS accretion / (dilution) to HDFC Bank shareholders | C7: =Accretion!$C$6/Inputs!$C$26-1 -> -0.012182121
B8: Combined net worth (HDFC Ltd's investment in the bank eliminated at its carrying value) | C8: =Inputs!$C$22+Inputs!$D$22-Inputs!$C$9 -> 346280 | F8: Pooling basis, as the announcement presented it; acquisition accounting would restate HDFC Ltd's assets to fair value
B9: Pro forma book value per share (₹) | C9: =Accretion!$C$8/'Exchange Ratio'!$C$19 -> 466.24773
B10: Book value accretion / (dilution) | C10: =Accretion!$C$9/Inputs!$C$27-1 -> 0.076906367
B11: Pro forma return on closing equity | C11: =Accretion!$C$5/Accretion!$C$8 -> 0.14120925
B12: change from HDFC Bank standalone (percentage points) | C12: =Accretion!$C$11-Inputs!$C$28 -> -0.012735261
B14: PRO FORMA AFTER THE REGULATORY DRAG (from the Regulatory Drag sheet, full drag from year one)
B15: Combined net profit after the drag | C15: =Accretion!$C$5+'Regulatory Drag'!$C$27 -> 44891.964
B16: Pro forma EPS after the drag (₹) | C16: =(Accretion!$C$5+'Regulatory Drag'!$C$27)/'Exchange Ratio'!$C$19 -> 60.444659
B17: EPS accretion / (dilution) after the drag | C17: =(Accretion!$C$5+'Regulatory Drag'!$C$27)/'Exchange Ratio'!$C$19/Inputs!$C$26-1 -> -0.093109344
B18: Pro forma return on equity after the drag | C18: =(Accretion!$C$5+'Regulatory Drag'!$C$27)/Accretion!$C$8 -> 0.12964065
B20: VALUE AT ANNOUNCEMENT
B21: Combined market value at 1 April prices (₹ crore) | C21: =Inputs!$C$17*(1-Inputs!$C$8)+Inputs!$D$17 -> 1104266.1
B22: as a multiple of pro forma book | C22: =Accretion!$C$21/Accretion!$C$8 -> 3.1889399
B23: HDFC Bank standalone price / book before the deal | C23: =Inputs!$C$29 -> 3.4797237
B24: Multiple the market would need to hold for HDFC Bank holders to be no worse off | C24: =Inputs!$C$15/Accretion!$C$9 -> 3.2312221 | F24: Book-value accretion means a lower P/B keeps the price whole; the question is whether a lower-ROE bank deserves it
B25: The arithmetic at announcement was benign: EPS roughly neutral before regulatory costs, meaningful book-value accretion, a lower return on equity. The bank was buying a lower-return business with its own high-multiple paper, which is accretive to book and dilutive to ROE by construction. Whether that creates value depends entirely on the multiple the market attaches to the lower ROE.

Sheet Regulatory Drag
B1: HDFC Bank / HDFC Ltd — Capstone: Live-Deal Replication and Post-Mortem | F1: HDFC BANK
B2: What happens when a mortgage lender's balance sheet becomes a bank's
B4: RESERVE REQUIREMENTS ON HDFC LTD'S LIABILITIES
B5: HDFC Ltd liabilities that become bank liabilities subject to CRR and SLR (deposits plus borrowings) | C5: =Inputs!$D$24+Inputs!$D$25 -> 622900
B6: Cash reserve to hold (earning nothing) | C6: ='Regulatory Drag'!$C$5*Inputs!$C$33 -> 28030.5
B7: Government securities to hold | C7: ='Regulatory Drag'!$C$5*Inputs!$C$34 -> 112122
B8: Total low-yield assets required | C8: ='Regulatory Drag'!$C$6+'Regulatory Drag'!$C$7 -> 140152.5
B9: as % of HDFC Ltd's loan book | C9: ='Regulatory Drag'!$C$8/Inputs!$D$23 -> 0.24658977
B10: Pre-tax income forgone: CRR at the full mortgage yield, SLR at the yield gap | C10: ='Regulatory Drag'!$C$6*Inputs!$C$36+'Regulatory Drag'!$C$7*Inputs!$C$37 -> 4204.575 | F10: CRR forgoes the whole lending yield; SLR forgoes only the spread over government bonds
B12: PRIORITY-SECTOR LENDING ON HDFC LTD'S BOOK
B13: Priority-sector assets required on the acquired loan book | C13: =Inputs!$D$23*Inputs!$C$35 -> 227345.2
B14: of which a shortfall to be met through certificates and RIDF | C14: ='Regulatory Drag'!$C$13*Inputs!$C$38 -> 113672.6
B15: Pre-tax cost of meeting the shortfall | C15: ='Regulatory Drag'!$C$14*Inputs!$C$39 -> 1136.726
B17: FUNDING COST: REPLACING BONDS WITH DEPOSITS
B18: HDFC Ltd's average cost of borrowings (stated) | C18: 0.065
B19: HDFC Bank's average cost of deposits (stated) | C19: 0.038
B20: Share of HDFC Ltd's borrowings refinanced with deposits over the glide path | C20: 0.5
B21: Pre-tax saving once refinanced | C21: =Inputs!$D$25*'Regulatory Drag'!$C$20*('Regulatory Drag'!$C$18-'Regulatory Drag'!$C$19) -> 6237 | F21: The strategic case for the deal: a bank funds mortgages more cheaply than a bond-funded lender. It arrives only as deposits are gathered
B23: NET DRAG
B24: Pre-tax drag: reserves plus priority-sector | C24: ='Regulatory Drag'!$C$10+'Regulatory Drag'!$C$15 -> 5341.301
B25: Net pre-tax effect after the funding saving | C25: ='Regulatory Drag'!$C$21-'Regulatory Drag'!$C$24 -> 895.699
B26: Net after-tax effect | C26: ='Regulatory Drag'!$C$25*(1-Inputs!$C$40) -> 671.77425
B27: After-tax drag in year one, before any refinancing benefit | C27: =-'Regulatory Drag'!$C$24*(1-Inputs!$C$40) -> -4005.9758
B28: as % of HDFC Ltd's FY2022 net profit | C28: =-'Regulatory Drag'!$C$27/Inputs!$D$21 -> 0.2915133
B29: This sheet is the deal in one line: the bank takes a drag of roughly a fifth of HDFC Ltd's profit on day one, and earns it back only as it replaces ₹4.6 lakh crore of bonds with deposits. The RBI granted a glide path on part of the requirement, which spreads the drag; it does not remove it. Deposit growth, not the exchange ratio, was always the variable that decided the outcome.

Sheet Post-Mortem
B1: HDFC Bank / HDFC Ltd — Capstone: Live-Deal Replication and Post-Mortem | H1: HDFC BANK
B2: What actually happened: FY2023 (last pre-merger year) to FY2026, and the share price against Nifty Bank
B4: REPORTED RESULTS (standalone; per-share on the pre-bonus basis)
C5: FY2023A | D5: FY2024A | E5: FY2025A | F5: FY2026A
B6: Net profit | C6: 44109 | D6: 60812 | E6: 67347 | F6: 70479 | H6: FY2024 onward includes HDFC Ltd from 1 July 2023
B7: Net worth | C7: 280199 | D7: 437600 | E7: 498000 | F7: 550000 | H7: FY2026 net worth is derived: prior year plus profit less dividends; the others are reported
B8: Shares outstanding (crore, pre-bonus) | C8: 557.97 | D8: 759.69 | E8: 765 | F8: 770.8
B9: EPS (₹) | C9: ='Post-Mortem'!$C$6/'Post-Mortem'!$C$8 -> 79.052637 | D9: ='Post-Mortem'!$D$6/'Post-Mortem'!$D$8 -> 80.048441 | E9: ='Post-Mortem'!$E$6/'Post-Mortem'!$E$8 -> 88.035294 | F9: ='Post-Mortem'!$F$6/'Post-Mortem'!$F$8 -> 91.43617
B10: Book value per share (₹) | C10: ='Post-Mortem'!$C$7/'Post-Mortem'!$C$8 -> 502.17574 | D10: ='Post-Mortem'!$D$7/'Post-Mortem'!$D$8 -> 576.02443 | E10: ='Post-Mortem'!$E$7/'Post-Mortem'!$E$8 -> 650.98039 | F10: ='Post-Mortem'!$F$7/'Post-Mortem'!$F$8 -> 713.54437
B11: Return on closing equity | C11: ='Post-Mortem'!$C$6/'Post-Mortem'!$C$7 -> 0.15742026 | D11: ='Post-Mortem'!$D$6/'Post-Mortem'!$D$7 -> 0.13896709 | E11: ='Post-Mortem'!$E$6/'Post-Mortem'!$E$7 -> 0.13523494 | F11: ='Post-Mortem'!$F$6/'Post-Mortem'!$F$7 -> 0.12814364
B12: Dividend per share (₹) | C12: 19 | D12: 19.5 | E12: 22 | F12: 24
B13: EPS growth | D13: ='Post-Mortem'!$D$9/'Post-Mortem'!$C$9-1 -> 0.012596715 | E13: ='Post-Mortem'!$E$9/'Post-Mortem'!$D$9-1 -> 0.099775251 | F13: ='Post-Mortem'!$F$9/'Post-Mortem'!$E$9-1 -> 0.038630826
B15: ANNOUNCEMENT CASE AGAINST OUTCOME
B16: Pro forma ROE at announcement, after the full regulatory drag | C16: =Accretion!$C$18 -> 0.12964065
B17: Reported ROE, FY2026 | C17: ='Post-Mortem'!$F$11 -> 0.12814364
B18: HDFC Bank ROE in its last standalone year, FY2023 | C18: ='Post-Mortem'!$C$11 -> 0.15742026
B19: ROE given up against the standalone bank (percentage points) | C19: ='Post-Mortem'!$F$11-'Post-Mortem'!$C$11 -> -0.029276626
B20: EPS growth FY2023–FY2026, compound | C20: =('Post-Mortem'!$F$9/'Post-Mortem'!$C$9)^(1/3)-1 -> 0.049704893
B21: Book value per share growth FY2023–FY2026, compound | C21: =('Post-Mortem'!$F$10/'Post-Mortem'!$C$10)^(1/3)-1 -> 0.12422978
B23: THE SHARE PRICE (pre-bonus basis; the August 2025 1:1 bonus is reversed)
B24: Date | C24: 1 Apr 2022 | D24: 4 Apr 2022 | E24: 30 Jun 2023 | F24: 18 Sep 2026
B25: HDFC Bank (₹) | C25: 1506.55 | D25: 1656.8 | E25: 1701.4 | F25: 1463.8
B26: Nifty Bank index | C26: 37148 | D26: 38000 | E26: 44700 | F26: 56056 | H26: 4 April and 30 June levels are approximate; the endpoints are exact
B27: HDFC Bank price return, 1 April 2022 to 18 September 2026 | C27: ='Post-Mortem'!$F$25/'Post-Mortem'!$C$25-1 -> -0.028376091
B28: Dividends received per pre-bonus share over the period (₹) | C28: =15.5+'Post-Mortem'!$C$12+'Post-Mortem'!$D$12+'Post-Mortem'!$E$12+'Post-Mortem'!$F$12 -> 100 | H28: FY2022 dividend of ₹15.50 paid after April 2022 is included
B29: HDFC Bank total shareholder return | C29: =('Post-Mortem'!$F$25+'Post-Mortem'!$C$28)/'Post-Mortem'!$C$25-1 -> 0.03800073
B30: Nifty Bank price return over the same period | C30: ='Post-Mortem'!$F$26/'Post-Mortem'!$C$26-1 -> 0.50899106
B31: Relative performance against Nifty Bank (price basis) | C31: ='Post-Mortem'!$C$27-'Post-Mortem'!$C$30 -> -0.53736715
B32: Price / book today on FY2026 book | C32: ='Post-Mortem'!$F$25/'Post-Mortem'!$F$10 -> 2.0514492
B33: Price / book on 1 April 2022 (standalone) | C33: =Inputs!$C$29 -> 3.4797237
B34: De-rating of the multiple | C34: ='Post-Mortem'!$C$32/'Post-Mortem'!$C$33-1 -> -0.41045631
B35: ROE on average equity, FY2026 | C35: ='Post-Mortem'!$F$6/AVERAGE('Post-Mortem'!$E$7,'Post-Mortem'!$F$7) -> 0.13450191
B36: Cost of equity the price implies at 7% long-run growth: g + (ROE − g) / (P/B) | C36: =0.07+('Post-Mortem'!$C$35-0.07)/'Post-Mortem'!$C$32 -> 0.10144212 | H36: Project 11's frame in reverse. The market prices India's largest private bank at a cost of equity near 10%; the de-rating is the lower ROE at an unchanged discount rate
B37: For comparison: cost of equity the 2022 price implied at the standalone ROE | C37: =0.07+(Inputs!$C$28-0.07)/Inputs!$C$29 -> 0.094123902
B38: Book value per share compounded at double digits and EPS grew, exactly as the accretion arithmetic said they would. Return on equity fell by about three points, exactly as the arithmetic said it would. The share price has gone nowhere in four and a half years while the bank index rose by half: the market applied the multiple a 13% ROE deserves to a book that had become larger and lower-yielding. The deal was accretive to everything except the thing the price is set on.

Sheet Summary
B1: HDFC Bank / HDFC Ltd — Capstone: Live-Deal Replication and Post-Mortem | F1: HDFC BANK
B2: The merger at announcement and three years on
B4: AT ANNOUNCEMENT, 4 APRIL 2022
B5: Exchange ratio · premium to HDFC Ltd's close | C5: =TEXT(Inputs!$C$7,"0.00")&"x · "&TEXT('Exchange Ratio'!$C$15,"0.0%") -> 1.68x · 3.3%
B6: HDFC Ltd shareholders' ownership of the combined bank | C6: ='Exchange Ratio'!$C$20 -> 0.41012889
B7: versus their contribution of net profit / net worth | C7: =TEXT('Exchange Ratio'!$E$6,"0.0%")&" / "&TEXT('Exchange Ratio'!$E$7,"0.0%") -> 42.4% / 47.4%
B8: Pro forma EPS accretion before / after the regulatory drag | C8: =TEXT(Accretion!$C$7,"0.0%")&" / "&TEXT(Accretion!$C$17,"0.0%") -> -1.2% / -9.3%
B9: Pro forma book value accretion | C9: =Accretion!$C$10 -> 0.076906367
B10: ROE: standalone bank → pro forma after the drag | C10: =TEXT(Inputs!$C$28,"0.0%")&" → "&TEXT(Accretion!$C$18,"0.0%") -> 15.4% → 13.0%
B11: Low-yield assets required by CRR and SLR on HDFC Ltd's liabilities (₹ crore) | C11: ='Regulatory Drag'!$C$8 -> 140152.5
B12: After-tax drag in year one as % of HDFC Ltd's profit | C12: ='Regulatory Drag'!$C$28 -> 0.2915133
B14: THREE YEARS ON
B15: Reported ROE FY2026 · ROE given up against standalone FY2023 | C15: =TEXT('Post-Mortem'!$F$11,"0.0%")&" · "&TEXT('Post-Mortem'!$C$19,"0.0%") -> 12.8% · -2.9%
B16: EPS and book value per share growth FY2023–FY2026, compound | C16: =TEXT('Post-Mortem'!$C$20,"0.0%")&" / "&TEXT('Post-Mortem'!$C$21,"0.0%") -> 5.0% / 12.4%
B17: HDFC Bank total shareholder return since the day before the announcement | C17: ='Post-Mortem'!$C$29 -> 0.03800073
B18: Nifty Bank over the same period | C18: ='Post-Mortem'!$C$30 -> 0.50899106
B19: Relative performance | C19: ='Post-Mortem'!$C$31 -> -0.53736715
B20: Price / book: 1 April 2022 → today | C20: =TEXT('Post-Mortem'!$C$33,"0.00")&"x → "&TEXT('Post-Mortem'!$C$32,"0.00")&"x" -> 3.48x → 2.05x
B22: • The ratio was set on market value, and it favoured the bank. On a look-through basis — counting the 21% of the bank that HDFC Ltd's shareholders already owned — they contributed 42% of the profit and 47% of the net worth and received 41% of the shares, which is what 40% of the combined market value implied. The bank's 3.5x book against the lender's 2x did the work; the 3% premium was the price of a deal presented as a merger of equals.
B23: • The accretion arithmetic was right, and it was the wrong question. EPS and book value per share both grew as forecast. What the pro forma also said — and what the pitch would have put on a back page — was that return on equity would fall by three points as ₹1.4 lakh crore of reserves and priority-sector assets were bolted on to a book funded with bonds.
B24: • The market did exactly what Project 11 says it should. A bank's price is book value times a multiple set by ROE against the cost of equity. The bank's book grew and its ROE fell; the multiple de-rated from about 3.5x to about 2x; the price went nowhere while Nifty Bank rose by half. The cost of equity the price implies is almost unchanged from 2022: the market re-priced the ROE, not the franchise. There is no mystery to explain.
B25: • The thesis is not dead, it is slow. The saving from replacing HDFC Ltd's bonds with deposits is real and larger than the regulatory drag — but it arrives at the pace of deposit growth, and a bank that had to slow loan growth to fix its loan-to-deposit ratio cannot gather deposits faster than the system. The deal will be judged on ROE in FY2028, not FY2026.

Sheet Checks
B1: HDFC Bank / HDFC Ltd — Capstone: Live-Deal Replication and Post-Mortem | E1: HDFC BANK
B2: Every check must read TRUE
B4: INTEGRITY CHECKS
B5: Exchange ratio equals 42 / 25 | C5: =ABS(Inputs!$C$7-1.68)<0.0001 -> TRUE
B6: HDFC Ltd shareholders' ownership reproduces the announced 41% within one point | C6: =ABS('Exchange Ratio'!$C$20-0.41)<0.01 -> TRUE
B7: Contribution shares lie between 0% and 100% | C7: =AND(MIN('Exchange Ratio'!$E$6,'Exchange Ratio'!$E$7,'Exchange Ratio'!$E$8,'Exchange Ratio'!$E$9)>0,MAX('Exchange Ratio'!$E$6,'Exchange Ratio'!$E$7,'Exchange Ratio'!$E$8,'Exchange Ratio'!$E$9)<1) -> TRUE
B8: Implied ratio from market capitalisation is close to the agreed ratio (within 15%) | C8: =ABS('Exchange Ratio'!$F$9/Inputs!$C$7-1)<0.15 -> TRUE
B9: Ownership given is below the look-through profit and net-worth contributions and within 2 points of the market-value contribution (the ratio was set on price) | C9: =AND('Exchange Ratio'!$C$20<'Exchange Ratio'!$E$6,'Exchange Ratio'!$C$20<'Exchange Ratio'!$E$7,ABS('Exchange Ratio'!$C$20-'Exchange Ratio'!$E$9)<0.02) -> TRUE
B10: Pro forma ROE is below HDFC Bank's standalone ROE (lower-return business acquired) | C10: =Accretion!$C$11<Inputs!$C$28 -> TRUE
B11: Book value accretion is positive and the EPS effect before the drag is within 3% of neutral, as announced | C11: =AND(Accretion!$C$10>0,ABS(Accretion!$C$7)<0.03) -> TRUE
B12: Regulatory drag in year one is between 10% and 40% of HDFC Ltd's profit | C12: =AND('Regulatory Drag'!$C$28>0.1,'Regulatory Drag'!$C$28<0.4) -> TRUE
B13: Funding saving once refinanced exceeds the gross regulatory drag (the strategic case holds in steady state) | C13: ='Regulatory Drag'!$C$21>'Regulatory Drag'!$C$24 -> TRUE
B14: Accretion sheet's post-drag rows tie to the Regulatory Drag sheet | C14: =ABS(Accretion!$C$15-(Accretion!$C$5+'Regulatory Drag'!$C$27))<0.01 -> TRUE
B15: Post-merger share count FY2024 is within 3% of the model's post-merger count | C15: =ABS('Post-Mortem'!$D$8/'Exchange Ratio'!$C$19-1)<0.03 -> TRUE
B16: Reported ROE fell from FY2023 to FY2026 | C16: ='Post-Mortem'!$F$11<'Post-Mortem'!$C$11 -> TRUE
B17: HDFC Bank underperformed Nifty Bank over the period | C17: ='Post-Mortem'!$C$31<0 -> TRUE
B18: Book value per share grew every year | C18: =AND('Post-Mortem'!$D$10>'Post-Mortem'!$C$10,'Post-Mortem'!$E$10>'Post-Mortem'!$D$10,'Post-Mortem'!$F$10>'Post-Mortem'!$E$10) -> TRUE
B19: Cost of equity the price implies today lies between 9% and 13%, and is close to what the 2022 price implied | C19: =AND('Post-Mortem'!$C$36>0.09,'Post-Mortem'!$C$36<0.13,ABS('Post-Mortem'!$C$36-'Post-Mortem'!$C$37)<0.02) -> TRUE
B21: MODEL STATUS | C21: =IF(COUNTIF(C5:C19,FALSE())=0,"MODEL OK","CHECK FAILED") -> MODEL OK
B23: The second and eleventh checks tie the model to the announcement (41% ownership) and to the reported post-merger share count; the last three test the post-mortem's claims against the reported numbers rather than against the narrative.
