Workbook

Sheet Cover
B3: IB PORTFOLIO · PROJECT 04 OF 20
B4: Tata Consultancy Services
B5: Precedent Transactions — IT Services
B6: NSE: TCS · US$ millions at announcement · as of deals announced Sep 2014 – Jun 2024
B9: What this is | C9: Fourteen IT-services acquisitions from 2014 to 2024 (Capgemini–IGATE, Atos–Syntel, Capgemini–Altran, Carlyle–Hexaware, LTI–Mindtree, Cognizant–Belcan and others), built from announcement press releases and filings: enterprise value, target LTM revenue and EBITDA, implied multiples, one-day premia for public targets, consideration and source for every row. Statistics by acquirer type and geography, the control premium relative to Project 3's trading multiples, and an illustrative range for TCS.
B11: How it is built | C11: • Each row cites its announcement source; EV adds target net debt where only equity value was disclosed; EUR and INR deals converted at the announcement-date rate.
C12: • Private-target metrics are approximate where the source gave rounded figures; medians and quartiles are used because they are robust to a single imprecise entry, and the count of observations is shown for every statistic.
C13: • Premia are one-day to the unaffected close; two targets had run up on speculation and one merger was under common control, all noted in the table.
C14: • The implied TCS range is labelled illustrative: no precedent target is comparable in size to TCS.
B16: Contents | C16: Summary — precedent multiples, control premium vs trading comps, illustrative TCS range
C17: Inputs — screen definition, data caveats, TCS metrics from Project 3
C18: Transactions — fourteen deals 2014–2024 with sources, multiples, premia and statistics
C19: Checks — integrity checks
B21: Key outputs (live) | C21: Precedent median EV / Revenue | E21: =Transactions!K23 -> 2.5743243
C22: Precedent median EV / EBITDA | E22: =Transactions!L23 -> 14.666667
C23: Control premium vs trading comps (revenue) | E23: =Summary!C14 -> 0.41446391
C24: Deals in the set | E24: =Transactions!K27 -> 14
C25: Model status | E25: =Checks!C10 -> MODEL OK
B27: Colour code | C27: Blue = hard-coded input
C28: Black = formula
C29: Green = link to another sheet
C30: Accent fill = scenario selector / key levers
B32: Sources | C32: Acquirer press releases and exchange filings at announcement (cited per row)
C33: Target annual reports / 10-Ks for LTM revenue and EBITDA
C34: Project 3 for TCS metrics and trading-comps medians
B36: Prepared by | C36: Jainam Mehta · github.com/jainammehta1215/ib-portfolio

Sheet Inputs
B1: Tata Consultancy Services — Precedent Transactions — IT Services | F1: TATA CONSULTANCY SERVICES
B2: Screen definition and how to read the deal set
B4: SCREEN
B5: Sector | C5: IT services, consulting and engineering-services providers with offshore or nearshore delivery
B6: Period | C6: September 2014 – June 2024 (ten years; long enough for a cycle, short enough that business models are comparable)
B7: Size | C7: Enterprise value US$400m – US$7bn at announcement
B8: Control | C8: Majority or 100% acquisitions and mergers; minority stakes excluded
B9: Data basis | C9: Deal value and target LTM metrics as disclosed at announcement; where the press release gave only equity value, EV adds net debt from the target's last balance sheet; EUR/INR deals converted at the announcement-date rate
B10: Caveat | C10: Several private-target revenue figures are approximate (press releases give rounded or 'expected' numbers). Multiples on those rows are indicative; the statistics use medians and quartiles, which are robust to a single imprecise entry. Verify against the cited source before using any figure in a client document.
B12: TARGET FOR THE IMPLIED VALUATION (from Project 3)
B13: TCS LTM revenue (US$m) | C13: 28627 | F13: Project 3, LTM to Jun 2026
B14: TCS LTM EBITDA (US$m) | C14: 7748 | F14: Project 3
B15: TCS net debt (US$m, negative = net cash) | C15: -3020 | F15: Project 3
B16: TCS shares (m) | C16: 3618 | F16: Project 3
B17: USD per INR | C17: 0.010467 | F17: Project 3 (USDINR 95.54)
B18: TCS share price (INR) | C18: 2200.8 | F18: 12 Sep 2026
B19: Trading-comps peer median EV/Revenue (Project 3) | C19: 1.82 | F19: For the control-premium comparison
B20: Trading-comps peer median EV/EBITDA (Project 3) | C20: 8.75

Sheet Transactions
B1: Tata Consultancy Services — Precedent Transactions — IT Services | Q1: TATA CONSULTANCY SERVICES
B2: Deal database from primary announcements · blue = as disclosed · black = derived
B4: Announced | C4: Acquirer | D4: Acquirer type | E4: Target | F4: Target HQ | G4: EV (US$m) | H4: LTM revenue | I4: LTM EBITDA | J4: EBITDA margin | K4: EV / Revenue | L4: EV / EBITDA | M4: Public target | N4: Premium (1-day) | O4: Consideration | P4: Source | Q4: Note
B5: 2014-09 | C5: Cognizant | D5: Strategic | E5: TriZetto | F5: US | G5: 2700 | H5: 711 | I5: 160 | J5: =IF(ISNUMBER(I5),I5/H5,"n/a") -> 0.22503516 | K5: =G5/H5 -> 3.7974684 | L5: =IF(ISNUMBER(I5),G5/I5,"n/a") -> 16.875 | M5: No | N5: n/a | O5: Cash | P5: Cognizant press release, 15 Sep 2014 | Q5: Healthcare IT platform; EBITDA approx.
B6: 2015-04 | C6: Capgemini | D6: Strategic | E6: IGATE | F6: US | G6: 4040 | H6: 1269 | I6: 310 | J6: =IF(ISNUMBER(I6),I6/H6,"n/a") -> 0.24428684 | K6: =G6/H6 -> 3.1836091 | L6: =IF(ISNUMBER(I6),G6/I6,"n/a") -> 13.032258 | M6: Yes | N6: 0.047 | O6: Cash (US$48/share) | P6: Capgemini press release, 27 Apr 2015; IGATE 10-K FY2014 | Q6: Premium to prior close; ~20% to 3-month average
B7: 2016-03 | C7: NTT Data | D7: Strategic | E7: Dell Services | F7: US | G7: 3055 | H7: 2700 | I7: n/a | J7: =IF(ISNUMBER(I7),I7/H7,"n/a") -> n/a | K7: =G7/H7 -> 1.1314815 | L7: =IF(ISNUMBER(I7),G7/I7,"n/a") -> n/a | M7: No | N7: n/a | O7: Cash | P7: NTT Data / Dell press release, 28 Mar 2016 | Q7: Carve-out; revenue approx.; low margin legacy infrastructure
B8: 2016-04 | C8: Blackstone | D8: Sponsor | E8: Mphasis (60.5% stake from HP) | F8: India | G8: 1400 | H8: 920 | I8: n/a | J8: =IF(ISNUMBER(I8),I8/H8,"n/a") -> n/a | K8: =G8/H8 -> 1.5217391 | L8: =IF(ISNUMBER(I8),G8/I8,"n/a") -> n/a | M8: Yes | N8: n/a | O8: Cash (INR 430/share) + open offer | P8: Blackstone press release, 4 Apr 2016; Mphasis FY16 annual report | Q8: Implied 100% EV approx.; stake purchase with open offer
B9: 2016-10 | C9: Wipro | D9: Strategic | E9: Appirio | F9: US | G9: 500 | H9: 200 | I9: n/a | J9: =IF(ISNUMBER(I9),I9/H9,"n/a") -> n/a | K9: =G9/H9 -> 2.5 | L9: =IF(ISNUMBER(I9),G9/I9,"n/a") -> n/a | M9: No | N9: n/a | O9: Cash | P9: Wipro press release, 20 Oct 2016 | Q9: Salesforce/Workday cloud services; revenue approx. (2016E)
B10: 2018-07 | C10: Atos | D10: Strategic | E10: Syntel | F10: US | G10: 3400 | H10: 924 | I10: 250 | J10: =IF(ISNUMBER(I10),I10/H10,"n/a") -> 0.27056277 | K10: =G10/H10 -> 3.6796537 | L10: =IF(ISNUMBER(I10),G10/I10,"n/a") -> 13.6 | M10: Yes | N10: 0.046 | O10: Cash (US$41/share) | P10: Atos press release, 22 Jul 2018; Syntel 10-K FY2017 | Q10: Premium to prior close after a run-up; ~24% to 3-month VWAP. EBITDA approx. (27% margin)
B11: 2019-06 | C11: Capgemini | D11: Strategic | E11: Altran Technologies | F11: France | G11: 5650 | H11: 3300 | I11: n/a | J11: =IF(ISNUMBER(I11),I11/H11,"n/a") -> n/a | K11: =G11/H11 -> 1.7121212 | L11: =IF(ISNUMBER(I11),G11/I11,"n/a") -> n/a | M11: Yes | N11: 0.22 | O11: Cash (€14/share) | P11: Capgemini press release, 24 Jun 2019; Altran 2018 annual report | Q11: EV ≈ €5.0bn incl. debt; converted at 1.13
B12: 2021-03 | C12: Wipro | D12: Strategic | E12: Capco | F12: UK | G12: 1450 | H12: 720 | I12: n/a | J12: =IF(ISNUMBER(I12),I12/H12,"n/a") -> n/a | K12: =G12/H12 -> 2.0138889 | L12: =IF(ISNUMBER(I12),G12/I12,"n/a") -> n/a | M12: No | N12: n/a | O12: Cash | P12: Wipro press release, 4 Mar 2021 | Q12: Financial-services consulting; 2020 revenue approx.
B13: 2021-10 | C13: Carlyle | D13: Sponsor | E13: Hexaware Technologies | F13: India | G13: 3000 | H13: 850 | I13: n/a | J13: =IF(ISNUMBER(I13),I13/H13,"n/a") -> n/a | K13: =G13/H13 -> 3.5294118 | L13: =IF(ISNUMBER(I13),G13/I13,"n/a") -> n/a | M13: No | N13: n/a | O13: Cash | P13: Carlyle / Baring PE Asia press release, Oct 2021 | Q13: Secondary buyout from Baring; EV approx.
B14: 2022-05 | C14: Wipro | D14: Strategic | E14: Rizing | F14: US | G14: 540 | H14: 180 | I14: n/a | J14: =IF(ISNUMBER(I14),I14/H14,"n/a") -> n/a | K14: =G14/H14 -> 3 | L14: =IF(ISNUMBER(I14),G14/I14,"n/a") -> n/a | M14: No | N14: n/a | O14: Cash | P14: Wipro press release, 5 May 2022 | Q14: SAP services; revenue approx.
B15: 2022-05 | C15: L&T Infotech | D15: Strategic | E15: Mindtree (merger) | F15: India | G15: 6700 | H15: 1410 | I15: 290 | J15: =IF(ISNUMBER(I15),I15/H15,"n/a") -> 0.20567376 | K15: =G15/H15 -> 4.751773 | L15: =IF(ISNUMBER(I15),G15/I15,"n/a") -> 23.103448 | M15: Yes | N15: 0 | O15: Stock (73 LTI shares per 100 Mindtree) | P15: LTI / Mindtree exchange filings, 6 May 2022; Mindtree FY22 annual report | Q15: Both under L&T control: not arm's-length; ratio ≈ market, premium ≈ 0
B16: 2024-01 | C16: Infosys | D16: Strategic | E16: in-tech | F16: Germany | G16: 490 | H16: 185 | I16: n/a | J16: =IF(ISNUMBER(I16),I16/H16,"n/a") -> n/a | K16: =G16/H16 -> 2.6486486 | L16: =IF(ISNUMBER(I16),G16/I16,"n/a") -> n/a | M16: No | N16: n/a | O16: Cash (€450m) | P16: Infosys press release, 18 Jan 2024 | Q16: Engineering R&D services; converted at 1.09
B17: 2024-05 | C17: Coforge | D17: Strategic | E17: Cigniti Technologies (54% + open offer) | F17: India | G17: 440 | H17: 220 | I17: 30 | J17: =IF(ISNUMBER(I17),I17/H17,"n/a") -> 0.13636364 | K17: =G17/H17 -> 2 | L17: =IF(ISNUMBER(I17),G17/I17,"n/a") -> 14.666667 | M17: Yes | N17: n/a | O17: Cash (INR 1,415/share) | P17: Coforge exchange filing, 2 May 2024; Cigniti FY24 annual report | Q17: Implied 100% EV approx.; struck near market
B18: 2024-06 | C18: Cognizant | D18: Strategic | E18: Belcan | F18: US | G18: 1290 | H18: 800 | I18: n/a | J18: =IF(ISNUMBER(I18),I18/H18,"n/a") -> n/a | K18: =G18/H18 -> 1.6125 | L18: =IF(ISNUMBER(I18),G18/I18,"n/a") -> n/a | M18: No | N18: n/a | O18: Cash and stock | P18: Cognizant press release, 10 Jun 2024 | Q18: Engineering services; revenue approx. (2023)
B20: STATISTICS
B21: Maximum | J21: =MAX(J5:J18) -> 0.27056277 | K21: =MAX(K5:K18) -> 4.751773 | L21: =MAX(L5:L18) -> 23.103448 | N21: =MAX(N5:N18) -> 0.22
B22: 75th percentile | J22: =PERCENTILE(J5:J18,0.75) -> 0.24428684 | K22: =PERCENTILE(K5:K18,0.75) -> 3.4429611 | L22: =PERCENTILE(L5:L18,0.75) -> 16.875 | N22: =PERCENTILE(N5:N18,0.75) -> 0.09025
B23: Median | J23: =MEDIAN(J5:J18) -> 0.22503516 | K23: =MEDIAN(K5:K18) -> 2.5743243 | L23: =MEDIAN(L5:L18) -> 14.666667 | N23: =MEDIAN(N5:N18) -> 0.0465
B24: Mean | J24: =AVERAGE(J5:J18) -> 0.21638443 | K24: =AVERAGE(K5:K18) -> 2.6487354 | L24: =AVERAGE(L5:L18) -> 16.255475 | N24: =AVERAGE(N5:N18) -> 0.07825
B25: 25th percentile | J25: =PERCENTILE(J5:J18,0.25) -> 0.20567376 | K25: =PERCENTILE(K5:K18,0.25) -> 1.7840909 | L25: =PERCENTILE(L5:L18,0.25) -> 13.6 | N25: =PERCENTILE(N5:N18,0.25) -> 0.0345
B26: Minimum | J26: =MIN(J5:J18) -> 0.13636364 | K26: =MIN(K5:K18) -> 1.1314815 | L26: =MIN(L5:L18) -> 13.032258 | N26: =MIN(N5:N18) -> 0
B27: Count | J27: =COUNT(J5:J18) -> 5 | K27: =COUNT(K5:K18) -> 14 | L27: =COUNT(L5:L18) -> 5 | N27: =COUNT(N5:N18) -> 4
B28: Text entries ('n/a') are ignored by the statistical functions, so EV/EBITDA and premium statistics are computed only over the deals where the figure was disclosed. Count shows how many observations each statistic rests on.
B30: BY ACQUIRER TYPE AND TARGET GEOGRAPHY (median EV / Revenue)
B31: Strategic acquirers | K31: {=MEDIAN(IF(D$5:D$18="Strategic",K$5:K$18))} -> 2.5743243 | L31: =COUNTIF(D5:D18,"Strategic") -> 12 | M31: deals
B32: Financial sponsors | K32: {=MEDIAN(IF(D$5:D$18="Sponsor",K$5:K$18))} -> 2.5255754 | L32: =COUNTIF(D5:D18,"Sponsor") -> 2 | M32: deals
B33: India-headquartered targets | K33: {=MEDIAN(IF(F$5:F$18="India",K$5:K$18))} -> 2.7647059 | L33: =COUNTIF(F5:F18,"India") -> 4 | M33: deals
B34: US / Europe targets | K34: {=MEDIAN(IF(F$5:F$18<>"India",K$5:K$18))} -> 2.5743243 | L34: =COUNTIF(F5:F18,"<>India") -> 10 | M34: deals

Sheet Summary
B1: Tata Consultancy Services — Precedent Transactions — IT Services | H1: TATA CONSULTANCY SERVICES
B2: Precedent multiples, control premium versus trading comps, and the implied TCS range
B4: PRECEDENT MULTIPLES
C5: 25th pct | D5: Median | E5: 75th pct | F5: Count
B6: EV / LTM revenue | C6: =Transactions!K25 -> 1.7840909 | D6: =Transactions!K23 -> 2.5743243 | E6: =Transactions!K22 -> 3.4429611 | F6: =Transactions!K27 -> 14
B7: EV / LTM EBITDA (disclosed deals) | C7: =Transactions!L25 -> 13.6 | D7: =Transactions!L23 -> 14.666667 | E7: =Transactions!L22 -> 16.875 | F7: =Transactions!L27 -> 5
B8: EBITDA margin of targets | C8: =Transactions!J25 -> 0.20567376 | D8: =Transactions!J23 -> 0.22503516 | E8: =Transactions!J22 -> 0.24428684 | F8: =Transactions!J27 -> 5
B9: 1-day premium (public targets) | C9: =Transactions!N25 -> 0.0345 | D9: =Transactions!N23 -> 0.0465 | E9: =Transactions!N22 -> 0.09025 | F9: =Transactions!N27 -> 4
B11: CONTROL PREMIUM: PRECEDENTS vs TRADING COMPARABLES
B12: Precedent median EV / Revenue | C12: =Transactions!K23 -> 2.5743243
B13: Trading-comps peer median EV / Revenue (Project 3) | C13: =Inputs!$C$19 -> 1.82
B14: Implied control premium on revenue multiple | C14: =C12/C13-1 -> 0.41446391
B15: Precedent median EV / EBITDA | C15: =Transactions!L23 -> 14.666667
B16: Trading-comps peer median EV / EBITDA (Project 3) | C16: =Inputs!$C$20 -> 8.75
B17: Implied control premium on EBITDA multiple | C17: =C15/C16-1 -> 0.67619048
B19: IMPLIED TCS VALUE PER SHARE (INR) — illustrative
B20: Multiple | C20: TCS metric (US$m) | D20: 25th pct | E20: Median | F20: 75th pct | G20: Implied @25th | H20: Implied @median | I20: Implied @75th
B21: EV / LTM revenue | C21: =Inputs!$C$13 -> 28627 | D21: =Transactions!K25 -> 1.7840909 | E21: =Transactions!K23 -> 2.5743243 | F21: =Transactions!K22 -> 3.4429611 | G21: =(Inputs!$C$13*Transactions!K25-Inputs!$C$15)/Inputs!$C$16/Inputs!$C$17 -> 1428.4059 | H21: =(Inputs!$C$13*Transactions!K23-Inputs!$C$15)/Inputs!$C$16/Inputs!$C$17 -> 2025.7719 | I21: =(Inputs!$C$13*Transactions!K22-Inputs!$C$15)/Inputs!$C$16/Inputs!$C$17 -> 2682.4057
B22: EV / LTM EBITDA | C22: =Inputs!$C$14 -> 7748 | D22: =Transactions!L25 -> 13.6 | E22: =Transactions!L23 -> 14.666667 | F22: =Transactions!L22 -> 16.875 | G22: =(Inputs!$C$14*Transactions!L25-Inputs!$C$15)/Inputs!$C$16/Inputs!$C$17 -> 2862.2637 | H22: =(Inputs!$C$14*Transactions!L23-Inputs!$C$15)/Inputs!$C$16/Inputs!$C$17 -> 3080.5003 | I22: =(Inputs!$C$14*Transactions!L22-Inputs!$C$15)/Inputs!$C$16/Inputs!$C$17 -> 3532.3182
B23: Current TCS share price (INR) | H23: =Inputs!$C$18 -> 2200.8
B25: Illustrative only: every precedent target is a fraction of TCS's size and none is a like-for-like control transaction for a US$80bn company. The range is shown to complete the football field (Project 5) and to quantify the sector's control premium; it is not a takeover valuation of TCS.
B27: READING THE RESULT
B28: • Precedent multiples sit above trading multiples for the same kind of business: buyers pay a control premium for synergies and for the right to run the asset. The gap between the two medians is the sector's typical premium; the public-target 1-day premia are low here because several targets (IGATE, Syntel) had run up on deal speculation, and one (LTI–Mindtree) was a merger under common control.
B29: • Strategic acquirers dominate this sector and paid more than sponsors, consistent with synergies being real in offshore IT services (client cross-sell, pyramid cost savings).
B30: • Multiples cluster around 1.5–3.5× revenue for mid-cap services assets; the outliers (TriZetto, Mindtree) had platform or scarcity value. A banker would show this dispersion to a seller before quoting a price.
B31: • The data quality caveat on the Inputs sheet is part of the deliverable: precedent analysis from public sources always carries approximation in private-target metrics, and saying so is more credible than false precision.

Sheet Checks
B1: Tata Consultancy Services — Precedent Transactions — IT Services | D1: TATA CONSULTANCY SERVICES
B2: Integrity checks · should all be TRUE
B4: All EV / Revenue multiples positive | C4: =MIN(Transactions!K5:K18)>0 -> TRUE
B5: EV / Revenue median within 1x–6x | C5: =AND(Transactions!K23>1,Transactions!K23<6) -> TRUE
B6: EV / EBITDA statistics computed on ≥ 4 disclosed deals | C6: =Transactions!L27>=4 -> TRUE
B7: Control premium on revenue multiple is positive | C7: =Summary!C14>0 -> TRUE
B8: Implied TCS range is ordered | C8: =AND(Summary!G21<=Summary!H21,Summary!H21<=Summary!I21) -> TRUE
B10: OVERALL | C10: =IF(COUNTIF(C4:C8,FALSE())=0,"MODEL OK","CHECK ERRORS") -> MODEL OK
