Workbook

Sheet Cover
B3: IB PORTFOLIO · PROJECT 11 OF 20
B4: Emirates NBD
B5: Bank Valuation — Dividend Discount and Excess Return
B6: DFM: EMIRATESNBD · AED millions · per-share values in AED · as of FY2025 accounts · market data 18 Sep 2026
B9: What this is | C9: An equity-side valuation of Emirates NBD on the FY2025 audited accounts and 18 September 2026 market data. A five-year equity roll-forward under clean surplus feeds both a dividend discount model and an excess-return model; the two are forced to agree, the justified multiples are derived, and the share price is run backwards into the return on equity and the cost of equity it implies.
B11: How it is built | C11: • Cost of equity built up from the US Treasury yield (the dirham is pegged), a UAE country risk premium, a mature-market equity premium and a stated beta.
C12: • An equity roll-forward with ROE fading from 17% to a 14% terminal level and a payout that rises so retained earnings fund exactly the growth assumed; the terminal payout is derived, not typed.
C13: • A dividend discount model with a Gordon terminal value, and an excess-return model starting from book value; the Checks sheet requires them to agree to the fils.
C14: • Justified P/B and P/E, the market-implied ROE and cost of equity, and two closed-form sensitivity grids.
B16: Contents | C16: Summary — the bank today, the two values, what the price implies
C17: Forecast — equity roll-forward, EPS, DPS and BVPS, terminal year
C18: DDM — dividends discounted plus terminal value
C19: Excess Return — book value plus capitalised spread over the cost of equity
C20: Justified Multiples — P/B and P/E from fundamentals; implied ROE and cost of equity
C21: Sensitivity — cost of equity against growth and against terminal ROE
C22: Inputs — FY2025 accounts, market data, cost of equity, terminal assumptions
C23: Checks — fourteen tests; must read MODEL OK
B25: Key outputs (live) | C25: Return on equity, FY2025 | E25: =Inputs!$C$13 -> 0.17327735
C26: Cost of equity | E26: =Inputs!$C$34 -> 0.1
C27: DDM value per share (AED) | E27: =DDM!$C$20 -> 41.714383
C28: Excess-return value per share (AED) | E28: ='Excess Return'!$C$24 -> 41.714383
C29: Upside / (downside) | E29: =DDM!$C$21 -> 0.34649395
C30: Sustainable ROE the price implies | E30: ='Justified Multiples'!$C$11 -> 0.12465933
B32: Colour code | C32: Blue = hard-coded input
C33: Black = formula
C34: Green = link to another sheet
C35: Accent fill = scenario selector / key levers
B37: Sources | C37: Emirates NBD Bank PJSC FY2025 annual accounts, via the Yahoo Finance fundamentals series for EMIRATESNBD.AE; the same figures used in Project 6.
C38: Share price and 52-week range: Dubai Financial Market close, 18 September 2026.
C39: US Treasury yield, UAE country risk premium and equity risk premium: September 2026 market data and Damodaran's country tables; beta is a stated input.
C40: Nothing here is a recommendation. The valuation is an analytical exercise on public information.
B42: Prepared by | C42: Jainam Mehta · github.com/jainammehta1215/ib-portfolio

Sheet Inputs
B1: Emirates NBD — Bank Valuation — Dividend Discount and Excess Return | F1: EMIRATES NBD
B2: FY2025 accounts, market data, cost of equity and terminal assumptions
B4: FY2025 ACCOUNTS (AED millions)
B5: Net profit attributable to equity holders | C5: 23442 | F5: As in Project 6
B6: Net profit, FY2024 | C6: 22973
B7: Shareholders' equity, 31 December 2025 | C7: 144582
B8: Shareholders' equity, 31 December 2024 | C8: 125990
B9: Goodwill and intangibles | C9: 5620
B10: Tangible book value | C10: =Inputs!$C$7-Inputs!$C$9 -> 138962
B11: Cash dividends paid in 2025 | C11: 6311 | F11: AED 1.00 per share
B12: Total assets | C12: 1164442
B13: Return on average equity, FY2025 | C13: =Inputs!$C$5/AVERAGE(Inputs!$C$7,Inputs!$C$8) -> 0.17327735
B14: Return on average tangible equity, FY2025 | C14: =Inputs!$C$5/AVERAGE(Inputs!$C$10,Inputs!$C$8-Inputs!$C$9) -> 0.18078756
B15: Dividend payout, FY2025 | C15: =Inputs!$C$11/Inputs!$C$5 -> 0.26921764
B16: Return on assets, FY2025 | C16: =Inputs!$C$5/Inputs!$C$12 -> 0.020131531
B18: MARKET DATA
B19: Share price (AED, DFM close 18 Sep 2026) | C19: 30.98
B20: Shares outstanding (millions) | C20: 6311
B21: Market capitalisation | C21: =Inputs!$C$19*Inputs!$C$20 -> 195514.78
B22: Book value per share (AED) | C22: =Inputs!$C$7/Inputs!$C$20 -> 22.909523
B23: Tangible book value per share (AED) | C23: =Inputs!$C$10/Inputs!$C$20 -> 22.019014
B24: Price / book | C24: =Inputs!$C$19/Inputs!$C$22 -> 1.3522761
B25: Price / tangible book | C25: =Inputs!$C$19/Inputs!$C$23 -> 1.4069658
B26: Price / FY2025 earnings | C26: =Inputs!$C$21/Inputs!$C$5 -> 8.3403626
B27: Dividend yield on the last dividend | C27: =Inputs!$C$11/Inputs!$C$21 -> 0.03227889
B29: COST OF EQUITY
B30: Risk-free rate (10-year US Treasury; the dirham is pegged) | C30: 0.041 | F30: September 2026
B31: UAE country risk premium | C31: 0.009 | F31: Damodaran country tables for an Aa2 sovereign, rounded up for oil-price and regional concentration
B32: Mature-market equity risk premium | C32: 0.05
B33: Beta versus the DFM General Index | C33: 1 | F33: Large domestic banks sit close to their index; stated input
B34: Cost of equity | C34: =Inputs!$C$30+Inputs!$C$31+Inputs!$C$33*Inputs!$C$32 -> 0.1
B36: TERMINAL ASSUMPTIONS
B37: Long-run growth in earnings and book value | C37: 0.03 | F37: Nominal UAE GDP trend less some share loss; must be below the cost of equity
B38: Terminal return on equity | C38: 0.14 | F38: Below today's 17%: rate cuts compress margins and capital builds
B39: Terminal payout (1 − g / ROE, so book grows at g) | C39: =1-Inputs!$C$37/Inputs!$C$38 -> 0.78571429 | F39: Not a free input. If payout and growth are set independently the two models diverge

Sheet Forecast
B1: Emirates NBD — Bank Valuation — Dividend Discount and Excess Return | I1: EMIRATES NBD
B2: Equity roll-forward under clean surplus: closing book = opening book + earnings − dividends
B4: EQUITY ROLL-FORWARD (AED millions)
C5: FY2025A | D5: FY2026E | E5: FY2027E | F5: FY2028E | G5: FY2029E | H5: FY2030E
B6: Opening shareholders' equity | C6: =Inputs!$C$8 -> 125990 | D6: =C11 -> 144582 | E6: =D11 -> 161281.22 | F6: =E11 -> 178570.57 | G6: =F11 -> 196284.77 | H6: =G11 -> 213950.4
B7: Return on opening equity | C7: =Inputs!$C$5/Inputs!$C$8 -> 0.18606239 | D7: 0.165 | E7: 0.16 | F7: 0.155 | G7: 0.15 | H7: 0.145
B8: Net profit | C8: =Inputs!$C$5 -> 23442 | D8: =D6*D7 -> 23856.03 | E8: =E6*E7 -> 25804.995 | F8: =F6*F7 -> 27678.438 | G8: =G6*G7 -> 29442.715 | H8: =H6*H7 -> 31022.808
B9: Payout ratio | C9: =Inputs!$C$11/Inputs!$C$5 -> 0.26921764 | D9: 0.3 | E9: 0.33 | F9: 0.36 | G9: 0.4 | H9: 0.44
B10: Dividends | C10: =Inputs!$C$11 -> 6311 | D10: =D8*D9 -> 7156.809 | E10: =E8*E9 -> 8515.6485 | F10: =F8*F9 -> 9964.2377 | G10: =G8*G9 -> 11777.086 | H10: =H8*H9 -> 13650.035
B11: Closing shareholders' equity | C11: =Inputs!$C$7 -> 144582 | D11: =D6+D8-D10 -> 161281.22 | E11: =E6+E8-E10 -> 178570.57 | F11: =F6+F8-F10 -> 196284.77 | G11: =G6+G8-G10 -> 213950.4 | H11: =H6+H8-H10 -> 231323.17
B12: Growth in book value | C12: =Inputs!$C$7/Inputs!$C$8-1 -> 0.14756727 | D12: =D11/C11-1 -> 0.1155 | E12: =E11/D11-1 -> 0.1072 | F12: =F11/E11-1 -> 0.0992 | G12: =G11/F11-1 -> 0.09 | H12: =H11/G11-1 -> 0.0812
B13: Growth in net profit | C13: =Inputs!$C$5/Inputs!$C$6-1 -> 0.02041527 | D13: =D8/C8-1 -> 0.017661889 | E13: =E8/D8-1 -> 0.08169697 | F13: =F8/E8-1 -> 0.0726 | G13: =G8/F8-1 -> 0.063741935 | H13: =H8/G8-1 -> 0.053666667
B15: PER SHARE (AED)
B16: Earnings per share | C16: =C8/Inputs!$C$20 -> 3.7144668 | D16: =D8/Inputs!$C$20 -> 3.7800713 | E16: =E8/Inputs!$C$20 -> 4.0888917 | F16: =F8/Inputs!$C$20 -> 4.3857452 | G16: =G8/Inputs!$C$20 -> 4.6653011 | H16: =H8/Inputs!$C$20 -> 4.9156723
B17: Dividend per share | C17: =C10/Inputs!$C$20 -> 1 | D17: =D10/Inputs!$C$20 -> 1.1340214 | E17: =E10/Inputs!$C$20 -> 1.3493343 | F17: =F10/Inputs!$C$20 -> 1.5788683 | G17: =G10/Inputs!$C$20 -> 1.8661204 | H17: =H10/Inputs!$C$20 -> 2.1628958
B18: Book value per share (closing) | C18: =C11/Inputs!$C$20 -> 22.909523 | D18: =D11/Inputs!$C$20 -> 25.555573 | E18: =E11/Inputs!$C$20 -> 28.29513 | F18: =F11/Inputs!$C$20 -> 31.102007 | G18: =G11/Inputs!$C$20 -> 33.901188 | H18: =H11/Inputs!$C$20 -> 36.653964
B20: TERMINAL YEAR (FY2031E, the first year of steady state)
B21: Opening equity | C21: =Forecast!H11 -> 231323.17
B22: Net profit at the terminal ROE | C22: =Forecast!$C$21*Inputs!$C$38 -> 32385.244
B23: Dividends at the terminal payout | C23: =Forecast!$C$22*Inputs!$C$39 -> 25445.549
B24: Closing equity | C24: =Forecast!$C$21+Forecast!$C$22-Forecast!$C$23 -> 238262.86
B25: Implied growth in book (must equal g) | C25: =Forecast!$C$24/Forecast!$C$21-1 -> 0.03
B26: FY2025A closing equity is the reported figure, so the historical column absorbs other comprehensive income and any capital movements in that year. From FY2026E clean surplus is enforced exactly. The ROE path fades from the FY2025 level toward the terminal assumption; the payout rises so that retained earnings fund only the growth assumed.

Sheet DDM
B1: Emirates NBD — Bank Valuation — Dividend Discount and Excess Return | I1: EMIRATES NBD
B2: Dividend discount model — explicit dividends plus a Gordon terminal value
B4: PRESENT VALUE OF DIVIDENDS
D5: FY2026E | E5: FY2027E | F5: FY2028E | G5: FY2029E | H5: FY2030E
B6: Year | D6: 1 | E6: 2 | F6: 3 | G6: 4 | H6: 5
B7: Dividends | D7: =Forecast!D10 -> 7156.809 | E7: =Forecast!E10 -> 8515.6485 | F7: =Forecast!F10 -> 9964.2377 | G7: =Forecast!G10 -> 11777.086 | H7: =Forecast!H10 -> 13650.035
B8: Discount factor at the cost of equity | D8: =1/(1+Inputs!$C$34)^D6 -> 0.90909091 | E8: =1/(1+Inputs!$C$34)^E6 -> 0.82644628 | F8: =1/(1+Inputs!$C$34)^F6 -> 0.7513148 | G8: =1/(1+Inputs!$C$34)^G6 -> 0.68301346 | H8: =1/(1+Inputs!$C$34)^H6 -> 0.62092132
B9: Present value | D9: =D7*D8 -> 6506.19 | E9: =E7*E8 -> 7037.726 | F9: =F7*F8 -> 7486.2793 | G9: =G7*G8 -> 8043.9083 | H9: =H7*H8 -> 8475.598
B11: TERMINAL VALUE
B12: Terminal value at end FY2030E: FY2031E dividend / (ke − g) | C12: =Forecast!$C$23/(Inputs!$C$34-Inputs!$C$37) -> 363507.84
B13: Present value of terminal value | C13: =DDM!$C$12*DDM!H8 -> 225709.77
B14: Terminal value / terminal opening book (implied exit P/B) | C14: =DDM!$C$12/Forecast!$C$21 -> 1.5714286 | I14: Should sit close to the justified P/B at the terminal ROE
B16: EQUITY VALUE
B17: Sum of present values of dividends | C17: =SUM(DDM!D9:H9) -> 37549.702
B18: Equity value | C18: =DDM!$C$17+DDM!$C$13 -> 263259.47
B19: Terminal value as % of equity value | C19: =DDM!$C$13/DDM!$C$18 -> 0.85736619
B20: Value per share (AED) | C20: =DDM!$C$18/Inputs!$C$20 -> 41.714383
B21: Upside / (downside) to the share price | C21: =DDM!$C$20/Inputs!$C$19-1 -> 0.34649395
B22: Implied price / book on FY2025 equity | C22: =DDM!$C$18/Inputs!$C$7 -> 1.8208316
B23: Implied price / FY2025 earnings | C23: =DDM!$C$18/Inputs!$C$5 -> 11.230248

Sheet Excess Return
B1: Emirates NBD — Bank Valuation — Dividend Discount and Excess Return | I1: EMIRATES NBD
B2: Book value today plus the present value of returns earned above the cost of equity
B4: EXCESS RETURNS (AED millions)
D5: FY2026E | E5: FY2027E | F5: FY2028E | G5: FY2029E | H5: FY2030E
B6: Opening equity | D6: =Forecast!D6 -> 144582 | E6: =Forecast!E6 -> 161281.22 | F6: =Forecast!F6 -> 178570.57 | G6: =Forecast!G6 -> 196284.77 | H6: =Forecast!H6 -> 213950.4
B7: Return on opening equity | D7: =Forecast!D7 -> 0.165 | E7: =Forecast!E7 -> 0.16 | F7: =Forecast!F7 -> 0.155 | G7: =Forecast!G7 -> 0.15 | H7: =Forecast!H7 -> 0.145
B8: Cost of equity | D8: =Inputs!$C$34 -> 0.1 | E8: =Inputs!$C$34 -> 0.1 | F8: =Inputs!$C$34 -> 0.1 | G8: =Inputs!$C$34 -> 0.1 | H8: =Inputs!$C$34 -> 0.1
B9: Spread: ROE − cost of equity | D9: =D7-D8 -> 0.065 | E9: =E7-E8 -> 0.06 | F9: =F7-F8 -> 0.055 | G9: =G7-G8 -> 0.05 | H9: =H7-H8 -> 0.045
B10: Excess return: spread × opening equity | D10: =D9*D6 -> 9397.83 | E10: =E9*E6 -> 9676.8733 | F10: =F9*F6 -> 9821.3812 | G10: =G9*G6 -> 9814.2384 | H10: =H9*H6 -> 9627.7679
B11: Discount factor | D11: =DDM!D8 -> 0.90909091 | E11: =DDM!E8 -> 0.82644628 | F11: =DDM!F8 -> 0.7513148 | G11: =DDM!G8 -> 0.68301346 | H11: =DDM!H8 -> 0.62092132
B12: Present value of excess return | D12: =D10*D11 -> 8543.4818 | E12: =E10*E11 -> 7997.4159 | F12: =F10*F11 -> 7378.9491 | G12: =G10*G11 -> 6703.2569 | H12: =H10*H11 -> 5978.0864
B14: TERMINAL EXCESS RETURN
B15: FY2031E excess return: (terminal ROE − ke) × opening equity | C15: =(Inputs!$C$38-Inputs!$C$34)*Forecast!$C$21 -> 9252.9268
B16: Terminal value of excess returns at end FY2030E: ER / (ke − g) | C16: ='Excess Return'!$C$15/(Inputs!$C$34-Inputs!$C$37) -> 132184.67
B17: Present value | C17: ='Excess Return'!$C$16*'Excess Return'!H11 -> 82076.279
B19: EQUITY VALUE BUILT UP
B20: Book value today (31 December 2025) | C20: =Inputs!$C$7 -> 144582
B21: Add: present value of explicit excess returns | C21: =SUM('Excess Return'!D12:H12) -> 36601.19
B22: Add: present value of terminal excess returns | C22: ='Excess Return'!$C$17 -> 82076.279
B23: Equity value | C23: ='Excess Return'!$C$20+'Excess Return'!$C$21+'Excess Return'!$C$22 -> 263259.47
B24: Value per share (AED) | C24: ='Excess Return'!$C$23/Inputs!$C$20 -> 41.714383
B25: Share of value that is book value already on the balance sheet | C25: ='Excess Return'!$C$20/'Excess Return'!$C$23 -> 0.54919962
B26: Share of value that is future excess returns | C26: =1-'Excess Return'!$C$25 -> 0.45080038
B27: Difference from the DDM value per share (AED, should be nil) | C27: ='Excess Return'!$C$24-DDM!$C$20 -> 0
B28: The two models agree because the forecast obeys clean surplus and the terminal payout is derived from the terminal ROE and growth rather than set by hand. The excess-return layout says where the value comes from: most of it is book value the bank already holds, and the premium to book is the capitalised spread of ROE over the cost of equity.

Sheet Justified Multiples
B1: Emirates NBD — Bank Valuation — Dividend Discount and Excess Return | F1: EMIRATES NBD
B2: What P/B and P/E the fundamentals justify, and what the price implies
B4: JUSTIFIED PRICE / BOOK: (ROE − g) / (ke − g)
B5: At FY2025 return on equity | C5: =(Inputs!$C$13-Inputs!$C$37)/(Inputs!$C$34-Inputs!$C$37) -> 2.0468193
B6: At the terminal return on equity | C6: =(Inputs!$C$38-Inputs!$C$37)/(Inputs!$C$34-Inputs!$C$37) -> 1.5714286
B7: Market price / book today | C7: =Inputs!$C$24 -> 1.3522761
B8: Model price / book (DDM equity value / FY2025 book) | C8: =DDM!$C$22 -> 1.8208316
B10: WHAT THE PRICE IMPLIES
B11: Sustainable ROE the price implies at the model cost of equity: g + P/B × (ke − g) | C11: =Inputs!$C$37+Inputs!$C$24*(Inputs!$C$34-Inputs!$C$37) -> 0.12465933 | F11: If you believe the cost of equity, this is the return the market expects the bank to sustain
B12: Cost of equity the price implies at the terminal ROE: g + (ROE − g) / P/B | C12: =Inputs!$C$37+(Inputs!$C$38-Inputs!$C$37)/Inputs!$C$24 -> 0.11134434 | F12: If you believe the terminal ROE, this is the discount rate the market is using
B14: JUSTIFIED PRICE / EARNINGS: payout × (1 + g) / (ke − g)
B15: At the terminal payout and growth | C15: =Inputs!$C$39*(1+Inputs!$C$37)/(Inputs!$C$34-Inputs!$C$37) -> 11.561224
B16: Market price / FY2025 earnings | C16: =Inputs!$C$26 -> 8.3403626
B18: The justified P/B formula is the excess-return model collapsed to one line: a bank earning exactly its cost of equity is worth book, and every point of ROE above it adds 1/(ke − g) turns of book. It is the fastest way to see whether a bank's multiple and its returns are telling the same story.

Sheet Sensitivity
B1: Emirates NBD — Bank Valuation — Dividend Discount and Excess Return | H1: EMIRATES NBD
B2: Value per share (AED) — closed-form, every cell rebuilds the terminal value
B4: COST OF EQUITY (rows) versus LONG-RUN GROWTH (columns), terminal ROE at base
B5: ↓ rows \ columns → | C5: 0.02 | D5: 0.025 | E5: 0.03 | F5: 0.035 | G5: 0.04
B6: 0.09 | C6: =((Forecast!D10/(1+$B6)^1+Forecast!E10/(1+$B6)^2+Forecast!F10/(1+$B6)^3+Forecast!G10/(1+$B6)^4+Forecast!H10/(1+$B6)^5)+(Forecast!$C$21*Inputs!$C$38*(1-C$5/Inputs!$C$38))/($B6-C$5)/(1+$B6)^5)/Inputs!$C$20 -> 46.961688 | D6: =((Forecast!D10/(1+$B6)^1+Forecast!E10/(1+$B6)^2+Forecast!F10/(1+$B6)^3+Forecast!G10/(1+$B6)^4+Forecast!H10/(1+$B6)^5)+(Forecast!$C$21*Inputs!$C$38*(1-D$5/Inputs!$C$38))/($B6-D$5)/(1+$B6)^5)/Inputs!$C$20 -> 48.27062 | E6: =((Forecast!D10/(1+$B6)^1+Forecast!E10/(1+$B6)^2+Forecast!F10/(1+$B6)^3+Forecast!G10/(1+$B6)^4+Forecast!H10/(1+$B6)^5)+(Forecast!$C$21*Inputs!$C$38*(1-E$5/Inputs!$C$38))/($B6-E$5)/(1+$B6)^5)/Inputs!$C$20 -> 49.797708 | F6: =((Forecast!D10/(1+$B6)^1+Forecast!E10/(1+$B6)^2+Forecast!F10/(1+$B6)^3+Forecast!G10/(1+$B6)^4+Forecast!H10/(1+$B6)^5)+(Forecast!$C$21*Inputs!$C$38*(1-F$5/Inputs!$C$38))/($B6-F$5)/(1+$B6)^5)/Inputs!$C$20 -> 51.602447 | G6: =((Forecast!D10/(1+$B6)^1+Forecast!E10/(1+$B6)^2+Forecast!F10/(1+$B6)^3+Forecast!G10/(1+$B6)^4+Forecast!H10/(1+$B6)^5)+(Forecast!$C$21*Inputs!$C$38*(1-G$5/Inputs!$C$38))/($B6-G$5)/(1+$B6)^5)/Inputs!$C$20 -> 53.768135
B7: 0.095 | C7: =((Forecast!D10/(1+$B7)^1+Forecast!E10/(1+$B7)^2+Forecast!F10/(1+$B7)^3+Forecast!G10/(1+$B7)^4+Forecast!H10/(1+$B7)^5)+(Forecast!$C$21*Inputs!$C$38*(1-C$5/Inputs!$C$38))/($B7-C$5)/(1+$B7)^5)/Inputs!$C$20 -> 43.289283 | D7: =((Forecast!D10/(1+$B7)^1+Forecast!E10/(1+$B7)^2+Forecast!F10/(1+$B7)^3+Forecast!G10/(1+$B7)^4+Forecast!H10/(1+$B7)^5)+(Forecast!$C$21*Inputs!$C$38*(1-D$5/Inputs!$C$38))/($B7-D$5)/(1+$B7)^5)/Inputs!$C$20 -> 44.287152 | E7: =((Forecast!D10/(1+$B7)^1+Forecast!E10/(1+$B7)^2+Forecast!F10/(1+$B7)^3+Forecast!G10/(1+$B7)^4+Forecast!H10/(1+$B7)^5)+(Forecast!$C$21*Inputs!$C$38*(1-E$5/Inputs!$C$38))/($B7-E$5)/(1+$B7)^5)/Inputs!$C$20 -> 45.438539 | F7: =((Forecast!D10/(1+$B7)^1+Forecast!E10/(1+$B7)^2+Forecast!F10/(1+$B7)^3+Forecast!G10/(1+$B7)^4+Forecast!H10/(1+$B7)^5)+(Forecast!$C$21*Inputs!$C$38*(1-F$5/Inputs!$C$38))/($B7-F$5)/(1+$B7)^5)/Inputs!$C$20 -> 46.781825 | G7: =((Forecast!D10/(1+$B7)^1+Forecast!E10/(1+$B7)^2+Forecast!F10/(1+$B7)^3+Forecast!G10/(1+$B7)^4+Forecast!H10/(1+$B7)^5)+(Forecast!$C$21*Inputs!$C$38*(1-G$5/Inputs!$C$38))/($B7-G$5)/(1+$B7)^5)/Inputs!$C$20 -> 48.369344
B8: 0.1 | C8: =((Forecast!D10/(1+$B8)^1+Forecast!E10/(1+$B8)^2+Forecast!F10/(1+$B8)^3+Forecast!G10/(1+$B8)^4+Forecast!H10/(1+$B8)^5)+(Forecast!$C$21*Inputs!$C$38*(1-C$5/Inputs!$C$38))/($B8-C$5)/(1+$B8)^5)/Inputs!$C$20 -> 40.088724 | D8: =((Forecast!D10/(1+$B8)^1+Forecast!E10/(1+$B8)^2+Forecast!F10/(1+$B8)^3+Forecast!G10/(1+$B8)^4+Forecast!H10/(1+$B8)^5)+(Forecast!$C$21*Inputs!$C$38*(1-D$5/Inputs!$C$38))/($B8-D$5)/(1+$B8)^5)/Inputs!$C$20 -> 40.847364 | E8: =((Forecast!D10/(1+$B8)^1+Forecast!E10/(1+$B8)^2+Forecast!F10/(1+$B8)^3+Forecast!G10/(1+$B8)^4+Forecast!H10/(1+$B8)^5)+(Forecast!$C$21*Inputs!$C$38*(1-E$5/Inputs!$C$38))/($B8-E$5)/(1+$B8)^5)/Inputs!$C$20 -> 41.714383 | F8: =((Forecast!D10/(1+$B8)^1+Forecast!E10/(1+$B8)^2+Forecast!F10/(1+$B8)^3+Forecast!G10/(1+$B8)^4+Forecast!H10/(1+$B8)^5)+(Forecast!$C$21*Inputs!$C$38*(1-F$5/Inputs!$C$38))/($B8-F$5)/(1+$B8)^5)/Inputs!$C$20 -> 42.714788 | G8: =((Forecast!D10/(1+$B8)^1+Forecast!E10/(1+$B8)^2+Forecast!F10/(1+$B8)^3+Forecast!G10/(1+$B8)^4+Forecast!H10/(1+$B8)^5)+(Forecast!$C$21*Inputs!$C$38*(1-G$5/Inputs!$C$38))/($B8-G$5)/(1+$B8)^5)/Inputs!$C$20 -> 43.881928
B9: 0.105 | C9: =((Forecast!D10/(1+$B9)^1+Forecast!E10/(1+$B9)^2+Forecast!F10/(1+$B9)^3+Forecast!G10/(1+$B9)^4+Forecast!H10/(1+$B9)^5)+(Forecast!$C$21*Inputs!$C$38*(1-C$5/Inputs!$C$38))/($B9-C$5)/(1+$B9)^5)/Inputs!$C$20 -> 37.276379 | D9: =((Forecast!D10/(1+$B9)^1+Forecast!E10/(1+$B9)^2+Forecast!F10/(1+$B9)^3+Forecast!G10/(1+$B9)^4+Forecast!H10/(1+$B9)^5)+(Forecast!$C$21*Inputs!$C$38*(1-D$5/Inputs!$C$38))/($B9-D$5)/(1+$B9)^5)/Inputs!$C$20 -> 37.848963 | E9: =((Forecast!D10/(1+$B9)^1+Forecast!E10/(1+$B9)^2+Forecast!F10/(1+$B9)^3+Forecast!G10/(1+$B9)^4+Forecast!H10/(1+$B9)^5)+(Forecast!$C$21*Inputs!$C$38*(1-E$5/Inputs!$C$38))/($B9-E$5)/(1+$B9)^5)/Inputs!$C$20 -> 38.49789 | F9: =((Forecast!D10/(1+$B9)^1+Forecast!E10/(1+$B9)^2+Forecast!F10/(1+$B9)^3+Forecast!G10/(1+$B9)^4+Forecast!H10/(1+$B9)^5)+(Forecast!$C$21*Inputs!$C$38*(1-F$5/Inputs!$C$38))/($B9-F$5)/(1+$B9)^5)/Inputs!$C$20 -> 39.239522 | G9: =((Forecast!D10/(1+$B9)^1+Forecast!E10/(1+$B9)^2+Forecast!F10/(1+$B9)^3+Forecast!G10/(1+$B9)^4+Forecast!H10/(1+$B9)^5)+(Forecast!$C$21*Inputs!$C$38*(1-G$5/Inputs!$C$38))/($B9-G$5)/(1+$B9)^5)/Inputs!$C$20 -> 40.095251
B10: 0.11 | C10: =((Forecast!D10/(1+$B10)^1+Forecast!E10/(1+$B10)^2+Forecast!F10/(1+$B10)^3+Forecast!G10/(1+$B10)^4+Forecast!H10/(1+$B10)^5)+(Forecast!$C$21*Inputs!$C$38*(1-C$5/Inputs!$C$38))/($B10-C$5)/(1+$B10)^5)/Inputs!$C$20 -> 34.787216 | D10: =((Forecast!D10/(1+$B10)^1+Forecast!E10/(1+$B10)^2+Forecast!F10/(1+$B10)^3+Forecast!G10/(1+$B10)^4+Forecast!H10/(1+$B10)^5)+(Forecast!$C$21*Inputs!$C$38*(1-D$5/Inputs!$C$38))/($B10-D$5)/(1+$B10)^5)/Inputs!$C$20 -> 35.213732 | E10: =((Forecast!D10/(1+$B10)^1+Forecast!E10/(1+$B10)^2+Forecast!F10/(1+$B10)^3+Forecast!G10/(1+$B10)^4+Forecast!H10/(1+$B10)^5)+(Forecast!$C$21*Inputs!$C$38*(1-E$5/Inputs!$C$38))/($B10-E$5)/(1+$B10)^5)/Inputs!$C$20 -> 35.693563 | F10: =((Forecast!D10/(1+$B10)^1+Forecast!E10/(1+$B10)^2+Forecast!F10/(1+$B10)^3+Forecast!G10/(1+$B10)^4+Forecast!H10/(1+$B10)^5)+(Forecast!$C$21*Inputs!$C$38*(1-F$5/Inputs!$C$38))/($B10-F$5)/(1+$B10)^5)/Inputs!$C$20 -> 36.237372 | G10: =((Forecast!D10/(1+$B10)^1+Forecast!E10/(1+$B10)^2+Forecast!F10/(1+$B10)^3+Forecast!G10/(1+$B10)^4+Forecast!H10/(1+$B10)^5)+(Forecast!$C$21*Inputs!$C$38*(1-G$5/Inputs!$C$38))/($B10-G$5)/(1+$B10)^5)/Inputs!$C$20 -> 36.858867
B12: COST OF EQUITY (rows) versus TERMINAL ROE (columns), growth at base
B13: ↓ rows \ columns → | C13: 0.12 | D13: 0.13 | E13: 0.14 | F13: 0.15 | G13: 0.16
B14: 0.09 | C14: =((Forecast!D10/(1+$B14)^1+Forecast!E10/(1+$B14)^2+Forecast!F10/(1+$B14)^3+Forecast!G10/(1+$B14)^4+Forecast!H10/(1+$B14)^5)+(Forecast!$C$21*C$13*(1-Inputs!$C$37/C$13))/($B14-Inputs!$C$37)/(1+$B14)^5)/Inputs!$C$20 -> 41.856854 | D14: =((Forecast!D10/(1+$B14)^1+Forecast!E10/(1+$B14)^2+Forecast!F10/(1+$B14)^3+Forecast!G10/(1+$B14)^4+Forecast!H10/(1+$B14)^5)+(Forecast!$C$21*D$13*(1-Inputs!$C$37/D$13))/($B14-Inputs!$C$37)/(1+$B14)^5)/Inputs!$C$20 -> 45.827281 | E14: =((Forecast!D10/(1+$B14)^1+Forecast!E10/(1+$B14)^2+Forecast!F10/(1+$B14)^3+Forecast!G10/(1+$B14)^4+Forecast!H10/(1+$B14)^5)+(Forecast!$C$21*E$13*(1-Inputs!$C$37/E$13))/($B14-Inputs!$C$37)/(1+$B14)^5)/Inputs!$C$20 -> 49.797708 | F14: =((Forecast!D10/(1+$B14)^1+Forecast!E10/(1+$B14)^2+Forecast!F10/(1+$B14)^3+Forecast!G10/(1+$B14)^4+Forecast!H10/(1+$B14)^5)+(Forecast!$C$21*F$13*(1-Inputs!$C$37/F$13))/($B14-Inputs!$C$37)/(1+$B14)^5)/Inputs!$C$20 -> 53.768135 | G14: =((Forecast!D10/(1+$B14)^1+Forecast!E10/(1+$B14)^2+Forecast!F10/(1+$B14)^3+Forecast!G10/(1+$B14)^4+Forecast!H10/(1+$B14)^5)+(Forecast!$C$21*G$13*(1-Inputs!$C$37/G$13))/($B14-Inputs!$C$37)/(1+$B14)^5)/Inputs!$C$20 -> 57.738562
B15: 0.095 | C15: =((Forecast!D10/(1+$B15)^1+Forecast!E10/(1+$B15)^2+Forecast!F10/(1+$B15)^3+Forecast!G10/(1+$B15)^4+Forecast!H10/(1+$B15)^5)+(Forecast!$C$21*C$13*(1-Inputs!$C$37/C$13))/($B15-Inputs!$C$37)/(1+$B15)^5)/Inputs!$C$20 -> 38.274351 | D15: =((Forecast!D10/(1+$B15)^1+Forecast!E10/(1+$B15)^2+Forecast!F10/(1+$B15)^3+Forecast!G10/(1+$B15)^4+Forecast!H10/(1+$B15)^5)+(Forecast!$C$21*D$13*(1-Inputs!$C$37/D$13))/($B15-Inputs!$C$37)/(1+$B15)^5)/Inputs!$C$20 -> 41.856445 | E15: =((Forecast!D10/(1+$B15)^1+Forecast!E10/(1+$B15)^2+Forecast!F10/(1+$B15)^3+Forecast!G10/(1+$B15)^4+Forecast!H10/(1+$B15)^5)+(Forecast!$C$21*E$13*(1-Inputs!$C$37/E$13))/($B15-Inputs!$C$37)/(1+$B15)^5)/Inputs!$C$20 -> 45.438539 | F15: =((Forecast!D10/(1+$B15)^1+Forecast!E10/(1+$B15)^2+Forecast!F10/(1+$B15)^3+Forecast!G10/(1+$B15)^4+Forecast!H10/(1+$B15)^5)+(Forecast!$C$21*F$13*(1-Inputs!$C$37/F$13))/($B15-Inputs!$C$37)/(1+$B15)^5)/Inputs!$C$20 -> 49.020634 | G15: =((Forecast!D10/(1+$B15)^1+Forecast!E10/(1+$B15)^2+Forecast!F10/(1+$B15)^3+Forecast!G10/(1+$B15)^4+Forecast!H10/(1+$B15)^5)+(Forecast!$C$21*G$13*(1-Inputs!$C$37/G$13))/($B15-Inputs!$C$37)/(1+$B15)^5)/Inputs!$C$20 -> 52.602728
B16: 0.1 | C16: =((Forecast!D10/(1+$B16)^1+Forecast!E10/(1+$B16)^2+Forecast!F10/(1+$B16)^3+Forecast!G10/(1+$B16)^4+Forecast!H10/(1+$B16)^5)+(Forecast!$C$21*C$13*(1-Inputs!$C$37/C$13))/($B16-Inputs!$C$37)/(1+$B16)^5)/Inputs!$C$20 -> 35.211746 | D16: =((Forecast!D10/(1+$B16)^1+Forecast!E10/(1+$B16)^2+Forecast!F10/(1+$B16)^3+Forecast!G10/(1+$B16)^4+Forecast!H10/(1+$B16)^5)+(Forecast!$C$21*D$13*(1-Inputs!$C$37/D$13))/($B16-Inputs!$C$37)/(1+$B16)^5)/Inputs!$C$20 -> 38.463064 | E16: =((Forecast!D10/(1+$B16)^1+Forecast!E10/(1+$B16)^2+Forecast!F10/(1+$B16)^3+Forecast!G10/(1+$B16)^4+Forecast!H10/(1+$B16)^5)+(Forecast!$C$21*E$13*(1-Inputs!$C$37/E$13))/($B16-Inputs!$C$37)/(1+$B16)^5)/Inputs!$C$20 -> 41.714383 | F16: =((Forecast!D10/(1+$B16)^1+Forecast!E10/(1+$B16)^2+Forecast!F10/(1+$B16)^3+Forecast!G10/(1+$B16)^4+Forecast!H10/(1+$B16)^5)+(Forecast!$C$21*F$13*(1-Inputs!$C$37/F$13))/($B16-Inputs!$C$37)/(1+$B16)^5)/Inputs!$C$20 -> 44.965701 | G16: =((Forecast!D10/(1+$B16)^1+Forecast!E10/(1+$B16)^2+Forecast!F10/(1+$B16)^3+Forecast!G10/(1+$B16)^4+Forecast!H10/(1+$B16)^5)+(Forecast!$C$21*G$13*(1-Inputs!$C$37/G$13))/($B16-Inputs!$C$37)/(1+$B16)^5)/Inputs!$C$20 -> 48.217019
B17: 0.105 | C17: =((Forecast!D10/(1+$B17)^1+Forecast!E10/(1+$B17)^2+Forecast!F10/(1+$B17)^3+Forecast!G10/(1+$B17)^4+Forecast!H10/(1+$B17)^5)+(Forecast!$C$21*C$13*(1-Inputs!$C$37/C$13))/($B17-Inputs!$C$37)/(1+$B17)^5)/Inputs!$C$20 -> 32.564836 | D17: =((Forecast!D10/(1+$B17)^1+Forecast!E10/(1+$B17)^2+Forecast!F10/(1+$B17)^3+Forecast!G10/(1+$B17)^4+Forecast!H10/(1+$B17)^5)+(Forecast!$C$21*D$13*(1-Inputs!$C$37/D$13))/($B17-Inputs!$C$37)/(1+$B17)^5)/Inputs!$C$20 -> 35.531363 | E17: =((Forecast!D10/(1+$B17)^1+Forecast!E10/(1+$B17)^2+Forecast!F10/(1+$B17)^3+Forecast!G10/(1+$B17)^4+Forecast!H10/(1+$B17)^5)+(Forecast!$C$21*E$13*(1-Inputs!$C$37/E$13))/($B17-Inputs!$C$37)/(1+$B17)^5)/Inputs!$C$20 -> 38.49789 | F17: =((Forecast!D10/(1+$B17)^1+Forecast!E10/(1+$B17)^2+Forecast!F10/(1+$B17)^3+Forecast!G10/(1+$B17)^4+Forecast!H10/(1+$B17)^5)+(Forecast!$C$21*F$13*(1-Inputs!$C$37/F$13))/($B17-Inputs!$C$37)/(1+$B17)^5)/Inputs!$C$20 -> 41.464417 | G17: =((Forecast!D10/(1+$B17)^1+Forecast!E10/(1+$B17)^2+Forecast!F10/(1+$B17)^3+Forecast!G10/(1+$B17)^4+Forecast!H10/(1+$B17)^5)+(Forecast!$C$21*G$13*(1-Inputs!$C$37/G$13))/($B17-Inputs!$C$37)/(1+$B17)^5)/Inputs!$C$20 -> 44.430944
B18: 0.11 | C18: =((Forecast!D10/(1+$B18)^1+Forecast!E10/(1+$B18)^2+Forecast!F10/(1+$B18)^3+Forecast!G10/(1+$B18)^4+Forecast!H10/(1+$B18)^5)+(Forecast!$C$21*C$13*(1-Inputs!$C$37/C$13))/($B18-Inputs!$C$37)/(1+$B18)^5)/Inputs!$C$20 -> 30.255477 | D18: =((Forecast!D10/(1+$B18)^1+Forecast!E10/(1+$B18)^2+Forecast!F10/(1+$B18)^3+Forecast!G10/(1+$B18)^4+Forecast!H10/(1+$B18)^5)+(Forecast!$C$21*D$13*(1-Inputs!$C$37/D$13))/($B18-Inputs!$C$37)/(1+$B18)^5)/Inputs!$C$20 -> 32.97452 | E18: =((Forecast!D10/(1+$B18)^1+Forecast!E10/(1+$B18)^2+Forecast!F10/(1+$B18)^3+Forecast!G10/(1+$B18)^4+Forecast!H10/(1+$B18)^5)+(Forecast!$C$21*E$13*(1-Inputs!$C$37/E$13))/($B18-Inputs!$C$37)/(1+$B18)^5)/Inputs!$C$20 -> 35.693563 | F18: =((Forecast!D10/(1+$B18)^1+Forecast!E10/(1+$B18)^2+Forecast!F10/(1+$B18)^3+Forecast!G10/(1+$B18)^4+Forecast!H10/(1+$B18)^5)+(Forecast!$C$21*F$13*(1-Inputs!$C$37/F$13))/($B18-Inputs!$C$37)/(1+$B18)^5)/Inputs!$C$20 -> 38.412606 | G18: =((Forecast!D10/(1+$B18)^1+Forecast!E10/(1+$B18)^2+Forecast!F10/(1+$B18)^3+Forecast!G10/(1+$B18)^4+Forecast!H10/(1+$B18)^5)+(Forecast!$C$21*G$13*(1-Inputs!$C$37/G$13))/($B18-Inputs!$C$37)/(1+$B18)^5)/Inputs!$C$20 -> 41.131649
B20: The grids hold the explicit five-year dividend path fixed and rebuild only the discounting and the terminal value, which is where nearly all the sensitivity lives. The base cell reconciles to the DDM sheet exactly.

Sheet Summary
B1: Emirates NBD — Bank Valuation — Dividend Discount and Excess Return | F1: EMIRATES NBD
B2: The bank valuation on one page
B4: THE BANK TODAY
B5: Return on average equity, FY2025 | C5: =Inputs!$C$13 -> 0.17327735
B6: Book value per share (AED) | C6: =Inputs!$C$22 -> 22.909523
B7: Share price (AED) | C7: =Inputs!$C$19 -> 30.98
B8: Price / book | C8: =Inputs!$C$24 -> 1.3522761
B9: Cost of equity used | C9: =Inputs!$C$34 -> 0.1
B11: THE TWO MODELS
B12: Dividend discount value per share (AED) | C12: =DDM!$C$20 -> 41.714383
B13: Excess-return value per share (AED) | C13: ='Excess Return'!$C$24 -> 41.714383
B14: Upside / (downside) to the price | C14: =DDM!$C$21 -> 0.34649395
B15: Implied price / book at the model value | C15: =DDM!$C$22 -> 1.8208316
B16: Share of value that is book value already held | C16: ='Excess Return'!$C$25 -> 0.54919962
B17: Terminal value as % of the DDM value | C17: =DDM!$C$19 -> 0.85736619
B19: WHAT THE PRICE IMPLIES
B20: Justified P/B at the terminal ROE | C20: ='Justified Multiples'!$C$6 -> 1.5714286
B21: Sustainable ROE the price implies | C21: ='Justified Multiples'!$C$11 -> 0.12465933
B22: Cost of equity the price implies at the terminal ROE | C22: ='Justified Multiples'!$C$12 -> 0.11134434
B24: • Two methods, one forecast, one answer: the dividend model and the excess-return model agree to the fils because the forecast obeys clean surplus. If they ever disagree, the forecast is wrong, not the methods.
B25: • The market pays 1.35x book for a bank earning 17% on equity. At a 10% cost of equity that multiple is justified only if returns fade to about 11%; the fade built in here stops at 14% and lands well above the price. Either the market expects a harder landing for UAE bank margins, or it discounts them at a higher rate than a country-risk build-up gives.
B26: • The valuation is a bet on the spread between ROE and the cost of equity, and almost nothing else. A half-point on the cost of equity moves the value by about two dirhams; a point on the terminal ROE by about the same.
B27: • The excess-return split is the useful framing for a bank: just over half the value is book already on the balance sheet, and the market price sits only a third of the way from book to the model value. The argument is entirely about how long a 17% return can last.

Sheet Checks
B1: Emirates NBD — Bank Valuation — Dividend Discount and Excess Return | E1: EMIRATES NBD
B2: Every check must read TRUE
B4: INTEGRITY CHECKS
B5: FY2025 equity, earnings and shares tie to Project 6 | C5: =AND(ABS(Inputs!$C$7-144582)<1,ABS(Inputs!$C$5-23442)<1,ABS(Inputs!$C$20-6311)<1) -> TRUE
B6: Clean surplus holds in every forecast year (closing = opening + profit − dividends) | C6: =AND(ABS(Forecast!D11-(Forecast!D6+Forecast!D8-Forecast!D10))<0.01,ABS(Forecast!E11-(Forecast!E6+Forecast!E8-Forecast!E10))<0.01,ABS(Forecast!F11-(Forecast!F6+Forecast!F8-Forecast!F10))<0.01,ABS(Forecast!G11-(Forecast!G6+Forecast!G8-Forecast!G10))<0.01,ABS(Forecast!H11-(Forecast!H6+Forecast!H8-Forecast!H10))<0.01) -> TRUE
B7: Opening equity each year equals the prior year's closing equity | C7: =AND(ABS(Forecast!D6-Forecast!C11)<0.01,ABS(Forecast!E6-Forecast!D11)<0.01,ABS(Forecast!F6-Forecast!E11)<0.01,ABS(Forecast!G6-Forecast!F11)<0.01,ABS(Forecast!H6-Forecast!G11)<0.01) -> TRUE
B8: Terminal book grows at exactly g | C8: =ABS(Forecast!$C$25-Inputs!$C$37)<0.00001 -> TRUE
B9: Long-run growth is below the cost of equity | C9: =Inputs!$C$37<Inputs!$C$34 -> TRUE
B10: Terminal ROE is above the cost of equity (otherwise excess returns are negative) | C10: =Inputs!$C$38>Inputs!$C$34 -> TRUE
B11: Terminal ROE is not above the FY2025 ROE (the fade is a fade) | C11: =Inputs!$C$38<=Inputs!$C$13 -> TRUE
B12: Payout rises through the forecast | C12: =AND(Forecast!E9>=Forecast!D9,Forecast!F9>=Forecast!E9,Forecast!G9>=Forecast!F9,Forecast!H9>=Forecast!G9) -> TRUE
B13: DDM and excess-return values agree to within AED 0.001 per share | C13: =ABS('Excess Return'!$C$27)<0.001 -> TRUE
B14: DDM terminal exit P/B is within 0.1x of the justified P/B at the terminal ROE | C14: =ABS(DDM!$C$14-'Justified Multiples'!$C$6)<0.1 -> TRUE
B15: Base sensitivity cell reconciles to the DDM value | C15: =ABS(Sensitivity!E8-DDM!$C$20)<0.01 -> TRUE
B16: Market P/B reconciles to price times shares over equity | C16: =ABS(Inputs!$C$24-Inputs!$C$21/Inputs!$C$7)<0.001 -> TRUE
B17: Implied ROE at the market price reproduces the market P/B | C17: =ABS(('Justified Multiples'!$C$11-Inputs!$C$37)/(Inputs!$C$34-Inputs!$C$37)-Inputs!$C$24)<0.0001 -> TRUE
B18: Share price lies within the 52-week range | C18: =AND(Inputs!$C$19>=24-0.5,Inputs!$C$19<=37.4+0.5) -> TRUE
B20: MODEL STATUS | C20: =IF(COUNTIF(C5:C18,FALSE())=0,"MODEL OK","CHECK FAILED") -> MODEL OK
B22: The ninth check is the one that matters: two different valuation methods built on the same forecast must produce the same number. It fails the model the moment someone edits the terminal payout by hand.
