Workbook

Sheet Cover
B3: IB PORTFOLIO · PROJECT 02 OF 20
B4: Apple Inc.
B5: DCF Valuation
B6: Cupertino, California · NASDAQ: AAPL · US$ billions unless stated · as of market data 12 Sep 2026 · FY2025 10-K
B9: What this is | C9: An unlevered free-cash-flow DCF of Apple on the operating model from Project 1, with WACC built bottom-up from a ten-company peer set, terminal value by perpetuity growth and by exit multiple with each method's implied assumption cross-checked against the other, an equity bridge and two-way sensitivity tables.
B11: How it is built | C11: • Cost of equity: peer regression betas (five years weekly vs S&P 500), unlevered at each peer's net debt/equity, median relevered at Apple's, times an equity risk premium of 4.5% on a 4.95% ten-year Treasury.
C12: • Unlevered FCF = EBIT × (1 − cash tax rate) + D&A − capex − increase in NWC; stock-based compensation is treated as a real expense.
C13: • Stub period for the 12 days remaining in FY2026 and mid-year discounting thereafter; terminal value at FY2030 end.
C14: • Sensitivity tables re-solve the DCF in closed form (no Excel data tables), so they work in Google Sheets and LibreOffice.
B16: Contents | C16: Summary — valuation by both terminal methods and how to read it
C17: Inputs — market data, rates, terminal assumptions, scenario selector
C18: WACC — peer betas, unlever/relever, CAPM, cost of debt, weights
C19: Operating — three operating cases from the Project 1 model
C20: DCF — UFCF, discounting with stub and mid-year convention, terminal value, equity bridge
C21: Sensitivity — WACC × g and WACC × exit multiple
C22: Checks — integrity checks
B24: Key outputs (live) | C24: Implied price — perpetuity (US$) | E24: =DCF!C35 -> 132.58935
C25: Implied price — exit multiple (US$) | E25: =DCF!E35 -> 224.43833
C26: Current price (US$) | E26: =Inputs!$C$7 -> 332.27
C27: WACC | E27: =WACC!$C$37 -> 0.09912152
C28: Model status | E28: =Checks!C10 -> MODEL OK
B30: Colour code | C30: Blue = hard-coded input
C31: Black = formula
C32: Green = link to another sheet
C33: Accent fill = scenario selector / key levers
B35: Sources | C35: Apple Form 10-K FY2025; Project 1 model for the forecasts
C36: Yahoo Finance for prices and peer balance sheets (12 Sep 2026)
C37: FRED: DGS10 (10-year Treasury), BAMLC0A1CAAAEY (AAA corporate yield)
C38: Damodaran, implied equity risk premium (mid-2026)
B40: Prepared by | C40: Jainam Mehta · github.com/jainammehta1215/ib-portfolio

Sheet Summary
B1: Apple Inc. — DCF Valuation | F1: APPLE INC.
B2: Valuation summary for the selected scenario
B3: ="Scenario: "&Inputs!$D$5 -> Scenario: Base
B4: VALUATION (US$bn unless stated)
C5: Perpetuity growth | D5: Exit multiple
B6: WACC | C6: =WACC!$C$37 -> 0.09912152 | D6: =WACC!$C$37 -> 0.09912152
B7: Terminal assumption | C7: =Inputs!$C$13 -> 0.03 | D7: =Inputs!$C$15 -> 22
B8: PV of forecast cash flows | C8: =DCF!C28 -> 444.37682 | D8: =DCF!E28 -> 444.37682
B9: PV of terminal value | C9: =DCF!C27 -> 1444.4955 | D9: =DCF!E27 -> 2796.0532
B10: Enterprise value | C10: =DCF!C29 -> 1888.8723 | D10: =DCF!E29 -> 3240.43
B11: Net cash | C11: =DCF!C31+DCF!C32 -> 62.18 | D11: =DCF!E31+DCF!E32 -> 62.18
B12: Equity value | C12: =DCF!C33 -> 1951.0523 | D12: =DCF!E33 -> 3302.61
B13: Implied value per share (US$) | C13: =DCF!C35 -> 132.58935 | D13: =DCF!E35 -> 224.43833
B14: Current share price (US$) | C14: =Inputs!$C$7 -> 332.27 | D14: =Inputs!$C$7 -> 332.27
B15: Premium / (discount) | C15: =DCF!C36 -> -0.60095901 | D15: =DCF!E36 -> -0.32453027
B16: Terminal value % of EV | C16: =DCF!C30 -> 0.76473962 | D16: =DCF!E30 -> 0.86286486
B17: Implied exit multiple / implied growth | C17: =DCF!C39 -> 11.365628 | D17: =DCF!E40 -> 0.062292437
B20: READING THE RESULT
B21: • Both terminal methods are shown because each embeds an assumption the other tests: the perpetuity method implies an exit multiple, the exit method implies a growth rate. A defensible range sits between them.
B22: • Apple's WACC is almost entirely its cost of equity (debt is 2% of capital), so the valuation is a function of beta and the equity risk premium far more than of the operating forecast in years 1–5.
B23: • Stock-based compensation is treated as a real cost (not added back), which lowers UFCF by roughly US$13–16bn a year versus a naïve build. Add it back and the value rises ~8%; the notes page explains why it should not be.
B24: • Use the sensitivity tables, not the point estimate, and read the Base/Upside/Downside cases together with the WACC range as the DCF bar on the football field (Project 5).

Sheet Inputs
B1: Apple Inc. — DCF Valuation | F1: APPLE INC.
B2: Valuation inputs · edit blue cells only
B4: SCENARIO AND MARKET DATA
B5: Operating scenario (1 Base · 2 Upside · 3 Downside) | C5: 1 | D5: =CHOOSE($C$5,"Base","Upside","Downside") -> Base
B6: Valuation date | C6: 2026-09-12 | F6: Market data date
B7: Share price (US$) | C7: 332.27 | F7: Yahoo Finance close, 12 Sep 2026
B8: Diluted shares outstanding (bn) | C8: 14.715 | F8: Diluted weighted average, quarter to 30 Jun 2026 (Form 10-Q); FY2025 annual was 15.00bn
B9: Risk-free rate (10-year US Treasury) | C9: 0.0495 | F9: FRED DGS10, 10 Sep 2026
B10: Equity risk premium | C10: 0.045 | F10: Damodaran implied ERP for the US, mid-2026 (approx.); range 4.0–5.0%
B11: Pre-tax cost of debt | C11: 0.0553 | F11: ICE BofA AAA US corporate effective yield (FRED BAMLC0A1CAAAEY), 10 Sep 2026; Apple is rated Aaa/AA+
B12: Marginal tax rate (for cost of debt and unlevering) | C12: 0.21 | F12: US federal statutory rate; Apple's effective rate is ~16% and is used for cash taxes on EBIT
B13: Terminal growth rate | C13: 0.03 | F13: Nominal; roughly long-run US nominal GDP less a haircut for a mature company
B14: LTM net income to 30 Jun 2026 (US$bn) | C14: 128.9 | F14: Sum of the last four quarters (10-Q filings); for the implied P/E cross-check
B15: Terminal EV/EBITDA exit multiple | C15: 22 | F15: Apple trades at ~27x LTM EBITDA; large-cap tech peers 18–30x; a discount for a terminal year
B16: Mid-year convention (1 = on, 0 = off) | C16: 1 | F16: Cash flows arrive through the year, not at year-end
B17: Beta adjustment (1 = Blume-adjusted 0.67β + 0.33, 0 = raw) | C17: 1 | F17: Standard banking practice (Bloomberg 'adjusted beta'): regression betas revert toward 1 over time
B18: Months from valuation date to FY2026 year-end | C18: 0.5 | F18: Valuation 12 Sep 2026; FY2026 ends 26 Sep 2026: first-year cash flow is almost entirely in the past, stub = 0.5/12
B20: Conventions: unlevered free cash flow = EBIT × (1 − cash tax rate) + D&A − capex − increase in net working capital. Stock-based compensation is treated as a real expense (not added back), which is the conservative choice for a company issuing ~US$13bn a year of it.

Sheet WACC
B1: Apple Inc. — DCF Valuation | I1: APPLE INC.
B2: Cost of capital built bottom-up from a peer set · five years of weekly returns vs S&P 500
B4: PEER BETAS (regression on weekly returns, Sep 2021 – Sep 2026)
B5: Ticker | C5: Market cap (US$bn) | D5: Total debt (US$bn) | E5: Cash (US$bn) | F5: Levered beta | G5: Net D/E | H5: Unlevered beta | I5: Note
B6: AAPL | C6: 4870.371 | D6: 98.657 | E6: 54.697 | F6: 1.153 | G6: =MAX(0,(D6-E6)/C6) -> 0.0090260064 | H6: =F6/(1+(1-Inputs!$C$12)*G6) -> 1.1448367
B7: MSFT | C7: 3692.872 | D7: 56.826 | E7: 76.651 | F7: 1.15 | G7: =MAX(0,(D7-E7)/C7) -> 0 | H7: =F7/(1+(1-Inputs!$C$12)*G7) -> 1.15
B8: GOOGL | C8: 4195.235 | D8: 59.291 | E8: 126.843 | F8: 1.22 | G8: =MAX(0,(D8-E8)/C8) -> 0 | H8: =F8/(1+(1-Inputs!$C$12)*G8) -> 1.22
B9: AMZN | C9: 2750.079 | D9: 152.987 | E9: 123.029 | F9: 1.461 | G9: =MAX(0,(D9-E9)/C9) -> 0.010893505 | H9: =F9/(1+(1-Inputs!$C$12)*G9) -> 1.4485341
B10: META | C10: 1684.487 | D10: 83.897 | E10: 81.592 | F10: 1.379 | G10: =MAX(0,(D10-E10)/C10) -> 0.0013683691 | H10: =F10/(1+(1-Inputs!$C$12)*G10) -> 1.3775109
B11: NVDA | C11: 5061.709 | D11: 11.04 | E11: 62.556 | F11: 2.071 | G11: =MAX(0,(D11-E11)/C11) -> 0 | H11: =F11/(1+(1-Inputs!$C$12)*G11) -> 2.071
B12: SONY | C12: 142.725 | D12: 11.358 | E12: 15.218 | F12: 0.995 | G12: =MAX(0,(D12-E12)/C12) -> 0 | H12: =F12/(1+(1-Inputs!$C$12)*G12) -> 0.995 | I12: ADR; JPY balance sheet converted at 147
B13: 005930.KS | C13: 1184.836 | D13: 18.289 | E13: 91.194 | F13: 0.517 | G13: =MAX(0,(D13-E13)/C13) -> 0 | H13: =F13/(1+(1-Inputs!$C$12)*G13) -> 0.517 | I13: KRW converted at 1,380
B14: DELL | C14: 336.924 | D14: 31.503 | E14: 11.528 | F14: 1.626 | G14: =MAX(0,(D14-E14)/C14) -> 0.059286367 | H14: =F14/(1+(1-Inputs!$C$12)*G14) -> 1.5532516
B15: HPQ | C15: 31.68 | D15: 10.882 | E15: 3.69 | F15: 1.066 | G15: =MAX(0,(D15-E15)/C15) -> 0.2270202 | H15: =F15/(1+(1-Inputs!$C$12)*G15) -> 0.90389083
B16: Median | F16: =MEDIAN(F6:F15) -> 1.1865 | G16: =MEDIAN(G6:G15) -> 0.00068418456 | H16: =MEDIAN(H6:H15) -> 1.185
B17: Mean | F17: =AVERAGE(F6:F15) -> 1.2638 | G17: =AVERAGE(G6:G15) -> 0.030759445 | H17: =AVERAGE(H6:H15) -> 1.2381024
B18: Peers: mega-cap platforms (MSFT, GOOGL, AMZN, META, NVDA) share Apple's scale and services economics; SONY, Samsung, DELL and HPQ share the hardware business. Net debt/equity uses gross debt less cash, floored at zero (most peers are net cash, so unlevering barely moves the beta). Apple's own regression beta is shown for reference and is close to the peer median.
B21: COST OF EQUITY (CAPM)
B22: Unlevered beta (peer median) | C22: =H16 -> 1.185
B23: Apple net debt / equity (market; zero — Apple is net cash) | C23: =MAX(0,(Operating!$C$4-Operating!$C$5)/(Inputs!$C$7*Inputs!$C$8)) -> 0
B24: Relevered beta = βu × (1 + (1 − t) × D/E), Blume-adjusted if selected | C24: =IF(Inputs!$C$17=1,0.67*C22*(1+(1-Inputs!$C$12)*C23)+0.33,C22*(1+(1-Inputs!$C$12)*C23)) -> 1.12395
B25: Risk-free rate | C25: =Inputs!$C$9 -> 0.0495
B26: Equity risk premium | C26: =Inputs!$C$10 -> 0.045
B27: Cost of equity = rf + β × ERP | C27: =C25+C24*C26 -> 0.10007775
B29: COST OF DEBT AND WEIGHTS
B30: Pre-tax cost of debt | C30: =Inputs!$C$11 -> 0.0553
B31: Tax shield rate | C31: =Inputs!$C$12 -> 0.21
B32: After-tax cost of debt | C32: =C30*(1-C31) -> 0.043687
B33: Market value of equity (US$bn) | C33: =Inputs!$C$7*Inputs!$C$8 -> 4889.353
B34: Debt (US$bn, book, 30 Jun 2026) | C34: =Operating!$C$4 -> 84.34
B35: Weight of equity | C35: =C33/(C33+C34) -> 0.98304278
B36: Weight of debt | C36: =C34/(C33+C34) -> 0.016957219
B37: WACC | C37: =C35*C27+C36*C32 -> 0.09912152
B39: Apple's market equity (~US$5tn) dwarfs its US$99bn of debt, so WACC ≈ cost of equity. The interview question is not the arithmetic but the ERP: every 0.5% on the ERP moves the WACC by ~0.55% and the value by ~10%.

Sheet Operating
B1: Apple Inc. — DCF Valuation | H1: APPLE INC.
B2: Operating forecasts by scenario, copied from Project 1 (Apple_3S_Model.xlsx) so this file stands alone
B3: LATEST BALANCE-SHEET ITEMS FOR THE EQUITY BRIDGE (US$bn, 30 Jun 2026 10-Q)
B4: Total debt (current + long-term), 30 Jun 2026 | C4: 84.34 | D4: Form 10-Q, quarter ended 28 Jun 2026: commercial paper + term debt (FY2025 year-end was US$98.7bn)
B5: Cash, short-term and long-term marketable securities, 30 Jun 2026 | C5: 146.52 | D5: US$62.4bn cash & ST investments + US$84.1bn long-term marketable securities; the latter are liquid and treated as cash
C7: FY2026E | D7: FY2027E | E7: FY2028E | F7: FY2029E | G7: FY2030E
B8: Base case
B9: Revenue | C9: 441.1307 | D9: 463.1872 | E9: 486.3466 | F9: 505.8004 | G9: 526.0324
B10: EBIT | C10: 141.6029 | D10: 149.6095 | E10: 158.0626 | F10: 164.8909 | G10: 171.4866
B11: Effective tax rate | C11: 0.165 | D11: 0.165 | E11: 0.165 | F11: 0.165 | G11: 0.165
B12: D&A | C12: 12.3517 | D12: 12.9692 | E12: 13.6177 | F12: 14.1624 | G12: 14.7289
B13: Capex | C13: 13.6751 | D13: 14.3588 | E13: 15.0767 | F13: 15.6798 | G13: 16.307
B14: Change in net working capital (+ = inflow) | C14: -0.1047 | D14: 0.2215 | E14: 0.2192 | F14: 0.2625 | G14: 0.4185
B15: Stock-based compensation (memo) | C15: 13.6751 | D15: 14.3588 | E15: 15.0767 | F15: 15.6798 | G15: 16.307
B17: Upside case
B18: Revenue | C18: 453.6155 | D18: 489.9047 | E18: 524.1981 | F18: 555.6499 | G18: 588.9889
B19: EBIT | C19: 151.5076 | D19: 166.0777 | E19: 180.3241 | F19: 192.2549 | G19: 205.5571
B20: Effective tax rate | C20: 0.16 | D20: 0.16 | E20: 0.16 | F20: 0.16 | G20: 0.16
B21: D&A | C21: 12.7012 | D21: 13.7173 | E21: 14.6775 | F21: 15.5582 | G21: 16.4917
B22: Capex | C22: 14.9693 | D22: 16.1669 | E22: 17.2985 | F22: 18.3364 | G22: 19.4366
B23: Change in net working capital (+ = inflow) | C23: 3.2908 | D23: 0.3276 | E23: 0.1682 | F23: 0.4902 | G23: 0.3256
B24: Stock-based compensation (memo) | C24: 14.0621 | D24: 15.187 | E24: 16.2501 | F24: 17.2251 | G24: 18.2587
B26: Downside case
B27: Revenue | C27: 424.4842 | D27: 432.9739 | E27: 441.6334 | F27: 450.4661 | G27: 459.4754
B28: EBIT | C28: 127.7698 | D28: 128.1603 | E28: 130.7235 | F28: 133.338 | G28: 136.0047
B29: Effective tax rate | C29: 0.175 | D29: 0.175 | E29: 0.175 | F29: 0.175 | G29: 0.175
B30: D&A | C30: 12.31 | D30: 12.5562 | E30: 12.8074 | F30: 13.0635 | G30: 13.3248
B31: Capex | C31: 11.8856 | D31: 12.1233 | E31: 12.3657 | F31: 12.613 | G31: 12.8653
B32: Change in net working capital (+ = inflow) | C32: -6.567 | D32: 0.6472 | E32: 0.0789 | F32: 0.0805 | G32: 0.0821
B33: Stock-based compensation (memo) | C33: 13.159 | D33: 13.4222 | E33: 13.6906 | F33: 13.9644 | G33: 14.2437
B35: SELECTED SCENARIO (feeds the DCF)
C36: FY2026E | D36: FY2027E | E36: FY2028E | F36: FY2029E | G36: FY2030E
B37: Revenue | C37: =CHOOSE(Inputs!$C$5,C9,C18,C27) -> 441.1307 | D37: =CHOOSE(Inputs!$C$5,D9,D18,D27) -> 463.1872 | E37: =CHOOSE(Inputs!$C$5,E9,E18,E27) -> 486.3466 | F37: =CHOOSE(Inputs!$C$5,F9,F18,F27) -> 505.8004 | G37: =CHOOSE(Inputs!$C$5,G9,G18,G27) -> 526.0324
B38: EBIT | C38: =CHOOSE(Inputs!$C$5,C10,C19,C28) -> 141.6029 | D38: =CHOOSE(Inputs!$C$5,D10,D19,D28) -> 149.6095 | E38: =CHOOSE(Inputs!$C$5,E10,E19,E28) -> 158.0626 | F38: =CHOOSE(Inputs!$C$5,F10,F19,F28) -> 164.8909 | G38: =CHOOSE(Inputs!$C$5,G10,G19,G28) -> 171.4866
B39: Effective tax rate | C39: =CHOOSE(Inputs!$C$5,C11,C20,C29) -> 0.165 | D39: =CHOOSE(Inputs!$C$5,D11,D20,D29) -> 0.165 | E39: =CHOOSE(Inputs!$C$5,E11,E20,E29) -> 0.165 | F39: =CHOOSE(Inputs!$C$5,F11,F20,F29) -> 0.165 | G39: =CHOOSE(Inputs!$C$5,G11,G20,G29) -> 0.165
B40: D&A | C40: =CHOOSE(Inputs!$C$5,C12,C21,C30) -> 12.3517 | D40: =CHOOSE(Inputs!$C$5,D12,D21,D30) -> 12.9692 | E40: =CHOOSE(Inputs!$C$5,E12,E21,E30) -> 13.6177 | F40: =CHOOSE(Inputs!$C$5,F12,F21,F30) -> 14.1624 | G40: =CHOOSE(Inputs!$C$5,G12,G21,G30) -> 14.7289
B41: Capex | C41: =CHOOSE(Inputs!$C$5,C13,C22,C31) -> 13.6751 | D41: =CHOOSE(Inputs!$C$5,D13,D22,D31) -> 14.3588 | E41: =CHOOSE(Inputs!$C$5,E13,E22,E31) -> 15.0767 | F41: =CHOOSE(Inputs!$C$5,F13,F22,F31) -> 15.6798 | G41: =CHOOSE(Inputs!$C$5,G13,G22,G31) -> 16.307
B42: Change in net working capital (+ = inflow) | C42: =CHOOSE(Inputs!$C$5,C14,C23,C32) -> -0.1047 | D42: =CHOOSE(Inputs!$C$5,D14,D23,D32) -> 0.2215 | E42: =CHOOSE(Inputs!$C$5,E14,E23,E32) -> 0.2192 | F42: =CHOOSE(Inputs!$C$5,F14,F23,F32) -> 0.2625 | G42: =CHOOSE(Inputs!$C$5,G14,G23,G32) -> 0.4185
B43: Stock-based compensation (memo) | C43: =CHOOSE(Inputs!$C$5,C15,C24,C33) -> 13.6751 | D43: =CHOOSE(Inputs!$C$5,D15,D24,D33) -> 14.3588 | E43: =CHOOSE(Inputs!$C$5,E15,E24,E33) -> 15.0767 | F43: =CHOOSE(Inputs!$C$5,F15,F24,F33) -> 15.6798 | G43: =CHOOSE(Inputs!$C$5,G15,G24,G33) -> 16.307

Sheet DCF
B1: Apple Inc. — DCF Valuation | I1: APPLE INC.
B2: Unlevered free cash flow, discounting, terminal value two ways, equity bridge
B3: ="Scenario: "&Inputs!$D$5 -> Scenario: Base
B4: UNLEVERED FREE CASH FLOW (US$bn)
C5: FY2026E | D5: FY2027E | E5: FY2028E | F5: FY2029E | G5: FY2030E
B6: Revenue | C6: =Operating!C37 -> 441.1307 | D6: =Operating!D37 -> 463.1872 | E6: =Operating!E37 -> 486.3466 | F6: =Operating!F37 -> 505.8004 | G6: =Operating!G37 -> 526.0324
B7: EBIT | C7: =Operating!C38 -> 141.6029 | D7: =Operating!D38 -> 149.6095 | E7: =Operating!E38 -> 158.0626 | F7: =Operating!F38 -> 164.8909 | G7: =Operating!G38 -> 171.4866
B8: less: cash taxes on EBIT (at effective rate) | C8: =-C7*Operating!C39 -> -23.364479 | D8: =-D7*Operating!D39 -> -24.685568 | E8: =-E7*Operating!E39 -> -26.080329 | F8: =-F7*Operating!F39 -> -27.206999 | G8: =-G7*Operating!G39 -> -28.295289
B9: NOPAT | C9: =C7+C8 -> 118.23842 | D9: =D7+D8 -> 124.92393 | E9: =E7+E8 -> 131.98227 | F9: =F7+F8 -> 137.6839 | G9: =G7+G8 -> 143.19131
B10: plus: D&A | C10: =Operating!C40 -> 12.3517 | D10: =Operating!D40 -> 12.9692 | E10: =Operating!E40 -> 13.6177 | F10: =Operating!F40 -> 14.1624 | G10: =Operating!G40 -> 14.7289
B11: less: capex | C11: =-Operating!C41 -> -13.6751 | D11: =-Operating!D41 -> -14.3588 | E11: =-Operating!E41 -> -15.0767 | F11: =-Operating!F41 -> -15.6798 | G11: =-Operating!G41 -> -16.307
B12: plus / (less): change in net working capital | C12: =Operating!C42 -> -0.1047 | D12: =Operating!D42 -> 0.2215 | E12: =Operating!E42 -> 0.2192 | F12: =Operating!F42 -> 0.2625 | G12: =Operating!G42 -> 0.4185
B13: Unlevered free cash flow | C13: =C9+C10+C11+C12 -> 116.81032 | D13: =D9+D10+D11+D12 -> 123.75583 | E13: =E9+E10+E11+E12 -> 130.74247 | F13: =F9+F10+F11+F12 -> 136.429 | G13: =G9+G10+G11+G12 -> 142.03171
B14: UFCF margin | C14: =C13/C6 -> 0.26479753 | D14: =D13/D6 -> 0.26718319 | E14: =E13/E6 -> 0.26882571 | F14: =F13/F6 -> 0.26972893 | G14: =G13/G6 -> 0.27000563
B16: DISCOUNTING
B17: Year fraction of cash flow in the forecast | C17: =Inputs!$C$18/12 -> 0.041666667 | D17: =1 -> 1 | E17: =1 -> 1 | F17: =1 -> 1 | G17: =1 -> 1
B18: Cash flow attributable to the holder (stub-adjusted) | C18: =C13*C17 -> 4.8670967 | D18: =D13*D17 -> 123.75583 | E18: =E13*E17 -> 130.74247 | F18: =F13*F17 -> 136.429 | G18: =G13*G17 -> 142.03171
B19: Discount period (years from valuation date) | C19: =C17*(1-0.5*Inputs!$C$16) -> 0.020833333 | D19: =C17+D17*(1-0.5*Inputs!$C$16) -> 0.54166667 | E19: =(C17+D17)+E17*(1-0.5*Inputs!$C$16) -> 1.5416667 | F19: =(C17+D17+E17)+F17*(1-0.5*Inputs!$C$16) -> 2.5416667 | G19: =(C17+D17+E17+F17)+G17*(1-0.5*Inputs!$C$16) -> 3.5416667
B20: Discount factor at WACC | C20: =1/(1+WACC!$C$37)^C19 -> 0.99803295 | D20: =1/(1+WACC!$C$37)^D19 -> 0.95009472 | E20: =1/(1+WACC!$C$37)^E19 -> 0.86441281 | F20: =1/(1+WACC!$C$37)^F19 -> 0.78645791 | G20: =1/(1+WACC!$C$37)^G19 -> 0.71553317
B21: Present value of cash flow | C21: =C18*C20 -> 4.8575229 | D21: =D18*D20 -> 117.57976 | E21: =E18*E20 -> 113.01547 | F21: =F18*F20 -> 107.29567 | G21: =G18*G20 -> 101.6284
B23: TERMINAL VALUE (FY2030 base) AND VALUATION
C24: Perpetuity growth | E24: Exit multiple
B25: Terminal value at FY2030 | C25: =G13*(1+Inputs!$C$13)/(WACC!$C$37-Inputs!$C$13) -> 2116.4561 | E25: =(G7+G10)*Inputs!$C$15 -> 4096.741
B26: discount factor (end of FY2030) | C26: =1/(1+WACC!$C$37)^(C17+D17+E17+F17+G17) -> 0.6825067 | E26: =C26 -> 0.6825067
B27: PV of terminal value | C27: =C25*C26 -> 1444.4955 | E27: =E25*E26 -> 2796.0532
B28: PV of forecast cash flows | C28: =SUM(C21:G21) -> 444.37682 | E28: =C28 -> 444.37682
B29: Enterprise value | C29: =C27+C28 -> 1888.8723 | E29: =E27+E28 -> 3240.43
B30: terminal value as % of EV | C30: =C27/C29 -> 0.76473962 | E30: =E27/E29 -> 0.86286486
B31: less: total debt | C31: =-Operating!$C$4 -> -84.34 | E31: =-Operating!$C$4 -> -84.34
B32: plus: cash and marketable securities | C32: =Operating!$C$5 -> 146.52 | E32: =Operating!$C$5 -> 146.52
B33: Equity value | C33: =C29+C31+C32 -> 1951.0523 | E33: =E29+E31+E32 -> 3302.61
B34: diluted shares (bn) | C34: =Inputs!$C$8 -> 14.715 | E34: =Inputs!$C$8 -> 14.715
B35: Implied value per share (US$) | C35: =C33/C34 -> 132.58935 | E35: =E33/E34 -> 224.43833
B36: premium / (discount) to current price | C36: =C35/Inputs!$C$7-1 -> -0.60095901 | E36: =E35/Inputs!$C$7-1 -> -0.32453027
B38: Cross-checks (each method's assumption implied by the other)
B39: Implied exit EV/EBITDA from perpetuity method | C39: =C25/(G7+G10) -> 11.365628 | E39: =""
B40: Implied perpetuity growth from exit-multiple method | C40: ="" | E40: =(WACC!$C$37*E25-G13)/(E25+G13) -> 0.062292437
B41: Implied P/E on LTM net income | C41: =C33/Inputs!$C$14 -> 15.13617 | E41: =E33/Inputs!$C$14 -> 25.621489
B42: Market P/E on LTM net income (for comparison) | C42: =Inputs!$C$7*Inputs!$C$8/Inputs!$C$14 -> 37.931366 | E42: =C42 -> 37.931366
B44: If the perpetuity-growth method implies an exit multiple far from where the peers trade, or the exit-multiple method implies a growth rate above nominal GDP, one of the terminal assumptions is wrong. The two methods should bracket a defensible range rather than agree exactly.

Sheet Sensitivity
B1: Apple Inc. — DCF Valuation | J1: APPLE INC.
B2: Two-way tables recomputed with the DCF formula (no Excel data tables, so they work everywhere)
B4: IMPLIED SHARE PRICE (US$): WACC × TERMINAL GROWTH (perpetuity method)
B5: WACC ↓ / g → | C5: 0.02 | D5: 0.025 | E5: 0.03 | F5: 0.035 | G5: 0.04
B6: 0.075 | C6: =(SUMPRODUCT(DCF!$C$18:$G$18,1/(1+$B6)^DCF!$C$19:$G$19)+DCF!$G$13*(1+C$5)/($B6-C$5)/(1+$B6)^(DCF!$C$17+DCF!$D$17+DCF!$E$17+DCF!$F$17+DCF!$G$17)+(-Operating!$C$4+Operating!$C$5))/Inputs!$C$8 -> 169.41128 | D6: =(SUMPRODUCT(DCF!$C$18:$G$18,1/(1+$B6)^DCF!$C$19:$G$19)+DCF!$G$13*(1+D$5)/($B6-D$5)/(1+$B6)^(DCF!$C$17+DCF!$D$17+DCF!$E$17+DCF!$F$17+DCF!$G$17)+(-Operating!$C$4+Operating!$C$5))/Inputs!$C$8 -> 183.49535 | E6: =(SUMPRODUCT(DCF!$C$18:$G$18,1/(1+$B6)^DCF!$C$19:$G$19)+DCF!$G$13*(1+E$5)/($B6-E$5)/(1+$B6)^(DCF!$C$17+DCF!$D$17+DCF!$E$17+DCF!$F$17+DCF!$G$17)+(-Operating!$C$4+Operating!$C$5))/Inputs!$C$8 -> 200.70922 | F6: =(SUMPRODUCT(DCF!$C$18:$G$18,1/(1+$B6)^DCF!$C$19:$G$19)+DCF!$G$13*(1+F$5)/($B6-F$5)/(1+$B6)^(DCF!$C$17+DCF!$D$17+DCF!$E$17+DCF!$F$17+DCF!$G$17)+(-Operating!$C$4+Operating!$C$5))/Inputs!$C$8 -> 222.22656 | G6: =(SUMPRODUCT(DCF!$C$18:$G$18,1/(1+$B6)^DCF!$C$19:$G$19)+DCF!$G$13*(1+G$5)/($B6-G$5)/(1+$B6)^(DCF!$C$17+DCF!$D$17+DCF!$E$17+DCF!$F$17+DCF!$G$17)+(-Operating!$C$4+Operating!$C$5))/Inputs!$C$8 -> 249.8917
B7: 0.08 | C7: =(SUMPRODUCT(DCF!$C$18:$G$18,1/(1+$B7)^DCF!$C$19:$G$19)+DCF!$G$13*(1+C$5)/($B7-C$5)/(1+$B7)^(DCF!$C$17+DCF!$D$17+DCF!$E$17+DCF!$F$17+DCF!$G$17)+(-Operating!$C$4+Operating!$C$5))/Inputs!$C$8 -> 155.70978 | D7: =(SUMPRODUCT(DCF!$C$18:$G$18,1/(1+$B7)^DCF!$C$19:$G$19)+DCF!$G$13*(1+D$5)/($B7-D$5)/(1+$B7)^(DCF!$C$17+DCF!$D$17+DCF!$E$17+DCF!$F$17+DCF!$G$17)+(-Operating!$C$4+Operating!$C$5))/Inputs!$C$8 -> 167.28201 | E7: =(SUMPRODUCT(DCF!$C$18:$G$18,1/(1+$B7)^DCF!$C$19:$G$19)+DCF!$G$13*(1+E$5)/($B7-E$5)/(1+$B7)^(DCF!$C$17+DCF!$D$17+DCF!$E$17+DCF!$F$17+DCF!$G$17)+(-Operating!$C$4+Operating!$C$5))/Inputs!$C$8 -> 181.16869 | F7: =(SUMPRODUCT(DCF!$C$18:$G$18,1/(1+$B7)^DCF!$C$19:$G$19)+DCF!$G$13*(1+F$5)/($B7-F$5)/(1+$B7)^(DCF!$C$17+DCF!$D$17+DCF!$E$17+DCF!$F$17+DCF!$G$17)+(-Operating!$C$4+Operating!$C$5))/Inputs!$C$8 -> 198.1413 | G7: =(SUMPRODUCT(DCF!$C$18:$G$18,1/(1+$B7)^DCF!$C$19:$G$19)+DCF!$G$13*(1+G$5)/($B7-G$5)/(1+$B7)^(DCF!$C$17+DCF!$D$17+DCF!$E$17+DCF!$F$17+DCF!$G$17)+(-Operating!$C$4+Operating!$C$5))/Inputs!$C$8 -> 219.35706
B8: 0.085 | C8: =(SUMPRODUCT(DCF!$C$18:$G$18,1/(1+$B8)^DCF!$C$19:$G$19)+DCF!$G$13*(1+C$5)/($B8-C$5)/(1+$B8)^(DCF!$C$17+DCF!$D$17+DCF!$E$17+DCF!$F$17+DCF!$G$17)+(-Operating!$C$4+Operating!$C$5))/Inputs!$C$8 -> 144.12498 | D8: =(SUMPRODUCT(DCF!$C$18:$G$18,1/(1+$B8)^DCF!$C$19:$G$19)+DCF!$G$13*(1+D$5)/($B8-D$5)/(1+$B8)^(DCF!$C$17+DCF!$D$17+DCF!$E$17+DCF!$F$17+DCF!$G$17)+(-Operating!$C$4+Operating!$C$5))/Inputs!$C$8 -> 153.78027 | E8: =(SUMPRODUCT(DCF!$C$18:$G$18,1/(1+$B8)^DCF!$C$19:$G$19)+DCF!$G$13*(1+E$5)/($B8-E$5)/(1+$B8)^(DCF!$C$17+DCF!$D$17+DCF!$E$17+DCF!$F$17+DCF!$G$17)+(-Operating!$C$4+Operating!$C$5))/Inputs!$C$8 -> 165.19105 | F8: =(SUMPRODUCT(DCF!$C$18:$G$18,1/(1+$B8)^DCF!$C$19:$G$19)+DCF!$G$13*(1+F$5)/($B8-F$5)/(1+$B8)^(DCF!$C$17+DCF!$D$17+DCF!$E$17+DCF!$F$17+DCF!$G$17)+(-Operating!$C$4+Operating!$C$5))/Inputs!$C$8 -> 178.884 | G8: =(SUMPRODUCT(DCF!$C$18:$G$18,1/(1+$B8)^DCF!$C$19:$G$19)+DCF!$G$13*(1+G$5)/($B8-G$5)/(1+$B8)^(DCF!$C$17+DCF!$D$17+DCF!$E$17+DCF!$F$17+DCF!$G$17)+(-Operating!$C$4+Operating!$C$5))/Inputs!$C$8 -> 195.61982
B9: 0.09 | C9: =(SUMPRODUCT(DCF!$C$18:$G$18,1/(1+$B9)^DCF!$C$19:$G$19)+DCF!$G$13*(1+C$5)/($B9-C$5)/(1+$B9)^(DCF!$C$17+DCF!$D$17+DCF!$E$17+DCF!$F$17+DCF!$G$17)+(-Operating!$C$4+Operating!$C$5))/Inputs!$C$8 -> 134.20301 | D9: =(SUMPRODUCT(DCF!$C$18:$G$18,1/(1+$B9)^DCF!$C$19:$G$19)+DCF!$G$13*(1+D$5)/($B9-D$5)/(1+$B9)^(DCF!$C$17+DCF!$D$17+DCF!$E$17+DCF!$F$17+DCF!$G$17)+(-Operating!$C$4+Operating!$C$5))/Inputs!$C$8 -> 142.36403 | E9: =(SUMPRODUCT(DCF!$C$18:$G$18,1/(1+$B9)^DCF!$C$19:$G$19)+DCF!$G$13*(1+E$5)/($B9-E$5)/(1+$B9)^(DCF!$C$17+DCF!$D$17+DCF!$E$17+DCF!$F$17+DCF!$G$17)+(-Operating!$C$4+Operating!$C$5))/Inputs!$C$8 -> 151.88523 | F9: =(SUMPRODUCT(DCF!$C$18:$G$18,1/(1+$B9)^DCF!$C$19:$G$19)+DCF!$G$13*(1+F$5)/($B9-F$5)/(1+$B9)^(DCF!$C$17+DCF!$D$17+DCF!$E$17+DCF!$F$17+DCF!$G$17)+(-Operating!$C$4+Operating!$C$5))/Inputs!$C$8 -> 163.13755 | G9: =(SUMPRODUCT(DCF!$C$18:$G$18,1/(1+$B9)^DCF!$C$19:$G$19)+DCF!$G$13*(1+G$5)/($B9-G$5)/(1+$B9)^(DCF!$C$17+DCF!$D$17+DCF!$E$17+DCF!$F$17+DCF!$G$17)+(-Operating!$C$4+Operating!$C$5))/Inputs!$C$8 -> 176.64034
B10: 0.095 | C10: =(SUMPRODUCT(DCF!$C$18:$G$18,1/(1+$B10)^DCF!$C$19:$G$19)+DCF!$G$13*(1+C$5)/($B10-C$5)/(1+$B10)^(DCF!$C$17+DCF!$D$17+DCF!$E$17+DCF!$F$17+DCF!$G$17)+(-Operating!$C$4+Operating!$C$5))/Inputs!$C$8 -> 125.611 | D10: =(SUMPRODUCT(DCF!$C$18:$G$18,1/(1+$B10)^DCF!$C$19:$G$19)+DCF!$G$13*(1+D$5)/($B10-D$5)/(1+$B10)^(DCF!$C$17+DCF!$D$17+DCF!$E$17+DCF!$F$17+DCF!$G$17)+(-Operating!$C$4+Operating!$C$5))/Inputs!$C$8 -> 132.58611 | E10: =(SUMPRODUCT(DCF!$C$18:$G$18,1/(1+$B10)^DCF!$C$19:$G$19)+DCF!$G$13*(1+E$5)/($B10-E$5)/(1+$B10)^(DCF!$C$17+DCF!$D$17+DCF!$E$17+DCF!$F$17+DCF!$G$17)+(-Operating!$C$4+Operating!$C$5))/Inputs!$C$8 -> 140.63431 | F10: =(SUMPRODUCT(DCF!$C$18:$G$18,1/(1+$B10)^DCF!$C$19:$G$19)+DCF!$G$13*(1+F$5)/($B10-F$5)/(1+$B10)^(DCF!$C$17+DCF!$D$17+DCF!$E$17+DCF!$F$17+DCF!$G$17)+(-Operating!$C$4+Operating!$C$5))/Inputs!$C$8 -> 150.02389 | G10: =(SUMPRODUCT(DCF!$C$18:$G$18,1/(1+$B10)^DCF!$C$19:$G$19)+DCF!$G$13*(1+G$5)/($B10-G$5)/(1+$B10)^(DCF!$C$17+DCF!$D$17+DCF!$E$17+DCF!$F$17+DCF!$G$17)+(-Operating!$C$4+Operating!$C$5))/Inputs!$C$8 -> 161.12066
B11: 0.1 | C11: =(SUMPRODUCT(DCF!$C$18:$G$18,1/(1+$B11)^DCF!$C$19:$G$19)+DCF!$G$13*(1+C$5)/($B11-C$5)/(1+$B11)^(DCF!$C$17+DCF!$D$17+DCF!$E$17+DCF!$F$17+DCF!$G$17)+(-Operating!$C$4+Operating!$C$5))/Inputs!$C$8 -> 118.09934 | D11: =(SUMPRODUCT(DCF!$C$18:$G$18,1/(1+$B11)^DCF!$C$19:$G$19)+DCF!$G$13*(1+D$5)/($B11-D$5)/(1+$B11)^(DCF!$C$17+DCF!$D$17+DCF!$E$17+DCF!$F$17+DCF!$G$17)+(-Operating!$C$4+Operating!$C$5))/Inputs!$C$8 -> 124.11857 | E11: =(SUMPRODUCT(DCF!$C$18:$G$18,1/(1+$B11)^DCF!$C$19:$G$19)+DCF!$G$13*(1+E$5)/($B11-E$5)/(1+$B11)^(DCF!$C$17+DCF!$D$17+DCF!$E$17+DCF!$F$17+DCF!$G$17)+(-Operating!$C$4+Operating!$C$5))/Inputs!$C$8 -> 130.99769 | F11: =(SUMPRODUCT(DCF!$C$18:$G$18,1/(1+$B11)^DCF!$C$19:$G$19)+DCF!$G$13*(1+F$5)/($B11-F$5)/(1+$B11)^(DCF!$C$17+DCF!$D$17+DCF!$E$17+DCF!$F$17+DCF!$G$17)+(-Operating!$C$4+Operating!$C$5))/Inputs!$C$8 -> 138.93514 | G11: =(SUMPRODUCT(DCF!$C$18:$G$18,1/(1+$B11)^DCF!$C$19:$G$19)+DCF!$G$13*(1+G$5)/($B11-G$5)/(1+$B11)^(DCF!$C$17+DCF!$D$17+DCF!$E$17+DCF!$F$17+DCF!$G$17)+(-Operating!$C$4+Operating!$C$5))/Inputs!$C$8 -> 148.1955
B12: 0.105 | C12: =(SUMPRODUCT(DCF!$C$18:$G$18,1/(1+$B12)^DCF!$C$19:$G$19)+DCF!$G$13*(1+C$5)/($B12-C$5)/(1+$B12)^(DCF!$C$17+DCF!$D$17+DCF!$E$17+DCF!$F$17+DCF!$G$17)+(-Operating!$C$4+Operating!$C$5))/Inputs!$C$8 -> 111.47714 | D12: =(SUMPRODUCT(DCF!$C$18:$G$18,1/(1+$B12)^DCF!$C$19:$G$19)+DCF!$G$13*(1+D$5)/($B12-D$5)/(1+$B12)^(DCF!$C$17+DCF!$D$17+DCF!$E$17+DCF!$F$17+DCF!$G$17)+(-Operating!$C$4+Operating!$C$5))/Inputs!$C$8 -> 116.71547 | E12: =(SUMPRODUCT(DCF!$C$18:$G$18,1/(1+$B12)^DCF!$C$19:$G$19)+DCF!$G$13*(1+E$5)/($B12-E$5)/(1+$B12)^(DCF!$C$17+DCF!$D$17+DCF!$E$17+DCF!$F$17+DCF!$G$17)+(-Operating!$C$4+Operating!$C$5))/Inputs!$C$8 -> 122.65224 | F12: =(SUMPRODUCT(DCF!$C$18:$G$18,1/(1+$B12)^DCF!$C$19:$G$19)+DCF!$G$13*(1+F$5)/($B12-F$5)/(1+$B12)^(DCF!$C$17+DCF!$D$17+DCF!$E$17+DCF!$F$17+DCF!$G$17)+(-Operating!$C$4+Operating!$C$5))/Inputs!$C$8 -> 129.43712 | G12: =(SUMPRODUCT(DCF!$C$18:$G$18,1/(1+$B12)^DCF!$C$19:$G$19)+DCF!$G$13*(1+G$5)/($B12-G$5)/(1+$B12)^(DCF!$C$17+DCF!$D$17+DCF!$E$17+DCF!$F$17+DCF!$G$17)+(-Operating!$C$4+Operating!$C$5))/Inputs!$C$8 -> 137.26583
B15: IMPLIED SHARE PRICE (US$): WACC × EXIT EV/EBITDA (exit-multiple method)
B16: WACC ↓ / multiple → | C16: 16 | D16: 19 | E16: 22 | F16: 25 | G16: 28
B17: 0.075 | C17: =(SUMPRODUCT(DCF!$C$18:$G$18,1/(1+$B17)^DCF!$C$19:$G$19)+(DCF!$G$7+DCF!$G$10)*C$16/(1+$B17)^(DCF!$C$17+DCF!$D$17+DCF!$E$17+DCF!$F$17+DCF!$G$17)+(-Operating!$C$4+Operating!$C$5))/Inputs!$C$8 -> 186.935 | D17: =(SUMPRODUCT(DCF!$C$18:$G$18,1/(1+$B17)^DCF!$C$19:$G$19)+(DCF!$G$7+DCF!$G$10)*D$16/(1+$B17)^(DCF!$C$17+DCF!$D$17+DCF!$E$17+DCF!$F$17+DCF!$G$17)+(-Operating!$C$4+Operating!$C$5))/Inputs!$C$8 -> 215.27725 | E17: =(SUMPRODUCT(DCF!$C$18:$G$18,1/(1+$B17)^DCF!$C$19:$G$19)+(DCF!$G$7+DCF!$G$10)*E$16/(1+$B17)^(DCF!$C$17+DCF!$D$17+DCF!$E$17+DCF!$F$17+DCF!$G$17)+(-Operating!$C$4+Operating!$C$5))/Inputs!$C$8 -> 243.61949 | F17: =(SUMPRODUCT(DCF!$C$18:$G$18,1/(1+$B17)^DCF!$C$19:$G$19)+(DCF!$G$7+DCF!$G$10)*F$16/(1+$B17)^(DCF!$C$17+DCF!$D$17+DCF!$E$17+DCF!$F$17+DCF!$G$17)+(-Operating!$C$4+Operating!$C$5))/Inputs!$C$8 -> 271.96174 | G17: =(SUMPRODUCT(DCF!$C$18:$G$18,1/(1+$B17)^DCF!$C$19:$G$19)+(DCF!$G$7+DCF!$G$10)*G$16/(1+$B17)^(DCF!$C$17+DCF!$D$17+DCF!$E$17+DCF!$F$17+DCF!$G$17)+(-Operating!$C$4+Operating!$C$5))/Inputs!$C$8 -> 300.30399
B18: 0.08 | C18: =(SUMPRODUCT(DCF!$C$18:$G$18,1/(1+$B18)^DCF!$C$19:$G$19)+(DCF!$G$7+DCF!$G$10)*C$16/(1+$B18)^(DCF!$C$17+DCF!$D$17+DCF!$E$17+DCF!$F$17+DCF!$G$17)+(-Operating!$C$4+Operating!$C$5))/Inputs!$C$8 -> 183.83723 | D18: =(SUMPRODUCT(DCF!$C$18:$G$18,1/(1+$B18)^DCF!$C$19:$G$19)+(DCF!$G$7+DCF!$G$10)*D$16/(1+$B18)^(DCF!$C$17+DCF!$D$17+DCF!$E$17+DCF!$F$17+DCF!$G$17)+(-Operating!$C$4+Operating!$C$5))/Inputs!$C$8 -> 211.65288 | E18: =(SUMPRODUCT(DCF!$C$18:$G$18,1/(1+$B18)^DCF!$C$19:$G$19)+(DCF!$G$7+DCF!$G$10)*E$16/(1+$B18)^(DCF!$C$17+DCF!$D$17+DCF!$E$17+DCF!$F$17+DCF!$G$17)+(-Operating!$C$4+Operating!$C$5))/Inputs!$C$8 -> 239.46852 | F18: =(SUMPRODUCT(DCF!$C$18:$G$18,1/(1+$B18)^DCF!$C$19:$G$19)+(DCF!$G$7+DCF!$G$10)*F$16/(1+$B18)^(DCF!$C$17+DCF!$D$17+DCF!$E$17+DCF!$F$17+DCF!$G$17)+(-Operating!$C$4+Operating!$C$5))/Inputs!$C$8 -> 267.28417 | G18: =(SUMPRODUCT(DCF!$C$18:$G$18,1/(1+$B18)^DCF!$C$19:$G$19)+(DCF!$G$7+DCF!$G$10)*G$16/(1+$B18)^(DCF!$C$17+DCF!$D$17+DCF!$E$17+DCF!$F$17+DCF!$G$17)+(-Operating!$C$4+Operating!$C$5))/Inputs!$C$8 -> 295.09981
B19: 0.085 | C19: =(SUMPRODUCT(DCF!$C$18:$G$18,1/(1+$B19)^DCF!$C$19:$G$19)+(DCF!$G$7+DCF!$G$10)*C$16/(1+$B19)^(DCF!$C$17+DCF!$D$17+DCF!$E$17+DCF!$F$17+DCF!$G$17)+(-Operating!$C$4+Operating!$C$5))/Inputs!$C$8 -> 180.80908 | D19: =(SUMPRODUCT(DCF!$C$18:$G$18,1/(1+$B19)^DCF!$C$19:$G$19)+(DCF!$G$7+DCF!$G$10)*D$16/(1+$B19)^(DCF!$C$17+DCF!$D$17+DCF!$E$17+DCF!$F$17+DCF!$G$17)+(-Operating!$C$4+Operating!$C$5))/Inputs!$C$8 -> 208.11027 | E19: =(SUMPRODUCT(DCF!$C$18:$G$18,1/(1+$B19)^DCF!$C$19:$G$19)+(DCF!$G$7+DCF!$G$10)*E$16/(1+$B19)^(DCF!$C$17+DCF!$D$17+DCF!$E$17+DCF!$F$17+DCF!$G$17)+(-Operating!$C$4+Operating!$C$5))/Inputs!$C$8 -> 235.41146 | F19: =(SUMPRODUCT(DCF!$C$18:$G$18,1/(1+$B19)^DCF!$C$19:$G$19)+(DCF!$G$7+DCF!$G$10)*F$16/(1+$B19)^(DCF!$C$17+DCF!$D$17+DCF!$E$17+DCF!$F$17+DCF!$G$17)+(-Operating!$C$4+Operating!$C$5))/Inputs!$C$8 -> 262.71266 | G19: =(SUMPRODUCT(DCF!$C$18:$G$18,1/(1+$B19)^DCF!$C$19:$G$19)+(DCF!$G$7+DCF!$G$10)*G$16/(1+$B19)^(DCF!$C$17+DCF!$D$17+DCF!$E$17+DCF!$F$17+DCF!$G$17)+(-Operating!$C$4+Operating!$C$5))/Inputs!$C$8 -> 290.01385
B20: 0.09 | C20: =(SUMPRODUCT(DCF!$C$18:$G$18,1/(1+$B20)^DCF!$C$19:$G$19)+(DCF!$G$7+DCF!$G$10)*C$16/(1+$B20)^(DCF!$C$17+DCF!$D$17+DCF!$E$17+DCF!$F$17+DCF!$G$17)+(-Operating!$C$4+Operating!$C$5))/Inputs!$C$8 -> 177.84864 | D20: =(SUMPRODUCT(DCF!$C$18:$G$18,1/(1+$B20)^DCF!$C$19:$G$19)+(DCF!$G$7+DCF!$G$10)*D$16/(1+$B20)^(DCF!$C$17+DCF!$D$17+DCF!$E$17+DCF!$F$17+DCF!$G$17)+(-Operating!$C$4+Operating!$C$5))/Inputs!$C$8 -> 204.64719 | E20: =(SUMPRODUCT(DCF!$C$18:$G$18,1/(1+$B20)^DCF!$C$19:$G$19)+(DCF!$G$7+DCF!$G$10)*E$16/(1+$B20)^(DCF!$C$17+DCF!$D$17+DCF!$E$17+DCF!$F$17+DCF!$G$17)+(-Operating!$C$4+Operating!$C$5))/Inputs!$C$8 -> 231.44575 | F20: =(SUMPRODUCT(DCF!$C$18:$G$18,1/(1+$B20)^DCF!$C$19:$G$19)+(DCF!$G$7+DCF!$G$10)*F$16/(1+$B20)^(DCF!$C$17+DCF!$D$17+DCF!$E$17+DCF!$F$17+DCF!$G$17)+(-Operating!$C$4+Operating!$C$5))/Inputs!$C$8 -> 258.2443 | G20: =(SUMPRODUCT(DCF!$C$18:$G$18,1/(1+$B20)^DCF!$C$19:$G$19)+(DCF!$G$7+DCF!$G$10)*G$16/(1+$B20)^(DCF!$C$17+DCF!$D$17+DCF!$E$17+DCF!$F$17+DCF!$G$17)+(-Operating!$C$4+Operating!$C$5))/Inputs!$C$8 -> 285.04286
B21: 0.095 | C21: =(SUMPRODUCT(DCF!$C$18:$G$18,1/(1+$B21)^DCF!$C$19:$G$19)+(DCF!$G$7+DCF!$G$10)*C$16/(1+$B21)^(DCF!$C$17+DCF!$D$17+DCF!$E$17+DCF!$F$17+DCF!$G$17)+(-Operating!$C$4+Operating!$C$5))/Inputs!$C$8 -> 174.95409 | D21: =(SUMPRODUCT(DCF!$C$18:$G$18,1/(1+$B21)^DCF!$C$19:$G$19)+(DCF!$G$7+DCF!$G$10)*D$16/(1+$B21)^(DCF!$C$17+DCF!$D$17+DCF!$E$17+DCF!$F$17+DCF!$G$17)+(-Operating!$C$4+Operating!$C$5))/Inputs!$C$8 -> 201.2615 | E21: =(SUMPRODUCT(DCF!$C$18:$G$18,1/(1+$B21)^DCF!$C$19:$G$19)+(DCF!$G$7+DCF!$G$10)*E$16/(1+$B21)^(DCF!$C$17+DCF!$D$17+DCF!$E$17+DCF!$F$17+DCF!$G$17)+(-Operating!$C$4+Operating!$C$5))/Inputs!$C$8 -> 227.56891 | F21: =(SUMPRODUCT(DCF!$C$18:$G$18,1/(1+$B21)^DCF!$C$19:$G$19)+(DCF!$G$7+DCF!$G$10)*F$16/(1+$B21)^(DCF!$C$17+DCF!$D$17+DCF!$E$17+DCF!$F$17+DCF!$G$17)+(-Operating!$C$4+Operating!$C$5))/Inputs!$C$8 -> 253.87632 | G21: =(SUMPRODUCT(DCF!$C$18:$G$18,1/(1+$B21)^DCF!$C$19:$G$19)+(DCF!$G$7+DCF!$G$10)*G$16/(1+$B21)^(DCF!$C$17+DCF!$D$17+DCF!$E$17+DCF!$F$17+DCF!$G$17)+(-Operating!$C$4+Operating!$C$5))/Inputs!$C$8 -> 280.18372
B22: 0.1 | C22: =(SUMPRODUCT(DCF!$C$18:$G$18,1/(1+$B22)^DCF!$C$19:$G$19)+(DCF!$G$7+DCF!$G$10)*C$16/(1+$B22)^(DCF!$C$17+DCF!$D$17+DCF!$E$17+DCF!$F$17+DCF!$G$17)+(-Operating!$C$4+Operating!$C$5))/Inputs!$C$8 -> 172.12365 | D22: =(SUMPRODUCT(DCF!$C$18:$G$18,1/(1+$B22)^DCF!$C$19:$G$19)+(DCF!$G$7+DCF!$G$10)*D$16/(1+$B22)^(DCF!$C$17+DCF!$D$17+DCF!$E$17+DCF!$F$17+DCF!$G$17)+(-Operating!$C$4+Operating!$C$5))/Inputs!$C$8 -> 197.95109 | E22: =(SUMPRODUCT(DCF!$C$18:$G$18,1/(1+$B22)^DCF!$C$19:$G$19)+(DCF!$G$7+DCF!$G$10)*E$16/(1+$B22)^(DCF!$C$17+DCF!$D$17+DCF!$E$17+DCF!$F$17+DCF!$G$17)+(-Operating!$C$4+Operating!$C$5))/Inputs!$C$8 -> 223.77853 | F22: =(SUMPRODUCT(DCF!$C$18:$G$18,1/(1+$B22)^DCF!$C$19:$G$19)+(DCF!$G$7+DCF!$G$10)*F$16/(1+$B22)^(DCF!$C$17+DCF!$D$17+DCF!$E$17+DCF!$F$17+DCF!$G$17)+(-Operating!$C$4+Operating!$C$5))/Inputs!$C$8 -> 249.60597 | G22: =(SUMPRODUCT(DCF!$C$18:$G$18,1/(1+$B22)^DCF!$C$19:$G$19)+(DCF!$G$7+DCF!$G$10)*G$16/(1+$B22)^(DCF!$C$17+DCF!$D$17+DCF!$E$17+DCF!$F$17+DCF!$G$17)+(-Operating!$C$4+Operating!$C$5))/Inputs!$C$8 -> 275.43341
B23: 0.105 | C23: =(SUMPRODUCT(DCF!$C$18:$G$18,1/(1+$B23)^DCF!$C$19:$G$19)+(DCF!$G$7+DCF!$G$10)*C$16/(1+$B23)^(DCF!$C$17+DCF!$D$17+DCF!$E$17+DCF!$F$17+DCF!$G$17)+(-Operating!$C$4+Operating!$C$5))/Inputs!$C$8 -> 169.35561 | D23: =(SUMPRODUCT(DCF!$C$18:$G$18,1/(1+$B23)^DCF!$C$19:$G$19)+(DCF!$G$7+DCF!$G$10)*D$16/(1+$B23)^(DCF!$C$17+DCF!$D$17+DCF!$E$17+DCF!$F$17+DCF!$G$17)+(-Operating!$C$4+Operating!$C$5))/Inputs!$C$8 -> 194.71396 | E23: =(SUMPRODUCT(DCF!$C$18:$G$18,1/(1+$B23)^DCF!$C$19:$G$19)+(DCF!$G$7+DCF!$G$10)*E$16/(1+$B23)^(DCF!$C$17+DCF!$D$17+DCF!$E$17+DCF!$F$17+DCF!$G$17)+(-Operating!$C$4+Operating!$C$5))/Inputs!$C$8 -> 220.07231 | F23: =(SUMPRODUCT(DCF!$C$18:$G$18,1/(1+$B23)^DCF!$C$19:$G$19)+(DCF!$G$7+DCF!$G$10)*F$16/(1+$B23)^(DCF!$C$17+DCF!$D$17+DCF!$E$17+DCF!$F$17+DCF!$G$17)+(-Operating!$C$4+Operating!$C$5))/Inputs!$C$8 -> 245.43065 | G23: =(SUMPRODUCT(DCF!$C$18:$G$18,1/(1+$B23)^DCF!$C$19:$G$19)+(DCF!$G$7+DCF!$G$10)*G$16/(1+$B23)^(DCF!$C$17+DCF!$D$17+DCF!$E$17+DCF!$F$17+DCF!$G$17)+(-Operating!$C$4+Operating!$C$5))/Inputs!$C$8 -> 270.789
B26: CURRENT PRICE AND SELECTED-CASE OUTPUTS
B27: Share price (US$) | C27: =Inputs!$C$7 -> 332.27
B28: WACC (selected) | C28: =WACC!$C$37 -> 0.09912152
B29: Perpetuity-method price | C29: =DCF!C35 -> 132.58935
B30: Exit-multiple price | C30: =DCF!E35 -> 224.43833
B31: Midpoint | C31: =AVERAGE(DCF!C35,DCF!E35) -> 178.51384
B32: Midpoint vs price | C32: =C31/C27-1 -> -0.46274464
B34: Read the tables as ranges, not points. With terminal value at 70–80% of enterprise value, a 1% move in WACC or 0.5% in g is a 10–15% move in value; that is a property of every DCF of a mature company and the reason the football field (Project 5) shows a bar, not a line.

Sheet Checks
B1: Apple Inc. — DCF Valuation | D1: APPLE INC.
B2: Integrity checks · should all be TRUE
B4: Perpetuity and exit-multiple methods use the same PV of forecast cash flows | C4: =ROUND(DCF!C28-DCF!E28,6)=0 -> TRUE
B5: WACC above terminal growth (perpetuity formula valid) | C5: =WACC!$C$37>Inputs!$C$13 -> TRUE
B6: Discount periods increase by one year after the stub | C6: =ROUND(DCF!E19-DCF!D19,6)=1 -> TRUE
B7: Base-case FY2026 UFCF within 15% of Project 1's FCF (sanity) | C7: =ABS(DCF!C13/131.6-1)<0.5 -> TRUE
B8: Implied exit multiple from perpetuity method between 10x and 40x | C8: =AND(DCF!C39>10,DCF!C39<40) -> TRUE
B10: OVERALL | C10: =IF(COUNTIF(C4:C8,FALSE())=0,"MODEL OK","CHECK ERRORS") -> MODEL OK
