Workbook

Sheet Cover
B3: IB PORTFOLIO · PROJECT 03 OF 20
B4: Tata Consultancy Services
B5: Trading Comparables
B6: NSE: TCS · US$ millions unless stated · share prices in local currency · as of prices 12 Sep 2026 · LTM to Jun 2026
B9: What this is | C9: A comparable-companies analysis for Tata Consultancy Services against eight Indian and global IT-services peers: peer selection with stated criteria, currency normalisation (Infosys reports in US$ while trading in INR), enterprise-value construction, LTM and calendarised forward multiples, peer statistics and the implied valuation range for TCS.
B11: How it is built | C11: • LTM figures are the sum of the last four reported quarters, so fiscal-year differences do not affect trailing multiples; forward figures are calendarised to TCS's FY2027 by month-overlap weights.
C12: • EV = market cap + total debt + minority interest − cash and short-term investments; every component converted to US$ at the rate for its own currency (statements and share price can differ).
C13: • Statistics exclude the target; the implied range applies the peer interquartile range of each multiple to TCS's own metric and bridges back to an INR price per share.
C14: • Peer-selection criteria and exclusions are written down on the Inputs sheet, because that is where the judgement in a comps page lives.
B16: Contents | C16: Summary — TCS metrics and the implied per-share range from peer multiples
C17: Inputs — FX, target, calendarisation window, peer-selection rationale
C18: Data — raw pulls in reporting currency
C19: Comps — US$ normalisation, EV build, LTM and calendarised multiples, peer statistics
C20: Calendarisation — worked example of aligning March and December fiscal years
C21: Checks — integrity checks
B23: Key outputs (live) | C23: TCS EV / LTM EBITDA | E23: =Comps!N5 -> 10.367694
C24: Peer median EV / LTM EBITDA | E24: =Comps!N18 -> 8.7477048
C25: TCS P/E (CY2027, calendarised) | E25: =Comps!T5 -> 14.191173
C26: Implied price range, median across methods (INR) | E26: =Summary!H24 -> 1848.2054
C27: Current price (INR) | E27: =Summary!$C$13 -> 2200.8
C28: Model status | E28: =Checks!C10 -> MODEL OK
B30: Colour code | C30: Blue = hard-coded input
C31: Black = formula
C32: Green = link to another sheet
C33: Accent fill = scenario selector / key levers
B35: Sources | C35: Yahoo Finance: prices, shares outstanding, quarterly financial statements, consensus revenue and EPS estimates (12 Sep 2026)
C36: Company filings for fiscal-year ends (TCS, Infosys, HCLTech, Wipro, Tech Mahindra, Persistent: 31 March; Accenture: 31 August; Cognizant, EPAM: 31 December)
B38: Prepared by | C38: Jainam Mehta · github.com/jainammehta1215/ib-portfolio

Sheet Summary
B1: Tata Consultancy Services — Trading Comparables | I1: TATA CONSULTANCY SERVICES
B2: Implied TCS valuation from the peer interquartile range · per-share values in INR
B4: TCS METRICS (US$m unless stated)
B5: LTM revenue | C5: =Comps!G5 -> 28626.931
B6: LTM EBITDA | C6: =Comps!H5 -> 7747.6734
B7: LTM EBIT | C7: =Comps!I5 -> 7183.9208
B8: LTM net income | C8: =Comps!J5 -> 5284.1603
B9: Calendarised FY2027 revenue | C9: =Comps!Q5 -> 30454.84
B10: Calendarised FY2027 EPS (INR) | C10: =Comps!R5 -> 155.08232
B11: Net debt (negative = net cash) | C11: =Comps!E5 -> -3019.9388
B12: Shares (m) | C12: =Data!G5 -> 3618.0875
B13: Share price (INR) | C13: =Data!F5 -> 2200.8
B14: USD per INR | C14: =Inputs!$C$5 -> 0.010467
B16: IMPLIED VALUE PER SHARE (INR) FROM PEER MULTIPLES
B17: Multiple | C17: TCS metric | D17: 25th pct | E17: Median | F17: 75th pct | G17: Implied price @25th | H17: Implied price @median | I17: Implied price @75th
B18: EV / LTM revenue | C18: =$C$5 -> 28626.931 | D18: =Comps!M20 -> 1.5022393 | E18: =Comps!M18 -> 1.8179032 | F18: =Comps!M17 -> 2.2418905 | G18: =($C$5*Comps!M20-$C$11)/$C$12/$C$14 -> 1215.3104 | H18: =($C$5*Comps!M18-$C$11)/$C$12/$C$14 -> 1453.9258 | I18: =($C$5*Comps!M17-$C$11)/$C$12/$C$14 -> 1774.4245
B19: EV / LTM EBITDA | C19: =$C$6 -> 7747.6734 | D19: =Comps!N20 -> 7.6861203 | E19: =Comps!N18 -> 8.7477048 | F19: =Comps!N17 -> 11.725034 | G19: =($C$6*Comps!N20-$C$11)/$C$12/$C$14 -> 1652.195 | H19: =($C$6*Comps!N18-$C$11)/$C$12/$C$14 -> 1869.3774 | I19: =($C$6*Comps!N17-$C$11)/$C$12/$C$14 -> 2478.489
B20: EV / LTM EBIT | C20: =$C$7 -> 7183.9208 | D20: =Comps!O20 -> 8.9044544 | E20: =Comps!O18 -> 10.407708 | F20: =Comps!O17 -> 14.171275 | G20: =($C$7*Comps!O20-$C$11)/$C$12/$C$14 -> 1768.8912 | H20: =($C$7*Comps!O18-$C$11)/$C$12/$C$14 -> 2054.0538 | I20: =($C$7*Comps!O17-$C$11)/$C$12/$C$14 -> 2767.9908
B21: P / E (LTM) | C21: =$C$8 -> 5284.1603 | D21: =Comps!P20 -> 13.093983 | E21: =Comps!P18 -> 15.26538 | F21: =Comps!P17 -> 21.087626 | G21: =$C$8*Comps!P20/$C$12/$C$14 -> 1827.0334 | H21: =$C$8*Comps!P18/$C$12/$C$14 -> 2130.0133 | I21: =$C$8*Comps!P17/$C$12/$C$14 -> 2942.4045
B22: EV / CY2027 revenue (calendarised) | C22: =$C$9 -> 30454.84 | D22: =Comps!S20 -> 1.4453301 | E22: =Comps!S18 -> 1.7896618 | F22: =Comps!S17 -> 2.0711387 | G22: =($C$9*Comps!S20-$C$11)/$C$12/$C$14 -> 1242.0541 | H22: =($C$9*Comps!S18-$C$11)/$C$12/$C$14 -> 1518.9599 | I22: =($C$9*Comps!S17-$C$11)/$C$12/$C$14 -> 1745.3189
B23: P / E (CY2027, calendarised) | C23: =$C$10 -> 155.08232 | D23: =Comps!T20 -> 12.08464 | E23: =Comps!T18 -> 13.362092 | F23: =Comps!T17 -> 17.3388 | G23: =$C$10*Comps!T20 -> 1874.114 | H23: =$C$10*Comps!T18 -> 2072.2242 | I23: =$C$10*Comps!T17 -> 2688.9413
B24: Range across methods (INR) | G24: =MIN(G18:I23) -> 1215.3104 | H24: =MEDIAN(G18:I23) -> 1848.2054 | I24: =MAX(G18:I23) -> 2942.4045
B25: Current share price (INR) | H25: =$C$13 -> 2200.8
B26: Median implied vs current | H26: =H24/H25-1 -> -0.16021202
B28: READING THE RESULT
B29: • TCS trades at a premium to the peer median on every multiple, which is its long-standing position: highest margins in the group, lowest client-concentration risk, and a Tata parent. The question a comps page answers is whether today's premium is larger or smaller than usual, not whether it exists.
B30: • The Indian large caps cluster tightly; the global names (Accenture, Cognizant, EPAM) trade lower because of slower growth and, in 2026, the AI-disruption discount on outsourcing. Mixing the two tiers widens the range; a banker would show both tiers and let the client see the gap.
B31: • Calendarised forward multiples are the ones institutional investors quote. The LTM columns are shown because they are the only ones that need no estimates and therefore no judgement.
B32: • The implied range is a market-based anchor for the football field (Project 5). It says what the market pays for businesses like this today; it says nothing about what TCS is intrinsically worth (Project 2's question).

Sheet Inputs
B1: Tata Consultancy Services — Trading Comparables | F1: TATA CONSULTANCY SERVICES
B2: FX rates, target and the peer-selection rationale
B4: FX (units of local currency per US$) AND TARGET
B5: USD per INR (1 / USDINR) | C5: 0.010467 | F5: USDINR = 95.54, Yahoo Finance 12 Sep 2026
B6: USD per USD | C6: 1
B7: Target ticker | C7: TCS.NS | F7: The company being valued; excluded from peer statistics
B8: Calendarisation window start | C8: 2026-04-01 | F8: TCS fiscal year FY2027: 1 Apr 2026 – 31 Mar 2027
B9: Calendarisation window end | C9: 2027-03-31
B10: Minimum peer market cap (US$m) for statistics | C10: 5000 | F10: Excludes tiny names from the range; set to 0 to include all
B12: PEER SELECTION
B13: Criteria | C13: IT services and consulting with offshore delivery; revenue > US$1bn; listed with liquid trading; LTM financials available. Two tiers: Indian large caps (the direct peers) and global consulting/services names (the customers' alternative suppliers).
B14: Included | C14: Infosys, HCLTech, Wipro (India large-cap); Tech Mahindra, Persistent (India mid-cap, higher growth, smaller); Accenture, Cognizant, EPAM (global).
B15: Excluded | C15: LTIMindtree and Capgemini: no usable data on the free feed (LTIMindtree would otherwise be included). Mphasis and Coforge: under the size threshold. IBM: conglomerate mix. Tata Elxsi: engineering R&D, different economics.
B16: Data quirks handled | C16: Infosys reports IFRS statements in US$ while its shares trade in INR; the statements currency is detected and every figure is normalised to US$ before any multiple is computed. Consensus estimates are in the share-price currency for all names.

Sheet Data
B1: Tata Consultancy Services — Trading Comparables | V1: TATA CONSULTANCY SERVICES
B2: Raw pulls in reporting currency (blue) · statements are LTM to the latest quarter · estimates are consensus averages
B4: Name | C4: Group | D4: Price ccy | E4: Statements ccy | F4: Share price (local) | G4: Shares (m) | H4: Market cap (local m) | I4: Total debt (stmt ccy m) | J4: Cash & ST inv (stmt ccy m) | K4: Minority interest (stmt ccy m) | L4: LTM revenue (stmt ccy m) | M4: LTM EBITDA (stmt ccy m) | N4: LTM EBIT (stmt ccy m) | O4: LTM net income (stmt ccy m) | P4: LTM period end | Q4: FY0 end (consensus) | R4: Revenue FY0 (price ccy m) | S4: Revenue FY1 (price ccy m) | T4: EPS FY0 (price ccy) | U4: EPS FY1 (price ccy)
A5: TCS.NS | B5: Tata Consultancy Services | C5: India large-cap | D5: INR | E5: INR | F5: 2200.8 | G5: 3618.0875 | H5: 7962687 | I5: 112830 | J5: 413730 | K5: 12380 | L5: 2734970 | M5: 740200 | N5: 686340 | O5: 504840 | P5: 2026-06-30 | Q5: 2027-03-31 | R5: 2909605.5 | S5: 3038222.2 | T5: 155.08232 | U5: 162.4991
A6: INFY.NS | B6: Infosys | C6: India large-cap | D6: INR | E6: USD | F6: 1037.7 | G6: 4050.2994 | H6: 4202995.7 | I6: 923 | J6: 3174 | K6: 55 | L6: 20297 | M6: 5129 | N6: 4579 | O6: 3324 | P6: 2026-06-30 | Q6: 2027-03-31 | R6: 1948595 | S6: 2022423.5 | T6: 76.47616 | U6: 79.9959
A7: HCLTECH.NS | B7: HCL Technologies | C7: India large-cap | D7: INR | E7: INR | F7: 1206.1 | G7: 2705.7667 | H7: 3263425.2 | I7: 52150 | J7: 306150 | K7: 320 | L7: 1327810 | M7: 275970 | N7: 232460 | O7: 170310 | P7: 2026-06-30 | Q7: 2027-03-31 | R7: 1422895.9 | S7: 1508629.6 | T7: 73.22011 | U7: 80.10137
A8: WIPRO.NS | B8: Wipro | C8: India large-cap | D8: INR | E8: INR | F8: 167.4 | G8: 9893.0299 | H8: 1656093.2 | I8: 212822 | J8: 395499 | K8: 2059 | L8: 949680 | M8: 212572 | N8: 182276 | O8: 132190 | P8: 2026-06-30 | Q8: 2027-03-31 | R8: 987540.03 | S8: 1017460.9 | T8: 13.31437 | U8: 13.8994
A9: TECHM.NS | B9: Tech Mahindra | C9: India mid-cap | D9: INR | E9: INR | F9: 1541 | G9: 885.89813 | H9: 1365169 | I9: 21862 | J9: 84255 | K9: 4616 | L9: 585324 | M9: 92187 | N9: 73272 | O9: 50815 | P9: 2026-06-30 | Q9: 2027-03-31 | R9: 635754.01 | S9: 671384.57 | T9: 77.28786 | U9: 87.10679
A10: PERSISTENT.NS | B10: Persistent Systems | C10: India mid-cap | D10: INR | E10: INR | F10: 5516 | G10: 156.23104 | H10: 861770.44 | I10: 4774.48 | J10: 20254.4 | K10: 0 | L10: 154709.56 | M10: 29195.17 | N10: 25013.27 | O10: 18766.93 | P10: 2026-06-30 | Q10: 2027-03-31 | R10: 183998.44 | S10: 212788.25 | T10: 144.30505 | U10: 176.86774
A11: ACN | B11: Accenture | C11: Global | D11: USD | E11: USD | F11: 188.60001 | G11: 611.94211 | H11: 115412.29 | I11: 8388.77 | J11: 10171.567 | K11: 1617.147 | L11: 73100.595 | M11: 12330.716 | N11: 10915.206 | O11: 7789.752 | P11: 2026-05-31 | Q11: 2026-08-31 | R11: 73566.228 | S11: 76588.902 | T11: 13.86349 | U11: 14.67784
A12: CTSH | B12: Cognizant | C12: Global | D12: USD | E12: USD | F12: 62.450001 | G12: 450.44421 | H12: 28130.241 | I12: 2094 | J12: 1051 | K12: 0 | L12: 21642 | M12: 4102 | N12: 3543 | O12: 2220 | P12: 2026-06-30 | Q12: 2026-12-31 | R12: 22196.694 | S12: 23254.152 | T12: 5.73656 | U12: 6.32016
A13: EPAM | B13: EPAM Systems | C13: Global | D13: USD | E13: USD | F13: 122.36 | G13: 51.586981 | H13: 6312.183 | I13: 152.243 | J13: 789.397 | K13: 0.582 | L13: 5616.749 | M13: 720.483 | N13: 553.337 | O13: 401.67 | P13: 2026-06-30 | Q13: 2026-12-31 | R13: 5656.9457 | S13: 5857.752 | T13: 13.15097 | U13: 14.06159
B15: Source: Yahoo Finance (prices, shares, quarterly statements, consensus revenue and EPS), 12 Sep 2026. LTM = sum of the last four reported quarters. Minority interest is zero where not reported. Persistent is below the size of the others and is flagged as mid-cap; the statistics exclude names under the market-cap floor on the Inputs sheet.

Sheet Comps
B1: Tata Consultancy Services — Trading Comparables | T1: TATA CONSULTANCY SERVICES
B2: Everything in US$ millions · EV = market cap + debt + minorities − cash · NTM figures calendarised to TCS's March year
B4: Company | C4: Group | D4: Market cap | E4: Net debt | F4: EV | G4: LTM revenue | H4: LTM EBITDA | I4: LTM EBIT | J4: LTM NI | K4: EBITDA margin | L4: Rev growth FY1/FY0 | M4: EV / Revenue | N4: EV / EBITDA | O4: EV / EBIT | P4: P / E (LTM) | Q4: CY revenue (cal.) | R4: CY EPS (cal., local) | S4: EV / CY revenue | T4: P / E (CY)
B5: =Data!$B$5 -> Tata Consultancy Services | C5: =Data!$C$5 -> India large-cap | D5: =Data!$H$5*IF(Data!$D$5="INR",Inputs!$C$5,1) -> 83345.445 | E5: =(Data!$I$5+Data!$K$5-Data!$J$5)*IF(Data!$E$5="INR",Inputs!$C$5,1) -> -3019.9388 | F5: =D5+E5 -> 80325.506 | G5: =Data!$L$5*IF(Data!$E$5="INR",Inputs!$C$5,1) -> 28626.931 | H5: =Data!$M$5*IF(Data!$E$5="INR",Inputs!$C$5,1) -> 7747.6734 | I5: =Data!$N$5*IF(Data!$E$5="INR",Inputs!$C$5,1) -> 7183.9208 | J5: =Data!$O$5*IF(Data!$E$5="INR",Inputs!$C$5,1) -> 5284.1603 | K5: =H5/G5 -> 0.27064282 | L5: =Data!$S$5/Data!$R$5-1 -> 0.044204182 | M5: =F5/G5 -> 2.8059419 | N5: =F5/H5 -> 10.367694 | O5: =F5/I5 -> 11.181291 | P5: =D5/J5 -> 15.772694 | Q5: =(MAX(0,MIN(DATEVALUE(Data!$Q$5),DATEVALUE(Inputs!$C$9))-DATEVALUE(Inputs!$C$8)+1)/365*Data!$R$5+(1-MAX(0,MIN(DATEVALUE(Data!$Q$5),DATEVALUE(Inputs!$C$9))-DATEVALUE(Inputs!$C$8)+1)/365)*Data!$S$5)*IF(Data!$D$5="INR",Inputs!$C$5,1) -> 30454.84 | R5: =MAX(0,MIN(DATEVALUE(Data!$Q$5),DATEVALUE(Inputs!$C$9))-DATEVALUE(Inputs!$C$8)+1)/365*Data!$T$5+(1-MAX(0,MIN(DATEVALUE(Data!$Q$5),DATEVALUE(Inputs!$C$9))-DATEVALUE(Inputs!$C$8)+1)/365)*Data!$U$5 -> 155.08232 | S5: =F5/Q5 -> 2.6375284 | T5: =Data!$F$5/R5 -> 14.191173
B6: =Data!$B$6 -> Infosys | C6: =Data!$C$6 -> India large-cap | D6: =Data!$H$6*IF(Data!$D$6="INR",Inputs!$C$5,1) -> 43992.756 | E6: =(Data!$I$6+Data!$K$6-Data!$J$6)*IF(Data!$E$6="INR",Inputs!$C$5,1) -> -2196 | F6: =D6+E6 -> 41796.756 | G6: =Data!$L$6*IF(Data!$E$6="INR",Inputs!$C$5,1) -> 20297 | H6: =Data!$M$6*IF(Data!$E$6="INR",Inputs!$C$5,1) -> 5129 | I6: =Data!$N$6*IF(Data!$E$6="INR",Inputs!$C$5,1) -> 4579 | J6: =Data!$O$6*IF(Data!$E$6="INR",Inputs!$C$5,1) -> 3324 | K6: =H6/G6 -> 0.25269744 | L6: =Data!$S$6/Data!$R$6-1 -> 0.037888032 | M6: =F6/G6 -> 2.0592578 | N6: =F6/H6 -> 8.1491044 | O6: =F6/I6 -> 9.1279223 | P6: =D6/J6 -> 13.234885 | Q6: =(MAX(0,MIN(DATEVALUE(Data!$Q$6),DATEVALUE(Inputs!$C$9))-DATEVALUE(Inputs!$C$8)+1)/365*Data!$R$6+(1-MAX(0,MIN(DATEVALUE(Data!$Q$6),DATEVALUE(Inputs!$C$9))-DATEVALUE(Inputs!$C$8)+1)/365)*Data!$S$6)*IF(Data!$D$6="INR",Inputs!$C$5,1) -> 20395.944 | R6: =MAX(0,MIN(DATEVALUE(Data!$Q$6),DATEVALUE(Inputs!$C$9))-DATEVALUE(Inputs!$C$8)+1)/365*Data!$T$6+(1-MAX(0,MIN(DATEVALUE(Data!$Q$6),DATEVALUE(Inputs!$C$9))-DATEVALUE(Inputs!$C$8)+1)/365)*Data!$U$6 -> 76.47616 | S6: =F6/Q6 -> 2.049268 | T6: =Data!$F$6/R6 -> 13.568934
B7: =Data!$B$7 -> HCL Technologies | C7: =Data!$C$7 -> India large-cap | D7: =Data!$H$7*IF(Data!$D$7="INR",Inputs!$C$5,1) -> 34158.272 | E7: =(Data!$I$7+Data!$K$7-Data!$J$7)*IF(Data!$E$7="INR",Inputs!$C$5,1) -> -2655.2686 | F7: =D7+E7 -> 31503.003 | G7: =Data!$L$7*IF(Data!$E$7="INR",Inputs!$C$5,1) -> 13898.187 | H7: =Data!$M$7*IF(Data!$E$7="INR",Inputs!$C$5,1) -> 2888.578 | I7: =Data!$N$7*IF(Data!$E$7="INR",Inputs!$C$5,1) -> 2433.1588 | J7: =Data!$O$7*IF(Data!$E$7="INR",Inputs!$C$5,1) -> 1782.6348 | K7: =H7/G7 -> 0.20783847 | L7: =Data!$S$7/Data!$R$7-1 -> 0.060253011 | M7: =F7/G7 -> 2.2666987 | N7: =F7/H7 -> 10.906059 | O7: =F7/I7 -> 12.947368 | P7: =D7/J7 -> 19.161677 | Q7: =(MAX(0,MIN(DATEVALUE(Data!$Q$7),DATEVALUE(Inputs!$C$9))-DATEVALUE(Inputs!$C$8)+1)/365*Data!$R$7+(1-MAX(0,MIN(DATEVALUE(Data!$Q$7),DATEVALUE(Inputs!$C$9))-DATEVALUE(Inputs!$C$8)+1)/365)*Data!$S$7)*IF(Data!$D$7="INR",Inputs!$C$5,1) -> 14893.451 | R7: =MAX(0,MIN(DATEVALUE(Data!$Q$7),DATEVALUE(Inputs!$C$9))-DATEVALUE(Inputs!$C$8)+1)/365*Data!$T$7+(1-MAX(0,MIN(DATEVALUE(Data!$Q$7),DATEVALUE(Inputs!$C$9))-DATEVALUE(Inputs!$C$8)+1)/365)*Data!$U$7 -> 73.22011 | S7: =F7/Q7 -> 2.1152252 | T7: =Data!$F$7/R7 -> 16.472251
B8: =Data!$B$8 -> Wipro | C8: =Data!$C$8 -> India large-cap | D8: =Data!$H$8*IF(Data!$D$8="INR",Inputs!$C$5,1) -> 17334.328 | E8: =(Data!$I$8+Data!$K$8-Data!$J$8)*IF(Data!$E$8="INR",Inputs!$C$5,1) -> -1890.5286 | F8: =D8+E8 -> 15443.799 | G8: =Data!$L$8*IF(Data!$E$8="INR",Inputs!$C$5,1) -> 9940.3006 | H8: =Data!$M$8*IF(Data!$E$8="INR",Inputs!$C$5,1) -> 2224.9911 | I8: =Data!$N$8*IF(Data!$E$8="INR",Inputs!$C$5,1) -> 1907.8829 | J8: =Data!$O$8*IF(Data!$E$8="INR",Inputs!$C$5,1) -> 1383.6327 | K8: =H8/G8 -> 0.2238354 | L8: =Data!$S$8/Data!$R$8-1 -> 0.030298363 | M8: =F8/G8 -> 1.5536551 | N8: =F8/H8 -> 6.9410609 | O8: =F8/I8 -> 8.0947311 | P8: =D8/J8 -> 12.528128 | Q8: =(MAX(0,MIN(DATEVALUE(Data!$Q$8),DATEVALUE(Inputs!$C$9))-DATEVALUE(Inputs!$C$8)+1)/365*Data!$R$8+(1-MAX(0,MIN(DATEVALUE(Data!$Q$8),DATEVALUE(Inputs!$C$9))-DATEVALUE(Inputs!$C$8)+1)/365)*Data!$S$8)*IF(Data!$D$8="INR",Inputs!$C$5,1) -> 10336.581 | R8: =MAX(0,MIN(DATEVALUE(Data!$Q$8),DATEVALUE(Inputs!$C$9))-DATEVALUE(Inputs!$C$8)+1)/365*Data!$T$8+(1-MAX(0,MIN(DATEVALUE(Data!$Q$8),DATEVALUE(Inputs!$C$9))-DATEVALUE(Inputs!$C$8)+1)/365)*Data!$U$8 -> 13.31437 | S8: =F8/Q8 -> 1.4940915 | T8: =Data!$F$8/R8 -> 12.572882
B9: =Data!$B$9 -> Tech Mahindra | C9: =Data!$C$9 -> India mid-cap | D9: =Data!$H$9*IF(Data!$D$9="INR",Inputs!$C$5,1) -> 14289.224 | E9: =(Data!$I$9+Data!$K$9-Data!$J$9)*IF(Data!$E$9="INR",Inputs!$C$5,1) -> -604.75186 | F9: =D9+E9 -> 13684.472 | G9: =Data!$L$9*IF(Data!$E$9="INR",Inputs!$C$5,1) -> 6126.5863 | H9: =Data!$M$9*IF(Data!$E$9="INR",Inputs!$C$5,1) -> 964.92133 | I9: =Data!$N$9*IF(Data!$E$9="INR",Inputs!$C$5,1) -> 766.93802 | J9: =Data!$O$9*IF(Data!$E$9="INR",Inputs!$C$5,1) -> 531.8806 | K9: =H9/G9 -> 0.15749739 | L9: =Data!$S$9/Data!$R$9-1 -> 0.056044562 | M9: =F9/G9 -> 2.2336211 | N9: =F9/H9 -> 14.181956 | O9: =F9/I9 -> 17.842996 | P9: =D9/J9 -> 26.865473 | Q9: =(MAX(0,MIN(DATEVALUE(Data!$Q$9),DATEVALUE(Inputs!$C$9))-DATEVALUE(Inputs!$C$8)+1)/365*Data!$R$9+(1-MAX(0,MIN(DATEVALUE(Data!$Q$9),DATEVALUE(Inputs!$C$9))-DATEVALUE(Inputs!$C$8)+1)/365)*Data!$S$9)*IF(Data!$D$9="INR",Inputs!$C$5,1) -> 6654.4373 | R9: =MAX(0,MIN(DATEVALUE(Data!$Q$9),DATEVALUE(Inputs!$C$9))-DATEVALUE(Inputs!$C$8)+1)/365*Data!$T$9+(1-MAX(0,MIN(DATEVALUE(Data!$Q$9),DATEVALUE(Inputs!$C$9))-DATEVALUE(Inputs!$C$8)+1)/365)*Data!$U$9 -> 77.28786 | S9: =F9/Q9 -> 2.0564432 | T9: =Data!$F$9/R9 -> 19.938448
B10: =Data!$B$10 -> Persistent Systems | C10: =Data!$C$10 -> India mid-cap | D10: =Data!$H$10*IF(Data!$D$10="INR",Inputs!$C$5,1) -> 9020.1512 | E10: =(Data!$I$10+Data!$K$10-Data!$J$10)*IF(Data!$E$10="INR",Inputs!$C$5,1) -> -162.02832 | F10: =D10+E10 -> 8858.1229 | G10: =Data!$L$10*IF(Data!$E$10="INR",Inputs!$C$5,1) -> 1619.345 | H10: =Data!$M$10*IF(Data!$E$10="INR",Inputs!$C$5,1) -> 305.58584 | I10: =Data!$N$10*IF(Data!$E$10="INR",Inputs!$C$5,1) -> 261.8139 | J10: =Data!$O$10*IF(Data!$E$10="INR",Inputs!$C$5,1) -> 196.43346 | K10: =H10/G10 -> 0.18870954 | L10: =Data!$S$10/Data!$R$10-1 -> 0.15646766 | M10: =F10/G10 -> 5.4701889 | N10: =F10/H10 -> 28.987347 | O10: =F10/I10 -> 33.833662 | P10: =D10/J10 -> 45.919628 | Q10: =(MAX(0,MIN(DATEVALUE(Data!$Q$10),DATEVALUE(Inputs!$C$9))-DATEVALUE(Inputs!$C$8)+1)/365*Data!$R$10+(1-MAX(0,MIN(DATEVALUE(Data!$Q$10),DATEVALUE(Inputs!$C$9))-DATEVALUE(Inputs!$C$8)+1)/365)*Data!$S$10)*IF(Data!$D$10="INR",Inputs!$C$5,1) -> 1925.9117 | R10: =MAX(0,MIN(DATEVALUE(Data!$Q$10),DATEVALUE(Inputs!$C$9))-DATEVALUE(Inputs!$C$8)+1)/365*Data!$T$10+(1-MAX(0,MIN(DATEVALUE(Data!$Q$10),DATEVALUE(Inputs!$C$9))-DATEVALUE(Inputs!$C$8)+1)/365)*Data!$U$10 -> 144.30505 | S10: =F10/Q10 -> 4.599444 | T10: =Data!$F$10/R10 -> 38.22458
B11: =Data!$B$11 -> Accenture | C11: =Data!$C$11 -> Global | D11: =Data!$H$11*IF(Data!$D$11="INR",Inputs!$C$5,1) -> 115412.29 | E11: =(Data!$I$11+Data!$K$11-Data!$J$11)*IF(Data!$E$11="INR",Inputs!$C$5,1) -> -165.65 | F11: =D11+E11 -> 115246.64 | G11: =Data!$L$11*IF(Data!$E$11="INR",Inputs!$C$5,1) -> 73100.595 | H11: =Data!$M$11*IF(Data!$E$11="INR",Inputs!$C$5,1) -> 12330.716 | I11: =Data!$N$11*IF(Data!$E$11="INR",Inputs!$C$5,1) -> 10915.206 | J11: =Data!$O$11*IF(Data!$E$11="INR",Inputs!$C$5,1) -> 7789.752 | K11: =H11/G11 -> 0.16868147 | L11: =Data!$S$11/Data!$R$11-1 -> 0.0410878 | M11: =F11/G11 -> 1.5765485 | N11: =F11/H11 -> 9.3463052 | O11: =F11/I11 -> 10.558356 | P11: =D11/J11 -> 14.815913 | Q11: =(MAX(0,MIN(DATEVALUE(Data!$Q$11),DATEVALUE(Inputs!$C$9))-DATEVALUE(Inputs!$C$8)+1)/365*Data!$R$11+(1-MAX(0,MIN(DATEVALUE(Data!$Q$11),DATEVALUE(Inputs!$C$9))-DATEVALUE(Inputs!$C$8)+1)/365)*Data!$S$11)*IF(Data!$D$11="INR",Inputs!$C$5,1) -> 75321.863 | R11: =MAX(0,MIN(DATEVALUE(Data!$Q$11),DATEVALUE(Inputs!$C$9))-DATEVALUE(Inputs!$C$8)+1)/365*Data!$T$11+(1-MAX(0,MIN(DATEVALUE(Data!$Q$11),DATEVALUE(Inputs!$C$9))-DATEVALUE(Inputs!$C$8)+1)/365)*Data!$U$11 -> 14.336482 | S11: =F11/Q11 -> 1.5300556 | T11: =Data!$F$11/R11 -> 13.15525
B12: =Data!$B$12 -> Cognizant | C12: =Data!$C$12 -> Global | D12: =Data!$H$12*IF(Data!$D$12="INR",Inputs!$C$5,1) -> 28130.241 | E12: =(Data!$I$12+Data!$K$12-Data!$J$12)*IF(Data!$E$12="INR",Inputs!$C$5,1) -> 1043 | F12: =D12+E12 -> 29173.241 | G12: =Data!$L$12*IF(Data!$E$12="INR",Inputs!$C$5,1) -> 21642 | H12: =Data!$M$12*IF(Data!$E$12="INR",Inputs!$C$5,1) -> 4102 | I12: =Data!$N$12*IF(Data!$E$12="INR",Inputs!$C$5,1) -> 3543 | J12: =Data!$O$12*IF(Data!$E$12="INR",Inputs!$C$5,1) -> 2220 | K12: =H12/G12 -> 0.18953886 | L12: =Data!$S$12/Data!$R$12-1 -> 0.047640369 | M12: =F12/G12 -> 1.3479919 | N12: =F12/H12 -> 7.1119554 | O12: =F12/I12 -> 8.2340506 | P12: =D12/J12 -> 12.67128 | Q12: =(MAX(0,MIN(DATEVALUE(Data!$Q$12),DATEVALUE(Inputs!$C$9))-DATEVALUE(Inputs!$C$8)+1)/365*Data!$R$12+(1-MAX(0,MIN(DATEVALUE(Data!$Q$12),DATEVALUE(Inputs!$C$9))-DATEVALUE(Inputs!$C$8)+1)/365)*Data!$S$12)*IF(Data!$D$12="INR",Inputs!$C$5,1) -> 22457.437 | R12: =MAX(0,MIN(DATEVALUE(Data!$Q$12),DATEVALUE(Inputs!$C$9))-DATEVALUE(Inputs!$C$8)+1)/365*Data!$T$12+(1-MAX(0,MIN(DATEVALUE(Data!$Q$12),DATEVALUE(Inputs!$C$9))-DATEVALUE(Inputs!$C$8)+1)/365)*Data!$U$12 -> 5.8804614 | S12: =F12/Q12 -> 1.2990459 | T12: =Data!$F$12/R12 -> 10.619915
B13: =Data!$B$13 -> EPAM Systems | C13: =Data!$C$13 -> Global | D13: =Data!$H$13*IF(Data!$D$13="INR",Inputs!$C$5,1) -> 6312.183 | E13: =(Data!$I$13+Data!$K$13-Data!$J$13)*IF(Data!$E$13="INR",Inputs!$C$5,1) -> -636.572 | F13: =D13+E13 -> 5675.611 | G13: =Data!$L$13*IF(Data!$E$13="INR",Inputs!$C$5,1) -> 5616.749 | H13: =Data!$M$13*IF(Data!$E$13="INR",Inputs!$C$5,1) -> 720.483 | I13: =Data!$N$13*IF(Data!$E$13="INR",Inputs!$C$5,1) -> 553.337 | J13: =Data!$O$13*IF(Data!$E$13="INR",Inputs!$C$5,1) -> 401.67 | K13: =H13/G13 -> 0.12827402 | L13: =Data!$S$13/Data!$R$13-1 -> 0.035497295 | M13: =F13/G13 -> 1.0104797 | N13: =F13/H13 -> 7.8775086 | O13: =F13/I13 -> 10.25706 | P13: =D13/J13 -> 15.714848 | Q13: =(MAX(0,MIN(DATEVALUE(Data!$Q$13),DATEVALUE(Inputs!$C$9))-DATEVALUE(Inputs!$C$8)+1)/365*Data!$R$13+(1-MAX(0,MIN(DATEVALUE(Data!$Q$13),DATEVALUE(Inputs!$C$9))-DATEVALUE(Inputs!$C$8)+1)/365)*Data!$S$13)*IF(Data!$D$13="INR",Inputs!$C$5,1) -> 5706.4596 | R13: =MAX(0,MIN(DATEVALUE(Data!$Q$13),DATEVALUE(Inputs!$C$9))-DATEVALUE(Inputs!$C$8)+1)/365*Data!$T$13+(1-MAX(0,MIN(DATEVALUE(Data!$Q$13),DATEVALUE(Inputs!$C$9))-DATEVALUE(Inputs!$C$8)+1)/365)*Data!$U$13 -> 13.375506 | S13: =F13/Q13 -> 0.9945941 | T13: =Data!$F$13/R13 -> 9.1480649
B15: PEER STATISTICS (excluding the target and names under the market-cap floor)
B16: Maximum | K16: =MAX(K6,K7,K8,K9,K10,K11,K12,K13) -> 0.25269744 | L16: =MAX(L6,L7,L8,L9,L10,L11,L12,L13) -> 0.15646766 | M16: =MAX(M6,M7,M8,M9,M10,M11,M12,M13) -> 5.4701889 | N16: =MAX(N6,N7,N8,N9,N10,N11,N12,N13) -> 28.987347 | O16: =MAX(O6,O7,O8,O9,O10,O11,O12,O13) -> 33.833662 | P16: =MAX(P6,P7,P8,P9,P10,P11,P12,P13) -> 45.919628 | Q16: =MAX(Q6,Q7,Q8,Q9,Q10,Q11,Q12,Q13) -> 75321.863 | R16: =MAX(R6,R7,R8,R9,R10,R11,R12,R13) -> 144.30505 | ... T16: =MAX(T6,T7,T8,T9,T10,T11,T12,T13) -> 38.22458
B17: 75th percentile | K17: =PERCENTILE((K6~K7~K8~K9~K10~K11~K12~K13),0.75) -> 0.2118377 | L17: =PERCENTILE((L6~L7~L8~L9~L10~L11~L12~L13),0.75) -> 0.057096674 | M17: =PERCENTILE((M6~M7~M8~M9~M10~M11~M12~M13),0.75) -> 2.2418905 | N17: =PERCENTILE((N6~N7~N8~N9~N10~N11~N12~N13),0.75) -> 11.725034 | O17: =PERCENTILE((O6~O7~O8~O9~O10~O11~O12~O13),0.75) -> 14.171275 | P17: =PERCENTILE((P6~P7~P8~P9~P10~P11~P12~P13),0.75) -> 21.087626 | Q17: =PERCENTILE((Q6~Q7~Q8~Q9~Q10~Q11~Q12~Q13),0.75) -> 20911.317 | R17: =PERCENTILE((R6~R7~R8~R9~R10~R11~R12~R13),0.75) -> 76.679085 | ... T17: =PERCENTILE((T6~T7~T8~T9~T10~T11~T12~T13),0.75) -> 17.3388
B18: Median | K18: =MEDIAN(K6,K7,K8,K9,K10,K11,K12,K13) -> 0.1891242 | L18: =MEDIAN(L6,L7,L8,L9,L10,L11,L12,L13) -> 0.044364084 | M18: =MEDIAN(M6,M7,M8,M9,M10,M11,M12,M13) -> 1.8179032 | N18: =MEDIAN(N6,N7,N8,N9,N10,N11,N12,N13) -> 8.7477048 | O18: =MEDIAN(O6,O7,O8,O9,O10,O11,O12,O13) -> 10.407708 | P18: =MEDIAN(P6,P7,P8,P9,P10,P11,P12,P13) -> 15.26538 | Q18: =MEDIAN(Q6,Q7,Q8,Q9,Q10,Q11,Q12,Q13) -> 12615.016 | R18: =MEDIAN(R6,R7,R8,R9,R10,R11,R12,R13) -> 43.778296 | ... T18: =MEDIAN(T6,T7,T8,T9,T10,T11,T12,T13) -> 13.362092
B19: Mean | K19: =AVERAGE(K6,K7,K8,K9,K10,K11,K12,K13) -> 0.18963407 | L19: =AVERAGE(L6,L7,L8,L9,L10,L11,L12,L13) -> 0.058147136 | M19: =AVERAGE(M6,M7,M8,M9,M10,M11,M12,M13) -> 2.1898052 | N19: =AVERAGE(N6,N7,N8,N9,N10,N11,N12,N13) -> 11.687662 | O19: =AVERAGE(O6,O7,O8,O9,O10,O11,O12,O13) -> 13.862018 | P19: =AVERAGE(P6,P7,P8,P9,P10,P11,P12,P13) -> 20.113979 | Q19: =AVERAGE(Q6,Q7,Q8,Q9,Q10,Q11,Q12,Q13) -> 19711.511 | R19: =AVERAGE(R6,R7,R8,R9,R10,R11,R12,R13) -> 52.2745 | ... T19: =AVERAGE(T6,T7,T8,T9,T10,T11,T12,T13) -> 16.712541
B20: 25th percentile | K20: =PERCENTILE((K6~K7~K8~K9~K10~K11~K12~K13),0.25) -> 0.16588545 | L20: =PERCENTILE((L6~L7~L8~L9~L10~L11~L12~L13),0.25) -> 0.037290348 | M20: =PERCENTILE((M6~M7~M8~M9~M10~M11~M12~M13),0.25) -> 1.5022393 | N20: =PERCENTILE((N6~N7~N8~N9~N10~N11~N12~N13),0.25) -> 7.6861203 | O20: =PERCENTILE((O6~O7~O8~O9~O10~O11~O12~O13),0.25) -> 8.9044544 | P20: =PERCENTILE((P6~P7~P8~P9~P10~P11~P12~P13),0.25) -> 13.093983 | Q20: =PERCENTILE((Q6~Q7~Q8~Q9~Q10~Q11~Q12~Q13),0.25) -> 6417.4428 | R20: =PERCENTILE((R6~R7~R8~R9~R10~R11~R12~R13),0.25) -> 13.360222 | ... T20: =PERCENTILE((T6~T7~T8~T9~T10~T11~T12~T13),0.25) -> 12.08464
B21: Minimum | K21: =MIN(K6,K7,K8,K9,K10,K11,K12,K13) -> 0.12827402 | L21: =MIN(L6,L7,L8,L9,L10,L11,L12,L13) -> 0.030298363 | M21: =MIN(M6,M7,M8,M9,M10,M11,M12,M13) -> 1.0104797 | N21: =MIN(N6,N7,N8,N9,N10,N11,N12,N13) -> 6.9410609 | O21: =MIN(O6,O7,O8,O9,O10,O11,O12,O13) -> 8.0947311 | P21: =MIN(P6,P7,P8,P9,P10,P11,P12,P13) -> 12.528128 | Q21: =MIN(Q6,Q7,Q8,Q9,Q10,Q11,Q12,Q13) -> 1925.9117 | R21: =MIN(R6,R7,R8,R9,R10,R11,R12,R13) -> 5.8804614 | ... T21: =MIN(T6,T7,T8,T9,T10,T11,T12,T13) -> 9.1480649
B22: Statistics are computed over the eight peers only (the target's row is outside the range by construction). All eight clear the US$5bn market-cap floor on the Inputs sheet, so the floor is not binding in this run; drop a name from the peer list to exclude it.
B24: TARGET vs PEER MEDIAN
B25: TCS | K25: =K5 -> 0.27064282 | L25: =L5 -> 0.044204182 | M25: =M5 -> 2.8059419 | N25: =N5 -> 10.367694 | O25: =O5 -> 11.181291 | P25: =P5 -> 15.772694 | Q25: =Q5 -> 30454.84 | R25: =R5 -> 155.08232 | ... T25: =T5 -> 14.191173
B26: Premium / (discount) to median | K26: =K5/K18-1 -> 0.43103221 | L26: =L5/L18-1 -> -0.003604319 | M26: =M5/M18-1 -> 0.5435046 | N26: =N5/N18-1 -> 0.18519019 | O26: =O5/O18-1 -> 0.074327814 | P26: =P5/P18-1 -> 0.033232972 | Q26: =Q5/Q18-1 -> 1.4141737 | R26: =R5/R18-1 -> 2.5424476 | ... T26: =T5/T18-1 -> 0.062047221

Sheet Calendarisation
B1: Tata Consultancy Services — Trading Comparables | H1: TATA CONSULTANCY SERVICES
B2: Why a March-year company cannot be compared to a December-year company without adjustment
B4: METHOD
B5: Consensus estimates are quoted for each company's own fiscal year. To compare TCS (year to 31 March) with Cognizant (year to 31 December) on a forward multiple, both must be expressed over the same twelve months. This workbook calendarises every peer to TCS's FY2027 (1 Apr 2026 – 31 Mar 2027): weight w0 on the consensus year that ends inside the window and (1 − w0) on the following year, where w0 = months of overlap / 12.
B7: Company | C7: Consensus FY0 ends | D7: Overlap with Apr-26 → Mar-27 (years) | E7: Weight on FY0 | F7: Weight on FY1 | G7: Revenue FY0 (local m) | H7: Revenue FY1 (local m) | I7: Calendarised revenue (local m)
B8: =Data!$B$5 -> Tata Consultancy Services | C8: =Data!$Q$5 -> 2027-03-31 | D8: =MAX(0,MIN(DATEVALUE(Data!$Q$5),DATEVALUE(Inputs!$C$9))-DATEVALUE(Inputs!$C$8)+1)/365 -> 1 | E8: =D8 -> 1 | F8: =1-D8 -> 0 | G8: =Data!$R$5 -> 2909605.5 | H8: =Data!$S$5 -> 3038222.2 | I8: =E8*G8+F8*H8 -> 2909605.5
B9: =Data!$B$6 -> Infosys | C9: =Data!$Q$6 -> 2027-03-31 | D9: =MAX(0,MIN(DATEVALUE(Data!$Q$6),DATEVALUE(Inputs!$C$9))-DATEVALUE(Inputs!$C$8)+1)/365 -> 1 | E9: =D9 -> 1 | F9: =1-D9 -> 0 | G9: =Data!$R$6 -> 1948595 | H9: =Data!$S$6 -> 2022423.5 | I9: =E9*G9+F9*H9 -> 1948595
B10: =Data!$B$7 -> HCL Technologies | C10: =Data!$Q$7 -> 2027-03-31 | D10: =MAX(0,MIN(DATEVALUE(Data!$Q$7),DATEVALUE(Inputs!$C$9))-DATEVALUE(Inputs!$C$8)+1)/365 -> 1 | E10: =D10 -> 1 | F10: =1-D10 -> 0 | G10: =Data!$R$7 -> 1422895.9 | H10: =Data!$S$7 -> 1508629.6 | I10: =E10*G10+F10*H10 -> 1422895.9
B11: =Data!$B$8 -> Wipro | C11: =Data!$Q$8 -> 2027-03-31 | D11: =MAX(0,MIN(DATEVALUE(Data!$Q$8),DATEVALUE(Inputs!$C$9))-DATEVALUE(Inputs!$C$8)+1)/365 -> 1 | E11: =D11 -> 1 | F11: =1-D11 -> 0 | G11: =Data!$R$8 -> 987540.03 | H11: =Data!$S$8 -> 1017460.9 | I11: =E11*G11+F11*H11 -> 987540.03
B12: =Data!$B$9 -> Tech Mahindra | C12: =Data!$Q$9 -> 2027-03-31 | D12: =MAX(0,MIN(DATEVALUE(Data!$Q$9),DATEVALUE(Inputs!$C$9))-DATEVALUE(Inputs!$C$8)+1)/365 -> 1 | E12: =D12 -> 1 | F12: =1-D12 -> 0 | G12: =Data!$R$9 -> 635754.01 | H12: =Data!$S$9 -> 671384.57 | I12: =E12*G12+F12*H12 -> 635754.01
B13: =Data!$B$10 -> Persistent Systems | C13: =Data!$Q$10 -> 2027-03-31 | D13: =MAX(0,MIN(DATEVALUE(Data!$Q$10),DATEVALUE(Inputs!$C$9))-DATEVALUE(Inputs!$C$8)+1)/365 -> 1 | E13: =D13 -> 1 | F13: =1-D13 -> 0 | G13: =Data!$R$10 -> 183998.44 | H13: =Data!$S$10 -> 212788.25 | I13: =E13*G13+F13*H13 -> 183998.44
B14: =Data!$B$11 -> Accenture | C14: =Data!$Q$11 -> 2026-08-31 | D14: =MAX(0,MIN(DATEVALUE(Data!$Q$11),DATEVALUE(Inputs!$C$9))-DATEVALUE(Inputs!$C$8)+1)/365 -> 0.41917808 | E14: =D14 -> 0.41917808 | F14: =1-D14 -> 0.58082192 | G14: =Data!$R$11 -> 73566.228 | H14: =Data!$S$11 -> 76588.902 | I14: =E14*G14+F14*H14 -> 75321.863
B15: =Data!$B$12 -> Cognizant | C15: =Data!$Q$12 -> 2026-12-31 | D15: =MAX(0,MIN(DATEVALUE(Data!$Q$12),DATEVALUE(Inputs!$C$9))-DATEVALUE(Inputs!$C$8)+1)/365 -> 0.75342466 | E15: =D15 -> 0.75342466 | F15: =1-D15 -> 0.24657534 | G15: =Data!$R$12 -> 22196.694 | H15: =Data!$S$12 -> 23254.152 | I15: =E15*G15+F15*H15 -> 22457.437
B16: =Data!$B$13 -> EPAM Systems | C16: =Data!$Q$13 -> 2026-12-31 | D16: =MAX(0,MIN(DATEVALUE(Data!$Q$13),DATEVALUE(Inputs!$C$9))-DATEVALUE(Inputs!$C$8)+1)/365 -> 0.75342466 | E16: =D16 -> 0.75342466 | F16: =1-D16 -> 0.24657534 | G16: =Data!$R$13 -> 5656.9457 | H16: =Data!$S$13 -> 5857.752 | I16: =E16*G16+F16*H16 -> 5706.4596
B18: Reading: an Indian peer's FY0 already coincides with the window (weight 1.0). Cognizant's calendar 2026 covers nine of the twelve months (weight 0.75). Accenture's year to August 2026 covers five months (weight 0.42), so most of its calendarised figure comes from FY2027. Without this step Accenture would be compared on a period ending seven months earlier than TCS's.

Sheet Checks
B1: Tata Consultancy Services — Trading Comparables | D1: TATA CONSULTANCY SERVICES
B2: Integrity checks · should all be TRUE
B4: Every peer's EV is positive | C4: =MIN(Comps!F5:F13)>0 -> TRUE
B5: Infosys statements detected as US$ (revenue in US$ ≈ 20bn, not 20m) | C5: =AND(Comps!G6>15000,Comps!G6<30000) -> TRUE
B6: Calendarisation weights lie between 0 and 1 | C6: =AND(MIN(Calendarisation!D8:D16)>=0,MAX(Calendarisation!D8:D16)<=1) -> TRUE
B7: TCS EV/EBITDA within a plausible band (10x–40x) | C7: =AND(Comps!N5>10,Comps!N5<40) -> TRUE
B8: Implied price range is ordered (25th ≤ median ≤ 75th) for EV/EBITDA | C8: =AND(Summary!G19<=Summary!H19,Summary!H19<=Summary!I19) -> TRUE
B10: OVERALL | C10: =IF(COUNTIF(C4:C8,FALSE())=0,"MODEL OK","CHECK ERRORS") -> MODEL OK
